Workbook

Sheet 封皮
A2: 研 发 费 辅 助 账
A5: 二〇二五年度
A8: 公司名称:

Sheet 立项
A2: 序号 | B2: 项目名称 | C2: 研发周期 | D2: 人员人工 | E2: 直接投入 | F2: 折旧费用 | G2: 其他费用 | H2: 合计 | I2: 研发人员
A3: RD01 | D3: ='人员人工-研发人员工资'!H475+'人员人工-研发人员社保'!H475+'人员人工-研发人员公积金'!H475 -> 0 | E3: ='直接投入-领料'!B4+'直接投入-动力'!H30 -> 0 | F3: =RD01!I114 -> 0 | G3: =其他费用!B15 -> 0 | H3: =SUM(D3:G3) -> 0
A4: RD02 | D4: ='人员人工-研发人员工资'!J475+'人员人工-研发人员社保'!J475+'人员人工-研发人员公积金'!J475 -> 0 | E4: ='直接投入-领料'!B5+'直接投入-动力'!I30 -> 0 | F4: =RD02!I114 -> 0 | G4: =其他费用!C15 -> 0 | H4: =SUM(D4:G4) -> 0
A5: RD03 | D5: ='人员人工-研发人员工资'!L475+'人员人工-研发人员社保'!L475+'人员人工-研发人员公积金'!L475 -> 0 | E5: ='直接投入-领料'!B6+'直接投入-动力'!J30 -> 0 | F5: =RD03!I114 -> 0 | G5: =其他费用!D15 -> 0 | H5: =SUM(D5:G5) -> 0
A6: RD04 | D6: ='人员人工-研发人员工资'!N475+'人员人工-研发人员社保'!N475+'人员人工-研发人员公积金'!N475 -> 0 | E6: ='直接投入-领料'!B7+'直接投入-动力'!K30 -> 0 | F6: =RD04!I114 -> 0 | G6: =其他费用!E15 -> 0 | H6: =SUM(D6:G6) -> 0
A7: RD05 | D7: ='人员人工-研发人员工资'!P475+'人员人工-研发人员社保'!P475+'人员人工-研发人员公积金'!P475 -> 0 | E7: ='直接投入-领料'!B8+'直接投入-动力'!L30 -> 0 | F7: =RD05!I114 -> 0 | G7: =其他费用!F15 -> 0 | H7: =SUM(D7:G7) -> 0
A8: RD06 | D8: ='人员人工-研发人员工资'!R475+'人员人工-研发人员社保'!R475+'人员人工-研发人员公积金'!R475 -> 0 | E8: ='直接投入-领料'!B9+'直接投入-动力'!M30 -> 0 | F8: =RD06!I114 -> 0 | G8: =其他费用!G15 -> 0 | H8: =SUM(D8:G8) -> 0
A9: RD07 | D9: ='人员人工-研发人员工资'!T475+'人员人工-研发人员社保'!T475+'人员人工-研发人员公积金'!T475 -> 0 | E9: ='直接投入-领料'!B10+'直接投入-动力'!N30 -> 0 | F9: =RD07!I114 -> 0 | G9: =其他费用!H15 -> 0 | H9: =SUM(D9:G9) -> 0
A10: RD08 | D10: ='人员人工-研发人员工资'!V475+'人员人工-研发人员社保'!V475+'人员人工-研发人员公积金'!V475 -> 0 | E10: ='直接投入-领料'!B11+'直接投入-动力'!O30 -> 0 | F10: =RD08!I114 -> 0 | G10: =其他费用!I15 -> 0 | H10: =SUM(D10:G10) -> 0
A11: RD09 | D11: ='人员人工-研发人员工资'!X475+'人员人工-研发人员社保'!X475+'人员人工-研发人员公积金'!X475 -> 0 | E11: ='直接投入-领料'!B12+'直接投入-动力'!P30 -> 0 | F11: =RD09!I114 -> 0 | G11: =其他费用!J15 -> 0 | H11: =SUM(D11:G11) -> 0
A12: RD10 | D12: ='人员人工-研发人员工资'!Z475+'人员人工-研发人员社保'!Z475+'人员人工-研发人员公积金'!Z475 -> 0 | E12: ='直接投入-领料'!B13+'直接投入-动力'!Q30 -> 0 | F12: =RD10!I114 -> 0 | G12: =其他费用!K15 -> 0 | H12: =SUM(D12:G12) -> 0
A13: 合计 | D13: =SUM(D3:D12) -> 0 | E13: =SUM(E3:E12) -> 0 | F13: =SUM(F3:F12) -> 0 | G13: =SUM(G3:G12) -> 0 | H13: =SUM(H3:H12) -> 0
F14: 营业收入
F15: 占比 | H15: =H13/H14 -> #DIV/0!
A16: 调账科目：工资--、社保--、公积金--、折旧--、动力--、材料--；调账金额最后一张表
A17: 附件：人员人工-研发人员工资中每月分摊表附计提工资凭证后，人员人工-研发人员社保中每月分摊表附计提社保凭证后，人员人工-研发人员公积金中每月分摊表附计提公积金凭证后，研发设备折旧表中每月研发折旧明细表附计提折旧凭证后，直接投入-动力中每月动力费分配表附计提电费凭证后，领料单打印版（最好买一式三联单据手写，该项目研发人员签字）附生产成本结转凭证后
A18: 汇算清缴107012表第一行填写此表中RD个数，第3行人员人工费用、第7行直接投入费用、第16行折旧费用、第28行其他费用按照上表合计数填写
A19: 辅助账打印：封皮、立项、各RD表带绿色标签
A20: 其他打印留存
D22: =ROUND(D3/10000,2) -> 0 | E22: =ROUND(E3/10000,2) -> 0 | F22: =ROUND(F3/10000,2) -> 0 | G22: =ROUND(G3/10000,2) -> 0 | H22: =ROUND(H3/10000,2) -> 0
D23: =ROUND(D4/10000,2) -> 0 | E23: =ROUND(E4/10000,2) -> 0 | F23: =ROUND(F4/10000,2) -> 0 | G23: =ROUND(G4/10000,2) -> 0 | H23: =ROUND(H4/10000,2) -> 0
D24: =ROUND(D5/10000,2) -> 0 | E24: =ROUND(E5/10000,2) -> 0 | F24: =ROUND(F5/10000,2) -> 0 | G24: =ROUND(G5/10000,2) -> 0 | H24: =ROUND(H5/10000,2) -> 0
D25: =ROUND(D6/10000,2) -> 0 | E25: =ROUND(E6/10000,2) -> 0 | F25: =ROUND(F6/10000,2) -> 0 | G25: =ROUND(G6/10000,2) -> 0 | H25: =ROUND(H6/10000,2) -> 0
D26: =ROUND(D7/10000,2) -> 0 | E26: =ROUND(E7/10000,2) -> 0 | F26: =ROUND(F7/10000,2) -> 0 | G26: =ROUND(G7/10000,2) -> 0 | H26: =ROUND(H7/10000,2) -> 0
D27: =ROUND(D8/10000,2) -> 0 | E27: =ROUND(E8/10000,2) -> 0 | F27: =ROUND(F8/10000,2) -> 0 | G27: =ROUND(G8/10000,2) -> 0 | H27: =ROUND(H8/10000,2) -> 0
D28: =ROUND(D9/10000,2) -> 0 | E28: =ROUND(E9/10000,2) -> 0 | F28: =ROUND(F9/10000,2) -> 0 | G28: =ROUND(G9/10000,2) -> 0 | H28: =ROUND(H9/10000,2) -> 0
D29: =ROUND(D10/10000,2) -> 0 | E29: =ROUND(E10/10000,2) -> 0 | F29: =ROUND(F10/10000,2) -> 0 | G29: =ROUND(G10/10000,2) -> 0 | H29: =ROUND(H10/10000,2) -> 0
D30: =ROUND(D11/10000,2) -> 0 | E30: =ROUND(E11/10000,2) -> 0 | F30: =ROUND(F11/10000,2) -> 0 | G30: =ROUND(G11/10000,2) -> 0 | H30: =ROUND(H11/10000,2) -> 0
D31: =ROUND(D12/10000,2) -> 0 | E31: =ROUND(E12/10000,2) -> 0 | F31: =ROUND(F12/10000,2) -> 0 | G31: =ROUND(G12/10000,2) -> 0 | H31: =ROUND(H12/10000,2) -> 0

Sheet 人员人工-研发人员工资
B1: 2025年1月份研发人员工资项目分摊表
A3: 序号 | B3: 姓名 | C3: 月工资 | D3: 出勤天数 | E3: 研发天数合计 | F3: 研发工资合计 | G3: =立项!$A$3 -> RD01 | I3: =立项!$A$4 -> RD02 | K3: =立项!$A$5 -> RD03 | M3: =立项!$A$6 -> RD04 | O3: =立项!$A$7 -> RD05 | Q3: =立项!$A$8 -> RD06 | S3: =立项!$A$9 -> RD07 | U3: =立项!$A$10 -> RD08 | W3: =立项!$A$11 -> RD09 | Y3: =立项!$A$12 -> RD10 | AA3: 核对公式 | AB3: 研发人员工资表
G4: =立项!C3 -> 0 | I4: =立项!C4 -> 0 | K4: =立项!C5 -> 0 | M4: =立项!C6 -> 0 | O4: =立项!C7 -> 0 | Q4: =立项!C8 -> 0 | S4: =立项!C9 -> 0 | U4: =立项!C10 -> 0 | W4: =立项!C11 -> 0 | Y4: =立项!C12 -> 0
G5: 研发天数 | H5: 研发工资 | I5: 研发天数 | J5: 研发工资 | K5: 研发天数 | L5: 研发工资 | M5: 研发天数 | N5: 研发工资 | O5: 研发天数 | P5: 研发工资 | Q5: 研发天数 | R5: 研发工资 | S5: 研发天数 | T5: 研发工资 | U5: 研发天数 | V5: 研发工资 | W5: 研发天数 | X5: 研发工资 | Y5: 研发天数 | Z5: 研发工资 | AB5: 姓名 | AC5: 1月 | AD5: 2月 | AE5: 3月 | AF5: 4月 | AG5: 5月 | AH5: 6月 | AI5: 7月 | AJ5: 8月 | AK5: 9月 | AL5: 10月 | AM5: 11月 | AN5: 12月 | AO5: 合计
A6: 1 | E6: =G6+I6+K6+M6+O6+Q6+S6+U6+W6+Y6 -> 0 | F6: =H6+J6+L6+N6+P6+R6+T6+V6+X6+Z6 -> 0 | H6: =IF($D6=0,0,ROUND(G6/$D6*$C6,2)) -> 0 | J6: =IF($D6=0,0,ROUND(I6/$D6*$C6,2)) -> 0 | L6: =IF($D6=0,0,ROUND(K6/$D6*$C6,2)) -> 0 | N6: =IF($D6=0,0,ROUND(M6/$D6*$C6,2)) -> 0 | P6: =IF($D6=0,0,ROUND(O6/$D6*$C6,2)) -> 0 | R6: =IF($D6=0,0,ROUND(Q6/$D6*$C6,2)) -> 0 | T6: =IF($D6=0,0,ROUND(S6/$D6*$C6,2)) -> 0 | V6: =IF($D6=0,0,ROUND(U6/$D6*$C6,2)) -> 0 | X6: =IF($D6=0,0,ROUND(W6/$D6*$C6,2)) -> 0 | Z6: =IF($D6=0,0,ROUND(Y6/$D6*$C6,2)) -> 0 | AA6: =D6-E6 -> 0 | AO6: =SUM(AC6:AN6) -> 0
A7: 2 | E7: =G7+I7+K7+M7+O7+Q7+S7+U7+W7+Y7 -> 0 | F7: =H7+J7+L7+N7+P7+R7+T7+V7+X7+Z7 -> 0 | H7: =IF($D7=0,0,ROUND(G7/$D7*$C7,2)) -> 0 | J7: =IF($D7=0,0,ROUND(I7/$D7*$C7,2)) -> 0 | L7: =IF($D7=0,0,ROUND(K7/$D7*$C7,2)) -> 0 | N7: =IF($D7=0,0,ROUND(M7/$D7*$C7,2)) -> 0 | P7: =IF($D7=0,0,ROUND(O7/$D7*$C7,2)) -> 0 | R7: =IF($D7=0,0,ROUND(Q7/$D7*$C7,2)) -> 0 | T7: =IF($D7=0,0,ROUND(S7/$D7*$C7,2)) -> 0 | V7: =IF($D7=0,0,ROUND(U7/$D7*$C7,2)) -> 0 | X7: =IF($D7=0,0,ROUND(W7/$D7*$C7,2)) -> 0 | Z7: =IF($D7=0,0,ROUND(Y7/$D7*$C7,2)) -> 0 | AA7: =D7-E7 -> 0 | AO7: =SUM(AC7:AN7) -> 0
A8: 3 | E8: =G8+I8+K8+M8+O8+Q8+S8+U8+W8+Y8 -> 0 | F8: =H8+J8+L8+N8+P8+R8+T8+V8+X8+Z8 -> 0 | H8: =IF($D8=0,0,ROUND(G8/$D8*$C8,2)) -> 0 | J8: =IF($D8=0,0,ROUND(I8/$D8*$C8,2)) -> 0 | L8: =IF($D8=0,0,ROUND(K8/$D8*$C8,2)) -> 0 | N8: =IF($D8=0,0,ROUND(M8/$D8*$C8,2)) -> 0 | P8: =IF($D8=0,0,ROUND(O8/$D8*$C8,2)) -> 0 | R8: =IF($D8=0,0,ROUND(Q8/$D8*$C8,2)) -> 0 | T8: =IF($D8=0,0,ROUND(S8/$D8*$C8,2)) -> 0 | V8: =IF($D8=0,0,ROUND(U8/$D8*$C8,2)) -> 0 | X8: =IF($D8=0,0,ROUND(W8/$D8*$C8,2)) -> 0 | Z8: =IF($D8=0,0,ROUND(Y8/$D8*$C8,2)) -> 0 | AA8: =D8-E8 -> 0 | AO8: =SUM(AC8:AN8) -> 0
A9: 4 | E9: =G9+I9+K9+M9+O9+Q9+S9+U9+W9+Y9 -> 0 | F9: =H9+J9+L9+N9+P9+R9+T9+V9+X9+Z9 -> 0 | H9: =IF($D9=0,0,ROUND(G9/$D9*$C9,2)) -> 0 | J9: =IF($D9=0,0,ROUND(I9/$D9*$C9,2)) -> 0 | L9: =IF($D9=0,0,ROUND(K9/$D9*$C9,2)) -> 0 | N9: =IF($D9=0,0,ROUND(M9/$D9*$C9,2)) -> 0 | P9: =IF($D9=0,0,ROUND(O9/$D9*$C9,2)) -> 0 | R9: =IF($D9=0,0,ROUND(Q9/$D9*$C9,2)) -> 0 | T9: =IF($D9=0,0,ROUND(S9/$D9*$C9,2)) -> 0 | V9: =IF($D9=0,0,ROUND(U9/$D9*$C9,2)) -> 0 | X9: =IF($D9=0,0,ROUND(W9/$D9*$C9,2)) -> 0 | Z9: =IF($D9=0,0,ROUND(Y9/$D9*$C9,2)) -> 0 | AA9: =D9-E9 -> 0 | AO9: =SUM(AC9:AN9) -> 0
A10: 5 | E10: =G10+I10+K10+M10+O10+Q10+S10+U10+W10+Y10 -> 0 | F10: =H10+J10+L10+N10+P10+R10+T10+V10+X10+Z10 -> 0 | H10: =IF($D10=0,0,ROUND(G10/$D10*$C10,2)) -> 0 | J10: =IF($D10=0,0,ROUND(I10/$D10*$C10,2)) -> 0 | L10: =IF($D10=0,0,ROUND(K10/$D10*$C10,2)) -> 0 | N10: =IF($D10=0,0,ROUND(M10/$D10*$C10,2)) -> 0 | P10: =IF($D10=0,0,ROUND(O10/$D10*$C10,2)) -> 0 | R10: =IF($D10=0,0,ROUND(Q10/$D10*$C10,2)) -> 0 | T10: =IF($D10=0,0,ROUND(S10/$D10*$C10,2)) -> 0 | V10: =IF($D10=0,0,ROUND(U10/$D10*$C10,2)) -> 0 | X10: =IF($D10=0,0,ROUND(W10/$D10*$C10,2)) -> 0 | Z10: =IF($D10=0,0,ROUND(Y10/$D10*$C10,2)) -> 0 | AA10: =D10-E10 -> 0 | AO10: =SUM(AC10:AN10) -> 0
A11: 6 | E11: =G11+I11+K11+M11+O11+Q11+S11+U11+W11+Y11 -> 0 | F11: =H11+J11+L11+N11+P11+R11+T11+V11+X11+Z11 -> 0 | H11: =IF($D11=0,0,ROUND(G11/$D11*$C11,2)) -> 0 | J11: =IF($D11=0,0,ROUND(I11/$D11*$C11,2)) -> 0 | L11: =IF($D11=0,0,ROUND(K11/$D11*$C11,2)) -> 0 | N11: =IF($D11=0,0,ROUND(M11/$D11*$C11,2)) -> 0 | P11: =IF($D11=0,0,ROUND(O11/$D11*$C11,2)) -> 0 | R11: =IF($D11=0,0,ROUND(Q11/$D11*$C11,2)) -> 0 | T11: =IF($D11=0,0,ROUND(S11/$D11*$C11,2)) -> 0 | V11: =IF($D11=0,0,ROUND(U11/$D11*$C11,2)) -> 0 | X11: =IF($D11=0,0,ROUND(W11/$D11*$C11,2)) -> 0 | Z11: =IF($D11=0,0,ROUND(Y11/$D11*$C11,2)) -> 0 | AA11: =D11-E11 -> 0 | AO11: =SUM(AC11:AN11) -> 0
A12: 7 | E12: =G12+I12+K12+M12+O12+Q12+S12+U12+W12+Y12 -> 0 | F12: =H12+J12+L12+N12+P12+R12+T12+V12+X12+Z12 -> 0 | H12: =IF($D12=0,0,ROUND(G12/$D12*$C12,2)) -> 0 | J12: =IF($D12=0,0,ROUND(I12/$D12*$C12,2)) -> 0 | L12: =IF($D12=0,0,ROUND(K12/$D12*$C12,2)) -> 0 | N12: =IF($D12=0,0,ROUND(M12/$D12*$C12,2)) -> 0 | P12: =IF($D12=0,0,ROUND(O12/$D12*$C12,2)) -> 0 | R12: =IF($D12=0,0,ROUND(Q12/$D12*$C12,2)) -> 0 | T12: =IF($D12=0,0,ROUND(S12/$D12*$C12,2)) -> 0 | V12: =IF($D12=0,0,ROUND(U12/$D12*$C12,2)) -> 0 | X12: =IF($D12=0,0,ROUND(W12/$D12*$C12,2)) -> 0 | Z12: =IF($D12=0,0,ROUND(Y12/$D12*$C12,2)) -> 0 | AA12: =D12-E12 -> 0 | AO12: =SUM(AC12:AN12) -> 0
A13: 8 | E13: =G13+I13+K13+M13+O13+Q13+S13+U13+W13+Y13 -> 0 | F13: =H13+J13+L13+N13+P13+R13+T13+V13+X13+Z13 -> 0 | H13: =IF($D13=0,0,ROUND(G13/$D13*$C13,2)) -> 0 | J13: =IF($D13=0,0,ROUND(I13/$D13*$C13,2)) -> 0 | L13: =IF($D13=0,0,ROUND(K13/$D13*$C13,2)) -> 0 | N13: =IF($D13=0,0,ROUND(M13/$D13*$C13,2)) -> 0 | P13: =IF($D13=0,0,ROUND(O13/$D13*$C13,2)) -> 0 | R13: =IF($D13=0,0,ROUND(Q13/$D13*$C13,2)) -> 0 | T13: =IF($D13=0,0,ROUND(S13/$D13*$C13,2)) -> 0 | V13: =IF($D13=0,0,ROUND(U13/$D13*$C13,2)) -> 0 | X13: =IF($D13=0,0,ROUND(W13/$D13*$C13,2)) -> 0 | Z13: =IF($D13=0,0,ROUND(Y13/$D13*$C13,2)) -> 0 | AA13: =D13-E13 -> 0 | AO13: =SUM(AC13:AN13) -> 0
A14: 9 | E14: =G14+I14+K14+M14+O14+Q14+S14+U14+W14+Y14 -> 0 | F14: =H14+J14+L14+N14+P14+R14+T14+V14+X14+Z14 -> 0 | H14: =IF($D14=0,0,ROUND(G14/$D14*$C14,2)) -> 0 | J14: =IF($D14=0,0,ROUND(I14/$D14*$C14,2)) -> 0 | L14: =IF($D14=0,0,ROUND(K14/$D14*$C14,2)) -> 0 | N14: =IF($D14=0,0,ROUND(M14/$D14*$C14,2)) -> 0 | P14: =IF($D14=0,0,ROUND(O14/$D14*$C14,2)) -> 0 | R14: =IF($D14=0,0,ROUND(Q14/$D14*$C14,2)) -> 0 | T14: =IF($D14=0,0,ROUND(S14/$D14*$C14,2)) -> 0 | V14: =IF($D14=0,0,ROUND(U14/$D14*$C14,2)) -> 0 | X14: =IF($D14=0,0,ROUND(W14/$D14*$C14,2)) -> 0 | Z14: =IF($D14=0,0,ROUND(Y14/$D14*$C14,2)) -> 0 | AA14: =D14-E14 -> 0 | AO14: =SUM(AC14:AN14) -> 0
A15: 10 | E15: =G15+I15+K15+M15+O15+Q15+S15+U15+W15+Y15 -> 0 | F15: =H15+J15+L15+N15+P15+R15+T15+V15+X15+Z15 -> 0 | H15: =IF($D15=0,0,ROUND(G15/$D15*$C15,2)) -> 0 | J15: =IF($D15=0,0,ROUND(I15/$D15*$C15,2)) -> 0 | L15: =IF($D15=0,0,ROUND(K15/$D15*$C15,2)) -> 0 | N15: =IF($D15=0,0,ROUND(M15/$D15*$C15,2)) -> 0 | P15: =IF($D15=0,0,ROUND(O15/$D15*$C15,2)) -> 0 | R15: =IF($D15=0,0,ROUND(Q15/$D15*$C15,2)) -> 0 | T15: =IF($D15=0,0,ROUND(S15/$D15*$C15,2)) -> 0 | V15: =IF($D15=0,0,ROUND(U15/$D15*$C15,2)) -> 0 | X15: =IF($D15=0,0,ROUND(W15/$D15*$C15,2)) -> 0 | Z15: =IF($D15=0,0,ROUND(Y15/$D15*$C15,2)) -> 0 | AA15: =D15-E15 -> 0 | AO15: =SUM(AC15:AN15) -> 0
A16: 11 | E16: =G16+I16+K16+M16+O16+Q16+S16+U16+W16+Y16 -> 0 | F16: =H16+J16+L16+N16+P16+R16+T16+V16+X16+Z16 -> 0 | H16: =IF($D16=0,0,ROUND(G16/$D16*$C16,2)) -> 0 | J16: =IF($D16=0,0,ROUND(I16/$D16*$C16,2)) -> 0 | L16: =IF($D16=0,0,ROUND(K16/$D16*$C16,2)) -> 0 | N16: =IF($D16=0,0,ROUND(M16/$D16*$C16,2)) -> 0 | P16: =IF($D16=0,0,ROUND(O16/$D16*$C16,2)) -> 0 | R16: =IF($D16=0,0,ROUND(Q16/$D16*$C16,2)) -> 0 | T16: =IF($D16=0,0,ROUND(S16/$D16*$C16,2)) -> 0 | V16: =IF($D16=0,0,ROUND(U16/$D16*$C16,2)) -> 0 | X16: =IF($D16=0,0,ROUND(W16/$D16*$C16,2)) -> 0 | Z16: =IF($D16=0,0,ROUND(Y16/$D16*$C16,2)) -> 0 | AA16: =D16-E16 -> 0 | AO16: =SUM(AC16:AN16) -> 0
A17: 12 | E17: =G17+I17+K17+M17+O17+Q17+S17+U17+W17+Y17 -> 0 | F17: =H17+J17+L17+N17+P17+R17+T17+V17+X17+Z17 -> 0 | H17: =IF($D17=0,0,ROUND(G17/$D17*$C17,2)) -> 0 | J17: =IF($D17=0,0,ROUND(I17/$D17*$C17,2)) -> 0 | L17: =IF($D17=0,0,ROUND(K17/$D17*$C17,2)) -> 0 | N17: =IF($D17=0,0,ROUND(M17/$D17*$C17,2)) -> 0 | P17: =IF($D17=0,0,ROUND(O17/$D17*$C17,2)) -> 0 | R17: =IF($D17=0,0,ROUND(Q17/$D17*$C17,2)) -> 0 | T17: =IF($D17=0,0,ROUND(S17/$D17*$C17,2)) -> 0 | V17: =IF($D17=0,0,ROUND(U17/$D17*$C17,2)) -> 0 | X17: =IF($D17=0,0,ROUND(W17/$D17*$C17,2)) -> 0 | Z17: =IF($D17=0,0,ROUND(Y17/$D17*$C17,2)) -> 0 | AA17: =D17-E17 -> 0 | AO17: =SUM(AC17:AN17) -> 0
... A23: 18 | E23: =G23+I23+K23+M23+O23+Q23+S23+U23+W23+Y23 -> 0 | F23: =H23+J23+L23+N23+P23+R23+T23+V23+X23+Z23 -> 0 | H23: =IF($D23=0,0,ROUND(G23/$D23*$C23,2)) -> 0 | J23: =IF($D23=0,0,ROUND(I23/$D23*$C23,2)) -> 0 | L23: =IF($D23=0,0,ROUND(K23/$D23*$C23,2)) -> 0 | N23: =IF($D23=0,0,ROUND(M23/$D23*$C23,2)) -> 0 | P23: =IF($D23=0,0,ROUND(O23/$D23*$C23,2)) -> 0 | R23: =IF($D23=0,0,ROUND(Q23/$D23*$C23,2)) -> 0 | T23: =IF($D23=0,0,ROUND(S23/$D23*$C23,2)) -> 0 | V23: =IF($D23=0,0,ROUND(U23/$D23*$C23,2)) -> 0 | X23: =IF($D23=0,0,ROUND(W23/$D23*$C23,2)) -> 0 | Z23: =IF($D23=0,0,ROUND(Y23/$D23*$C23,2)) -> 0 | AA23: =D23-E23 -> 0 | AO23: =SUM(AC23:AN23) -> 0
A24: 19 | E24: =G24+I24+K24+M24+O24+Q24+S24+U24+W24+Y24 -> 0 | F24: =H24+J24+L24+N24+P24+R24+T24+V24+X24+Z24 -> 0 | H24: =IF($D24=0,0,ROUND(G24/$D24*$C24,2)) -> 0 | J24: =IF($D24=0,0,ROUND(I24/$D24*$C24,2)) -> 0 | L24: =IF($D24=0,0,ROUND(K24/$D24*$C24,2)) -> 0 | N24: =IF($D24=0,0,ROUND(M24/$D24*$C24,2)) -> 0 | P24: =IF($D24=0,0,ROUND(O24/$D24*$C24,2)) -> 0 | R24: =IF($D24=0,0,ROUND(Q24/$D24*$C24,2)) -> 0 | T24: =IF($D24=0,0,ROUND(S24/$D24*$C24,2)) -> 0 | V24: =IF($D24=0,0,ROUND(U24/$D24*$C24,2)) -> 0 | X24: =IF($D24=0,0,ROUND(W24/$D24*$C24,2)) -> 0 | Z24: =IF($D24=0,0,ROUND(Y24/$D24*$C24,2)) -> 0 | AA24: =D24-E24 -> 0 | AO24: =SUM(AC25:AN25) -> 0
A25: 20 | E25: =G25+I25+K25+M25+O25+Q25+S25+U25+W25+Y25 -> 0 | F25: =H25+J25+L25+N25+P25+R25+T25+V25+X25+Z25 -> 0 | H25: =IF($D25=0,0,ROUND(G25/$D25*$C25,2)) -> 0 | J25: =IF($D25=0,0,ROUND(I25/$D25*$C25,2)) -> 0 | L25: =IF($D25=0,0,ROUND(K25/$D25*$C25,2)) -> 0 | N25: =IF($D25=0,0,ROUND(M25/$D25*$C25,2)) -> 0 | P25: =IF($D25=0,0,ROUND(O25/$D25*$C25,2)) -> 0 | R25: =IF($D25=0,0,ROUND(Q25/$D25*$C25,2)) -> 0 | T25: =IF($D25=0,0,ROUND(S25/$D25*$C25,2)) -> 0 | V25: =IF($D25=0,0,ROUND(U25/$D25*$C25,2)) -> 0 | X25: =IF($D25=0,0,ROUND(W25/$D25*$C25,2)) -> 0 | Z25: =IF($D25=0,0,ROUND(Y25/$D25*$C25,2)) -> 0 | AA25: =D25-E25 -> 0 | AO25: =SUM(AC25:AN25) -> 0
A26: 21 | E26: =G26+I26+K26+M26+O26+Q26+S26+U26+W26+Y26 -> 0 | F26: =H26+J26+L26+N26+P26+R26+T26+V26+X26+Z26 -> 0 | H26: =IF($D26=0,0,ROUND(G26/$D26*$C26,2)) -> 0 | J26: =IF($D26=0,0,ROUND(I26/$D26*$C26,2)) -> 0 | L26: =IF($D26=0,0,ROUND(K26/$D26*$C26,2)) -> 0 | N26: =IF($D26=0,0,ROUND(M26/$D26*$C26,2)) -> 0 | P26: =IF($D26=0,0,ROUND(O26/$D26*$C26,2)) -> 0 | R26: =IF($D26=0,0,ROUND(Q26/$D26*$C26,2)) -> 0 | T26: =IF($D26=0,0,ROUND(S26/$D26*$C26,2)) -> 0 | V26: =IF($D26=0,0,ROUND(U26/$D26*$C26,2)) -> 0 | X26: =IF($D26=0,0,ROUND(W26/$D26*$C26,2)) -> 0 | Z26: =IF($D26=0,0,ROUND(Y26/$D26*$C26,2)) -> 0 | AA26: =D26-E26 -> 0 | AO26: =SUM(AC26:AN26) -> 0
A27: 22 | E27: =G27+I27+K27+M27+O27+Q27+S27+U27+W27+Y27 -> 0 | F27: =H27+J27+L27+N27+P27+R27+T27+V27+X27+Z27 -> 0 | H27: =IF($D27=0,0,ROUND(G27/$D27*$C27,2)) -> 0 | J27: =IF($D27=0,0,ROUND(I27/$D27*$C27,2)) -> 0 | L27: =IF($D27=0,0,ROUND(K27/$D27*$C27,2)) -> 0 | N27: =IF($D27=0,0,ROUND(M27/$D27*$C27,2)) -> 0 | P27: =IF($D27=0,0,ROUND(O27/$D27*$C27,2)) -> 0 | R27: =IF($D27=0,0,ROUND(Q27/$D27*$C27,2)) -> 0 | T27: =IF($D27=0,0,ROUND(S27/$D27*$C27,2)) -> 0 | V27: =IF($D27=0,0,ROUND(U27/$D27*$C27,2)) -> 0 | X27: =IF($D27=0,0,ROUND(W27/$D27*$C27,2)) -> 0 | Z27: =IF($D27=0,0,ROUND(Y27/$D27*$C27,2)) -> 0 | AA27: =D27-E27 -> 0 | AO27: =SUM(AC27:AN27) -> 0
A28: 23 | E28: =G28+I28+K28+M28+O28+Q28+S28+U28+W28+Y28 -> 0 | F28: =H28+J28+L28+N28+P28+R28+T28+V28+X28+Z28 -> 0 | H28: =IF($D28=0,0,ROUND(G28/$D28*$C28,2)) -> 0 | J28: =IF($D28=0,0,ROUND(I28/$D28*$C28,2)) -> 0 | L28: =IF($D28=0,0,ROUND(K28/$D28*$C28,2)) -> 0 | N28: =IF($D28=0,0,ROUND(M28/$D28*$C28,2)) -> 0 | P28: =IF($D28=0,0,ROUND(O28/$D28*$C28,2)) -> 0 | R28: =IF($D28=0,0,ROUND(Q28/$D28*$C28,2)) -> 0 | T28: =IF($D28=0,0,ROUND(S28/$D28*$C28,2)) -> 0 | V28: =IF($D28=0,0,ROUND(U28/$D28*$C28,2)) -> 0 | X28: =IF($D28=0,0,ROUND(W28/$D28*$C28,2)) -> 0 | Z28: =IF($D28=0,0,ROUND(Y28/$D28*$C28,2)) -> 0 | AA28: =D28-E28 -> 0 | AO28: =SUM(AC28:AN28) -> 0
A29: 25 | E29: =G29+I29+K29+M29+O29+Q29+S29+U29+W29+Y29 -> 0 | F29: =H29+J29+L29+N29+P29+R29+T29+V29+X29+Z29 -> 0 | H29: =IF($D29=0,0,ROUND(G29/$D29*$C29,2)) -> 0 | J29: =IF($D29=0,0,ROUND(I29/$D29*$C29,2)) -> 0 | L29: =IF($D29=0,0,ROUND(K29/$D29*$C29,2)) -> 0 | N29: =IF($D29=0,0,ROUND(M29/$D29*$C29,2)) -> 0 | P29: =IF($D29=0,0,ROUND(O29/$D29*$C29,2)) -> 0 | R29: =IF($D29=0,0,ROUND(Q29/$D29*$C29,2)) -> 0 | T29: =IF($D29=0,0,ROUND(S29/$D29*$C29,2)) -> 0 | V29: =IF($D29=0,0,ROUND(U29/$D29*$C29,2)) -> 0 | X29: =IF($D29=0,0,ROUND(W29/$D29*$C29,2)) -> 0 | Z29: =IF($D29=0,0,ROUND(Y29/$D29*$C29,2)) -> 0 | AA29: =D29-E29 -> 0 | AO29: =SUM(AC29:AN29) -> 0
A30: 25 | E30: =G30+I30+K30+M30+O30+Q30+S30+U30+W30+Y30 -> 0 | F30: =H30+J30+L30+N30+P30+R30+T30+V30+X30+Z30 -> 0 | H30: =IF($D30=0,0,ROUND(G30/$D30*$C30,2)) -> 0 | J30: =IF($D30=0,0,ROUND(I30/$D30*$C30,2)) -> 0 | L30: =IF($D30=0,0,ROUND(K30/$D30*$C30,2)) -> 0 | N30: =IF($D30=0,0,ROUND(M30/$D30*$C30,2)) -> 0 | P30: =IF($D30=0,0,ROUND(O30/$D30*$C30,2)) -> 0 | R30: =IF($D30=0,0,ROUND(Q30/$D30*$C30,2)) -> 0 | T30: =IF($D30=0,0,ROUND(S30/$D30*$C30,2)) -> 0 | V30: =IF($D30=0,0,ROUND(U30/$D30*$C30,2)) -> 0 | X30: =IF($D30=0,0,ROUND(W30/$D30*$C30,2)) -> 0 | Z30: =IF($D30=0,0,ROUND(Y30/$D30*$C30,2)) -> 0 | AA30: =D30-E30 -> 0 | AO30: =SUM(AC30:AN30) -> 0
A31: 26 | E31: =G31+I31+K31+M31+O31+Q31+S31+U31+W31+Y31 -> 0 | F31: =H31+J31+L31+N31+P31+R31+T31+V31+X31+Z31 -> 0 | H31: =IF($D31=0,0,ROUND(G31/$D31*$C31,2)) -> 0 | J31: =IF($D31=0,0,ROUND(I31/$D31*$C31,2)) -> 0 | L31: =IF($D31=0,0,ROUND(K31/$D31*$C31,2)) -> 0 | N31: =IF($D31=0,0,ROUND(M31/$D31*$C31,2)) -> 0 | P31: =IF($D31=0,0,ROUND(O31/$D31*$C31,2)) -> 0 | R31: =IF($D31=0,0,ROUND(Q31/$D31*$C31,2)) -> 0 | T31: =IF($D31=0,0,ROUND(S31/$D31*$C31,2)) -> 0 | V31: =IF($D31=0,0,ROUND(U31/$D31*$C31,2)) -> 0 | X31: =IF($D31=0,0,ROUND(W31/$D31*$C31,2)) -> 0 | Z31: =IF($D31=0,0,ROUND(Y31/$D31*$C31,2)) -> 0 | AA31: =D31-E31 -> 0 | AO31: =SUM(AC31:AN31) -> 0
A32: 27 | E32: =G32+I32+K32+M32+O32+Q32+S32+U32+W32+Y32 -> 0 | F32: =H32+J32+L32+N32+P32+R32+T32+V32+X32+Z32 -> 0 | H32: =IF($D32=0,0,ROUND(G32/$D32*$C32,2)) -> 0 | J32: =IF($D32=0,0,ROUND(I32/$D32*$C32,2)) -> 0 | L32: =IF($D32=0,0,ROUND(K32/$D32*$C32,2)) -> 0 | N32: =IF($D32=0,0,ROUND(M32/$D32*$C32,2)) -> 0 | P32: =IF($D32=0,0,ROUND(O32/$D32*$C32,2)) -> 0 | R32: =IF($D32=0,0,ROUND(Q32/$D32*$C32,2)) -> 0 | T32: =IF($D32=0,0,ROUND(S32/$D32*$C32,2)) -> 0 | V32: =IF($D32=0,0,ROUND(U32/$D32*$C32,2)) -> 0 | X32: =IF($D32=0,0,ROUND(W32/$D32*$C32,2)) -> 0 | Z32: =IF($D32=0,0,ROUND(Y32/$D32*$C32,2)) -> 0 | AA32: =D32-E32 -> 0 | AO32: =SUM(AC32:AN32) -> 0
A33: 28 | E33: =G33+I33+K33+M33+O33+Q33+S33+U33+W33+Y33 -> 0 | F33: =H33+J33+L33+N33+P33+R33+T33+V33+X33+Z33 -> 0 | H33: =IF($D33=0,0,ROUND(G33/$D33*$C33,2)) -> 0 | J33: =IF($D33=0,0,ROUND(I33/$D33*$C33,2)) -> 0 | L33: =IF($D33=0,0,ROUND(K33/$D33*$C33,2)) -> 0 | N33: =IF($D33=0,0,ROUND(M33/$D33*$C33,2)) -> 0 | P33: =IF($D33=0,0,ROUND(O33/$D33*$C33,2)) -> 0 | R33: =IF($D33=0,0,ROUND(Q33/$D33*$C33,2)) -> 0 | T33: =IF($D33=0,0,ROUND(S33/$D33*$C33,2)) -> 0 | V33: =IF($D33=0,0,ROUND(U33/$D33*$C33,2)) -> 0 | X33: =IF($D33=0,0,ROUND(W33/$D33*$C33,2)) -> 0 | Z33: =IF($D33=0,0,ROUND(Y33/$D33*$C33,2)) -> 0 | AA33: =D33-E33 -> 0 | AO33: =SUM(AC33:AN33) -> 0
A34: 29 | E34: =G34+I34+K34+M34+O34+Q34+S34+U34+W34+Y34 -> 0 | F34: =H34+J34+L34+N34+P34+R34+T34+V34+X34+Z34 -> 0 | H34: =IF($D34=0,0,ROUND(G34/$D34*$C34,2)) -> 0 | J34: =IF($D34=0,0,ROUND(I34/$D34*$C34,2)) -> 0 | L34: =IF($D34=0,0,ROUND(K34/$D34*$C34,2)) -> 0 | N34: =IF($D34=0,0,ROUND(M34/$D34*$C34,2)) -> 0 | P34: =IF($D34=0,0,ROUND(O34/$D34*$C34,2)) -> 0 | R34: =IF($D34=0,0,ROUND(Q34/$D34*$C34,2)) -> 0 | T34: =IF($D34=0,0,ROUND(S34/$D34*$C34,2)) -> 0 | V34: =IF($D34=0,0,ROUND(U34/$D34*$C34,2)) -> 0 | X34: =IF($D34=0,0,ROUND(W34/$D34*$C34,2)) -> 0 | Z34: =IF($D34=0,0,ROUND(Y34/$D34*$C34,2)) -> 0 | AA34: =D34-E34 -> 0 | AO34: =SUM(AC34:AN34) -> 0
A35: 30 | E35: =G35+I35+K35+M35+O35+Q35+S35+U35+W35+Y35 -> 0 | F35: =H35+J35+L35+N35+P35+R35+T35+V35+X35+Z35 -> 0 | H35: =IF($D35=0,0,ROUND(G35/$D35*$C35,2)) -> 0 | J35: =IF($D35=0,0,ROUND(I35/$D35*$C35,2)) -> 0 | L35: =IF($D35=0,0,ROUND(K35/$D35*$C35,2)) -> 0 | N35: =IF($D35=0,0,ROUND(M35/$D35*$C35,2)) -> 0 | P35: =IF($D35=0,0,ROUND(O35/$D35*$C35,2)) -> 0 | R35: =IF($D35=0,0,ROUND(Q35/$D35*$C35,2)) -> 0 | T35: =IF($D35=0,0,ROUND(S35/$D35*$C35,2)) -> 0 | V35: =IF($D35=0,0,ROUND(U35/$D35*$C35,2)) -> 0 | X35: =IF($D35=0,0,ROUND(W35/$D35*$C35,2)) -> 0 | Z35: =IF($D35=0,0,ROUND(Y35/$D35*$C35,2)) -> 0 | AA35: =D35-E35 -> 0 | AO35: =SUM(AC35:AN35) -> 0
A36: 合计 | C36: =SUM(C6:C35) -> 0 | D36: =SUM(D6:D35) -> 0 | E36: =SUM(E6:E35) -> 0 | F36: =SUM(F6:F35) -> 0 | G36: =SUM(G6:G35) -> 0 | H36: =SUM(H6:H35) -> 0 | I36: =SUM(I6:I35) -> 0 | J36: =SUM(J6:J35) -> 0 | ... Z36: =SUM(Z6:Z35) -> 0 | AB36: 合计 | AC36: =SUM(AC6:AC35) -> 0
B38: 2025年2月份研发人员工资项目分摊表
A40: 序号 | B40: 姓名 | C40: 月工资 | D40: 出勤天数 | E40: 研发天数合计 | F40: 研发工资合计 | G40: =立项!$A$3 -> RD01 | I40: =立项!$A$4 -> RD02 | K40: =立项!$A$5 -> RD03 | M40: =立项!$A$6 -> RD04 | O40: =立项!$A$7 -> RD05 | Q40: =立项!$A$8 -> RD06 | S40: =立项!$A$9 -> RD07 | U40: =立项!$A$10 -> RD08 | W40: =立项!$A$11 -> RD09 | Y40: =立项!$A$12 -> RD10
G41: =立项!C3 -> 0 | I41: =立项!C4 -> 0 | K41: =立项!C5 -> 0 | M41: =立项!C6 -> 0 | O41: =立项!C7 -> 0 | Q41: =立项!C8 -> 0 | S41: =立项!C9 -> 0 | U41: =立项!C10 -> 0 | W41: =立项!C11 -> 0 | Y41: =立项!C12 -> 0
G42: 研发天数 | H42: 研发工资 | I42: 研发天数 | J42: 研发工资 | K42: 研发天数 | L42: 研发工资 | M42: 研发天数 | N42: 研发工资 | O42: 研发天数 | P42: 研发工资 | Q42: 研发天数 | R42: 研发工资 | S42: 研发天数 | T42: 研发工资 | U42: 研发天数 | V42: 研发工资 | W42: 研发天数 | X42: 研发工资 | Y42: 研发天数 | Z42: 研发工资
A43: 1 | E43: =G43+I43+K43+M43+O43+Q43+S43+U43+W43+Y43 -> 0 | F43: =H43+J43+L43+N43+P43+R43+T43+V43+X43+Z43 -> 0 | H43: =IF($D43=0,0,ROUND(G43/$D43*$C43,2)) -> 0 | J43: =IF($D43=0,0,ROUND(I43/$D43*$C43,2)) -> 0 | L43: =IF($D43=0,0,ROUND(K43/$D43*$C43,2)) -> 0 | N43: =IF($D43=0,0,ROUND(M43/$D43*$C43,2)) -> 0 | P43: =IF($D43=0,0,ROUND(O43/$D43*$C43,2)) -> 0 | R43: =IF($D43=0,0,ROUND(Q43/$D43*$C43,2)) -> 0 | T43: =IF($D43=0,0,ROUND(S43/$D43*$C43,2)) -> 0 | V43: =IF($D43=0,0,ROUND(U43/$D43*$C43,2)) -> 0 | X43: =IF($D43=0,0,ROUND(W43/$D43*$C43,2)) -> 0 | Z43: =IF($D43=0,0,ROUND(Y43/$D43*$C43,2)) -> 0 | AA43: =D43-E43 -> 0
A44: 2 | E44: =G44+I44+K44+M44+O44+Q44+S44+U44+W44+Y44 -> 0 | F44: =H44+J44+L44+N44+P44+R44+T44+V44+X44+Z44 -> 0 | H44: =IF($D44=0,0,ROUND(G44/$D44*$C44,2)) -> 0 | J44: =IF($D44=0,0,ROUND(I44/$D44*$C44,2)) -> 0 | L44: =IF($D44=0,0,ROUND(K44/$D44*$C44,2)) -> 0 | N44: =IF($D44=0,0,ROUND(M44/$D44*$C44,2)) -> 0 | P44: =IF($D44=0,0,ROUND(O44/$D44*$C44,2)) -> 0 | R44: =IF($D44=0,0,ROUND(Q44/$D44*$C44,2)) -> 0 | T44: =IF($D44=0,0,ROUND(S44/$D44*$C44,2)) -> 0 | V44: =IF($D44=0,0,ROUND(U44/$D44*$C44,2)) -> 0 | X44: =IF($D44=0,0,ROUND(W44/$D44*$C44,2)) -> 0 | Z44: =IF($D44=0,0,ROUND(Y44/$D44*$C44,2)) -> 0 | AA44: =D44-E44 -> 0
A45: 3 | E45: =G45+I45+K45+M45+O45+Q45+S45+U45+W45+Y45 -> 0 | F45: =H45+J45+L45+N45+P45+R45+T45+V45+X45+Z45 -> 0 | H45: =IF($D45=0,0,ROUND(G45/$D45*$C45,2)) -> 0 | J45: =IF($D45=0,0,ROUND(I45/$D45*$C45,2)) -> 0 | L45: =IF($D45=0,0,ROUND(K45/$D45*$C45,2)) -> 0 | N45: =IF($D45=0,0,ROUND(M45/$D45*$C45,2)) -> 0 | P45: =IF($D45=0,0,ROUND(O45/$D45*$C45,2)) -> 0 | R45: =IF($D45=0,0,ROUND(Q45/$D45*$C45,2)) -> 0 | T45: =IF($D45=0,0,ROUND(S45/$D45*$C45,2)) -> 0 | V45: =IF($D45=0,0,ROUND(U45/$D45*$C45,2)) -> 0 | X45: =IF($D45=0,0,ROUND(W45/$D45*$C45,2)) -> 0 | Z45: =IF($D45=0,0,ROUND(Y45/$D45*$C45,2)) -> 0 | AA45: =D45-E45 -> 0
A46: 4 | E46: =G46+I46+K46+M46+O46+Q46+S46+U46+W46+Y46 -> 0 | F46: =H46+J46+L46+N46+P46+R46+T46+V46+X46+Z46 -> 0 | H46: =IF($D46=0,0,ROUND(G46/$D46*$C46,2)) -> 0 | J46: =IF($D46=0,0,ROUND(I46/$D46*$C46,2)) -> 0 | L46: =IF($D46=0,0,ROUND(K46/$D46*$C46,2)) -> 0 | N46: =IF($D46=0,0,ROUND(M46/$D46*$C46,2)) -> 0 | P46: =IF($D46=0,0,ROUND(O46/$D46*$C46,2)) -> 0 | R46: =IF($D46=0,0,ROUND(Q46/$D46*$C46,2)) -> 0 | T46: =IF($D46=0,0,ROUND(S46/$D46*$C46,2)) -> 0 | V46: =IF($D46=0,0,ROUND(U46/$D46*$C46,2)) -> 0 | X46: =IF($D46=0,0,ROUND(W46/$D46*$C46,2)) -> 0 | Z46: =IF($D46=0,0,ROUND(Y46/$D46*$C46,2)) -> 0 | AA46: =D46-E46 -> 0
A47: 5 | E47: =G47+I47+K47+M47+O47+Q47+S47+U47+W47+Y47 -> 0 | F47: =H47+J47+L47+N47+P47+R47+T47+V47+X47+Z47 -> 0 | H47: =IF($D47=0,0,ROUND(G47/$D47*$C47,2)) -> 0 | J47: =IF($D47=0,0,ROUND(I47/$D47*$C47,2)) -> 0 | L47: =IF($D47=0,0,ROUND(K47/$D47*$C47,2)) -> 0 | N47: =IF($D47=0,0,ROUND(M47/$D47*$C47,2)) -> 0 | P47: =IF($D47=0,0,ROUND(O47/$D47*$C47,2)) -> 0 | R47: =IF($D47=0,0,ROUND(Q47/$D47*$C47,2)) -> 0 | T47: =IF($D47=0,0,ROUND(S47/$D47*$C47,2)) -> 0 | V47: =IF($D47=0,0,ROUND(U47/$D47*$C47,2)) -> 0 | X47: =IF($D47=0,0,ROUND(W47/$D47*$C47,2)) -> 0 | Z47: =IF($D47=0,0,ROUND(Y47/$D47*$C47,2)) -> 0 | AA47: =D47-E47 -> 0
A48: 6 | E48: =G48+I48+K48+M48+O48+Q48+S48+U48+W48+Y48 -> 0 | F48: =H48+J48+L48+N48+P48+R48+T48+V48+X48+Z48 -> 0 | H48: =IF($D48=0,0,ROUND(G48/$D48*$C48,2)) -> 0 | J48: =IF($D48=0,0,ROUND(I48/$D48*$C48,2)) -> 0 | L48: =IF($D48=0,0,ROUND(K48/$D48*$C48,2)) -> 0 | N48: =IF($D48=0,0,ROUND(M48/$D48*$C48,2)) -> 0 | P48: =IF($D48=0,0,ROUND(O48/$D48*$C48,2)) -> 0 | R48: =IF($D48=0,0,ROUND(Q48/$D48*$C48,2)) -> 0 | T48: =IF($D48=0,0,ROUND(S48/$D48*$C48,2)) -> 0 | V48: =IF($D48=0,0,ROUND(U48/$D48*$C48,2)) -> 0 | X48: =IF($D48=0,0,ROUND(W48/$D48*$C48,2)) -> 0 | Z48: =IF($D48=0,0,ROUND(Y48/$D48*$C48,2)) -> 0 | AA48: =D48-E48 -> 0
A49: 7 | E49: =G49+I49+K49+M49+O49+Q49+S49+U49+W49+Y49 -> 0 | F49: =H49+J49+L49+N49+P49+R49+T49+V49+X49+Z49 -> 0 | H49: =IF($D49=0,0,ROUND(G49/$D49*$C49,2)) -> 0 | J49: =IF($D49=0,0,ROUND(I49/$D49*$C49,2)) -> 0 | L49: =IF($D49=0,0,ROUND(K49/$D49*$C49,2)) -> 0 | N49: =IF($D49=0,0,ROUND(M49/$D49*$C49,2)) -> 0 | P49: =IF($D49=0,0,ROUND(O49/$D49*$C49,2)) -> 0 | R49: =IF($D49=0,0,ROUND(Q49/$D49*$C49,2)) -> 0 | T49: =IF($D49=0,0,ROUND(S49/$D49*$C49,2)) -> 0 | V49: =IF($D49=0,0,ROUND(U49/$D49*$C49,2)) -> 0 | X49: =IF($D49=0,0,ROUND(W49/$D49*$C49,2)) -> 0 | Z49: =IF($D49=0,0,ROUND(Y49/$D49*$C49,2)) -> 0 | AA49: =D49-E49 -> 0
A50: 8 | E50: =G50+I50+K50+M50+O50+Q50+S50+U50+W50+Y50 -> 0 | F50: =H50+J50+L50+N50+P50+R50+T50+V50+X50+Z50 -> 0 | H50: =IF($D50=0,0,ROUND(G50/$D50*$C50,2)) -> 0 | J50: =IF($D50=0,0,ROUND(I50/$D50*$C50,2)) -> 0 | L50: =IF($D50=0,0,ROUND(K50/$D50*$C50,2)) -> 0 | N50: =IF($D50=0,0,ROUND(M50/$D50*$C50,2)) -> 0 | P50: =IF($D50=0,0,ROUND(O50/$D50*$C50,2)) -> 0 | R50: =IF($D50=0,0,ROUND(Q50/$D50*$C50,2)) -> 0 | T50: =IF($D50=0,0,ROUND(S50/$D50*$C50,2)) -> 0 | V50: =IF($D50=0,0,ROUND(U50/$D50*$C50,2)) -> 0 | X50: =IF($D50=0,0,ROUND(W50/$D50*$C50,2)) -> 0 | Z50: =IF($D50=0,0,ROUND(Y50/$D50*$C50,2)) -> 0 | AA50: =D50-E50 -> 0
A51: 9 | E51: =G51+I51+K51+M51+O51+Q51+S51+U51+W51+Y51 -> 0 | F51: =H51+J51+L51+N51+P51+R51+T51+V51+X51+Z51 -> 0 | H51: =IF($D51=0,0,ROUND(G51/$D51*$C51,2)) -> 0 | J51: =IF($D51=0,0,ROUND(I51/$D51*$C51,2)) -> 0 | L51: =IF($D51=0,0,ROUND(K51/$D51*$C51,2)) -> 0 | N51: =IF($D51=0,0,ROUND(M51/$D51*$C51,2)) -> 0 | P51: =IF($D51=0,0,ROUND(O51/$D51*$C51,2)) -> 0 | R51: =IF($D51=0,0,ROUND(Q51/$D51*$C51,2)) -> 0 | T51: =IF($D51=0,0,ROUND(S51/$D51*$C51,2)) -> 0 | V51: =IF($D51=0,0,ROUND(U51/$D51*$C51,2)) -> 0 | X51: =IF($D51=0,0,ROUND(W51/$D51*$C51,2)) -> 0 | Z51: =IF($D51=0,0,ROUND(Y51/$D51*$C51,2)) -> 0 | AA51: =D51-E51 -> 0
A52: 10 | E52: =G52+I52+K52+M52+O52+Q52+S52+U52+W52+Y52 -> 0 | F52: =H52+J52+L52+N52+P52+R52+T52+V52+X52+Z52 -> 0 | H52: =IF($D52=0,0,ROUND(G52/$D52*$C52,2)) -> 0 | J52: =IF($D52=0,0,ROUND(I52/$D52*$C52,2)) -> 0 | L52: =IF($D52=0,0,ROUND(K52/$D52*$C52,2)) -> 0 | N52: =IF($D52=0,0,ROUND(M52/$D52*$C52,2)) -> 0 | P52: =IF($D52=0,0,ROUND(O52/$D52*$C52,2)) -> 0 | R52: =IF($D52=0,0,ROUND(Q52/$D52*$C52,2)) -> 0 | T52: =IF($D52=0,0,ROUND(S52/$D52*$C52,2)) -> 0 | V52: =IF($D52=0,0,ROUND(U52/$D52*$C52,2)) -> 0 | X52: =IF($D52=0,0,ROUND(W52/$D52*$C52,2)) -> 0 | Z52: =IF($D52=0,0,ROUND(Y52/$D52*$C52,2)) -> 0 | AA52: =D52-E52 -> 0
A53: 11 | E53: =G53+I53+K53+M53+O53+Q53+S53+U53+W53+Y53 -> 0 | F53: =H53+J53+L53+N53+P53+R53+T53+V53+X53+Z53 -> 0 | H53: =IF($D53=0,0,ROUND(G53/$D53*$C53,2)) -> 0 | J53: =IF($D53=0,0,ROUND(I53/$D53*$C53,2)) -> 0 | L53: =IF($D53=0,0,ROUND(K53/$D53*$C53,2)) -> 0 | N53: =IF($D53=0,0,ROUND(M53/$D53*$C53,2)) -> 0 | P53: =IF($D53=0,0,ROUND(O53/$D53*$C53,2)) -> 0 | R53: =IF($D53=0,0,ROUND(Q53/$D53*$C53,2)) -> 0 | T53: =IF($D53=0,0,ROUND(S53/$D53*$C53,2)) -> 0 | V53: =IF($D53=0,0,ROUND(U53/$D53*$C53,2)) -> 0 | X53: =IF($D53=0,0,ROUND(W53/$D53*$C53,2)) -> 0 | Z53: =IF($D53=0,0,ROUND(Y53/$D53*$C53,2)) -> 0 | AA53: =D53-E53 -> 0
A54: 12 | E54: =G54+I54+K54+M54+O54+Q54+S54+U54+W54+Y54 -> 0 | F54: =H54+J54+L54+N54+P54+R54+T54+V54+X54+Z54 -> 0 | H54: =IF($D54=0,0,ROUND(G54/$D54*$C54,2)) -> 0 | J54: =IF($D54=0,0,ROUND(I54/$D54*$C54,2)) -> 0 | L54: =IF($D54=0,0,ROUND(K54/$D54*$C54,2)) -> 0 | N54: =IF($D54=0,0,ROUND(M54/$D54*$C54,2)) -> 0 | P54: =IF($D54=0,0,ROUND(O54/$D54*$C54,2)) -> 0 | R54: =IF($D54=0,0,ROUND(Q54/$D54*$C54,2)) -> 0 | T54: =IF($D54=0,0,ROUND(S54/$D54*$C54,2)) -> 0 | V54: =IF($D54=0,0,ROUND(U54/$D54*$C54,2)) -> 0 | X54: =IF($D54=0,0,ROUND(W54/$D54*$C54,2)) -> 0 | Z54: =IF($D54=0,0,ROUND(Y54/$D54*$C54,2)) -> 0 | AA54: =D54-E54 -> 0
... A72: 30 | E72: =G72+I72+K72+M72+O72+Q72+S72+U72+W72+Y72 -> 0 | F72: =H72+J72+L72+N72+P72+R72+T72+V72+X72+Z72 -> 0 | H72: =IF($D72=0,0,ROUND(G72/$D72*$C72,2)) -> 0 | J72: =IF($D72=0,0,ROUND(I72/$D72*$C72,2)) -> 0 | L72: =IF($D72=0,0,ROUND(K72/$D72*$C72,2)) -> 0 | N72: =IF($D72=0,0,ROUND(M72/$D72*$C72,2)) -> 0 | P72: =IF($D72=0,0,ROUND(O72/$D72*$C72,2)) -> 0 | R72: =IF($D72=0,0,ROUND(Q72/$D72*$C72,2)) -> 0 | T72: =IF($D72=0,0,ROUND(S72/$D72*$C72,2)) -> 0 | V72: =IF($D72=0,0,ROUND(U72/$D72*$C72,2)) -> 0 | X72: =IF($D72=0,0,ROUND(W72/$D72*$C72,2)) -> 0 | Z72: =IF($D72=0,0,ROUND(Y72/$D72*$C72,2)) -> 0 | AA72: =D72-E72 -> 0
A73: 合计 | C73: =SUM(C43:C72) -> 0 | D73: =SUM(D43:D72) -> 0 | E73: =SUM(E43:E72) -> 0 | F73: =SUM(F43:F72) -> 0 | G73: =SUM(G43:G72) -> 0 | H73: =SUM(H43:H72) -> 0 | I73: =SUM(I43:I72) -> 0 | J73: =SUM(J43:J72) -> 0 | ... Z73: =SUM(Z43:Z72) -> 0
B76: 2025年3月份研发人员工资项目分摊表
A78: 序号 | B78: 姓名 | C78: 月工资 | D78: 出勤天数 | E78: 研发天数合计 | F78: 研发工资合计 | G78: =立项!$A$3 -> RD01 | I78: =立项!$A$4 -> RD02 | K78: =立项!$A$5 -> RD03 | M78: =立项!$A$6 -> RD04 | O78: =立项!$A$7 -> RD05 | Q78: =立项!$A$8 -> RD06 | S78: =立项!$A$9 -> RD07 | U78: =立项!$A$10 -> RD08 | W78: =立项!$A$11 -> RD09 | Y78: =立项!$A$12 -> RD10
G79: =立项!C3 -> 0 | I79: =立项!C4 -> 0 | K79: =立项!C5 -> 0 | M79: =立项!C6 -> 0 | O79: =立项!C7 -> 0 | Q79: =立项!C8 -> 0 | S79: =立项!C9 -> 0 | U79: =立项!C10 -> 0 | W79: =立项!C11 -> 0 | Y79: =立项!C12 -> 0
G80: 研发天数 | H80: 研发工资 | I80: 研发天数 | J80: 研发工资 | K80: 研发天数 | L80: 研发工资 | M80: 研发天数 | N80: 研发工资 | O80: 研发天数 | P80: 研发工资 | Q80: 研发天数 | R80: 研发工资 | S80: 研发天数 | T80: 研发工资 | U80: 研发天数 | V80: 研发工资 | W80: 研发天数 | X80: 研发工资 | Y80: 研发天数 | Z80: 研发工资
A81: 1 | E81: =G81+I81+K81+M81+O81+Q81+S81+U81+W81+Y81 -> 0 | F81: =H81+J81+L81+N81+P81+R81+T81+V81+X81+Z81 -> 0 | H81: =IF($D81=0,0,ROUND(G81/$D81*$C81,2)) -> 0 | J81: =IF($D81=0,0,ROUND(I81/$D81*$C81,2)) -> 0 | L81: =IF($D81=0,0,ROUND(K81/$D81*$C81,2)) -> 0 | N81: =IF($D81=0,0,ROUND(M81/$D81*$C81,2)) -> 0 | P81: =IF($D81=0,0,ROUND(O81/$D81*$C81,2)) -> 0 | R81: =IF($D81=0,0,ROUND(Q81/$D81*$C81,2)) -> 0 | T81: =IF($D81=0,0,ROUND(S81/$D81*$C81,2)) -> 0 | V81: =IF($D81=0,0,ROUND(U81/$D81*$C81,2)) -> 0 | X81: =IF($D81=0,0,ROUND(W81/$D81*$C81,2)) -> 0 | Z81: =IF($D81=0,0,ROUND(Y81/$D81*$C81,2)) -> 0 | AA81: =D81-E81 -> 0
A82: 2 | E82: =G82+I82+K82+M82+O82+Q82+S82+U82+W82+Y82 -> 0 | F82: =H82+J82+L82+N82+P82+R82+T82+V82+X82+Z82 -> 0 | H82: =IF($D82=0,0,ROUND(G82/$D82*$C82,2)) -> 0 | J82: =IF($D82=0,0,ROUND(I82/$D82*$C82,2)) -> 0 | L82: =IF($D82=0,0,ROUND(K82/$D82*$C82,2)) -> 0 | N82: =IF($D82=0,0,ROUND(M82/$D82*$C82,2)) -> 0 | P82: =IF($D82=0,0,ROUND(O82/$D82*$C82,2)) -> 0 | R82: =IF($D82=0,0,ROUND(Q82/$D82*$C82,2)) -> 0 | T82: =IF($D82=0,0,ROUND(S82/$D82*$C82,2)) -> 0 | V82: =IF($D82=0,0,ROUND(U82/$D82*$C82,2)) -> 0 | X82: =IF($D82=0,0,ROUND(W82/$D82*$C82,2)) -> 0 | Z82: =IF($D82=0,0,ROUND(Y82/$D82*$C82,2)) -> 0 | AA82: =D82-E82 -> 0
A83: 3 | E83: =G83+I83+K83+M83+O83+Q83+S83+U83+W83+Y83 -> 0 | F83: =H83+J83+L83+N83+P83+R83+T83+V83+X83+Z83 -> 0 | H83: =IF($D83=0,0,ROUND(G83/$D83*$C83,2)) -> 0 | J83: =IF($D83=0,0,ROUND(I83/$D83*$C83,2)) -> 0 | L83: =IF($D83=0,0,ROUND(K83/$D83*$C83,2)) -> 0 | N83: =IF($D83=0,0,ROUND(M83/$D83*$C83,2)) -> 0 | P83: =IF($D83=0,0,ROUND(O83/$D83*$C83,2)) -> 0 | R83: =IF($D83=0,0,ROUND(Q83/$D83*$C83,2)) -> 0 | T83: =IF($D83=0,0,ROUND(S83/$D83*$C83,2)) -> 0 | V83: =IF($D83=0,0,ROUND(U83/$D83*$C83,2)) -> 0 | X83: =IF($D83=0,0,ROUND(W83/$D83*$C83,2)) -> 0 | Z83: =IF($D83=0,0,ROUND(Y83/$D83*$C83,2)) -> 0 | AA83: =D83-E83 -> 0
A84: 4 | E84: =G84+I84+K84+M84+O84+Q84+S84+U84+W84+Y84 -> 0 | F84: =H84+J84+L84+N84+P84+R84+T84+V84+X84+Z84 -> 0 | H84: =IF($D84=0,0,ROUND(G84/$D84*$C84,2)) -> 0 | J84: =IF($D84=0,0,ROUND(I84/$D84*$C84,2)) -> 0 | L84: =IF($D84=0,0,ROUND(K84/$D84*$C84,2)) -> 0 | N84: =IF($D84=0,0,ROUND(M84/$D84*$C84,2)) -> 0 | P84: =IF($D84=0,0,ROUND(O84/$D84*$C84,2)) -> 0 | R84: =IF($D84=0,0,ROUND(Q84/$D84*$C84,2)) -> 0 | T84: =IF($D84=0,0,ROUND(S84/$D84*$C84,2)) -> 0 | V84: =IF($D84=0,0,ROUND(U84/$D84*$C84,2)) -> 0 | X84: =IF($D84=0,0,ROUND(W84/$D84*$C84,2)) -> 0 | Z84: =IF($D84=0,0,ROUND(Y84/$D84*$C84,2)) -> 0 | AA84: =D84-E84 -> 0
A85: 5 | E85: =G85+I85+K85+M85+O85+Q85+S85+U85+W85+Y85 -> 0 | F85: =H85+J85+L85+N85+P85+R85+T85+V85+X85+Z85 -> 0 | H85: =IF($D85=0,0,ROUND(G85/$D85*$C85,2)) -> 0 | J85: =IF($D85=0,0,ROUND(I85/$D85*$C85,2)) -> 0 | L85: =IF($D85=0,0,ROUND(K85/$D85*$C85,2)) -> 0 | N85: =IF($D85=0,0,ROUND(M85/$D85*$C85,2)) -> 0 | P85: =IF($D85=0,0,ROUND(O85/$D85*$C85,2)) -> 0 | R85: =IF($D85=0,0,ROUND(Q85/$D85*$C85,2)) -> 0 | T85: =IF($D85=0,0,ROUND(S85/$D85*$C85,2)) -> 0 | V85: =IF($D85=0,0,ROUND(U85/$D85*$C85,2)) -> 0 | X85: =IF($D85=0,0,ROUND(W85/$D85*$C85,2)) -> 0 | Z85: =IF($D85=0,0,ROUND(Y85/$D85*$C85,2)) -> 0 | AA85: =D85-E85 -> 0
A86: 6 | E86: =G86+I86+K86+M86+O86+Q86+S86+U86+W86+Y86 -> 0 | F86: =H86+J86+L86+N86+P86+R86+T86+V86+X86+Z86 -> 0 | H86: =IF($D86=0,0,ROUND(G86/$D86*$C86,2)) -> 0 | J86: =IF($D86=0,0,ROUND(I86/$D86*$C86,2)) -> 0 | L86: =IF($D86=0,0,ROUND(K86/$D86*$C86,2)) -> 0 | N86: =IF($D86=0,0,ROUND(M86/$D86*$C86,2)) -> 0 | P86: =IF($D86=0,0,ROUND(O86/$D86*$C86,2)) -> 0 | R86: =IF($D86=0,0,ROUND(Q86/$D86*$C86,2)) -> 0 | T86: =IF($D86=0,0,ROUND(S86/$D86*$C86,2)) -> 0 | V86: =IF($D86=0,0,ROUND(U86/$D86*$C86,2)) -> 0 | X86: =IF($D86=0,0,ROUND(W86/$D86*$C86,2)) -> 0 | Z86: =IF($D86=0,0,ROUND(Y86/$D86*$C86,2)) -> 0 | AA86: =D86-E86 -> 0
A87: 7 | E87: =G87+I87+K87+M87+O87+Q87+S87+U87+W87+Y87 -> 0 | F87: =H87+J87+L87+N87+P87+R87+T87+V87+X87+Z87 -> 0 | H87: =IF($D87=0,0,ROUND(G87/$D87*$C87,2)) -> 0 | J87: =IF($D87=0,0,ROUND(I87/$D87*$C87,2)) -> 0 | L87: =IF($D87=0,0,ROUND(K87/$D87*$C87,2)) -> 0 | N87: =IF($D87=0,0,ROUND(M87/$D87*$C87,2)) -> 0 | P87: =IF($D87=0,0,ROUND(O87/$D87*$C87,2)) -> 0 | R87: =IF($D87=0,0,ROUND(Q87/$D87*$C87,2)) -> 0 | T87: =IF($D87=0,0,ROUND(S87/$D87*$C87,2)) -> 0 | V87: =IF($D87=0,0,ROUND(U87/$D87*$C87,2)) -> 0 | X87: =IF($D87=0,0,ROUND(W87/$D87*$C87,2)) -> 0 | Z87: =IF($D87=0,0,ROUND(Y87/$D87*$C87,2)) -> 0 | AA87: =D87-E87 -> 0
A88: 8 | E88: =G88+I88+K88+M88+O88+Q88+S88+U88+W88+Y88 -> 0 | F88: =H88+J88+L88+N88+P88+R88+T88+V88+X88+Z88 -> 0 | H88: =IF($D88=0,0,ROUND(G88/$D88*$C88,2)) -> 0 | J88: =IF($D88=0,0,ROUND(I88/$D88*$C88,2)) -> 0 | L88: =IF($D88=0,0,ROUND(K88/$D88*$C88,2)) -> 0 | N88: =IF($D88=0,0,ROUND(M88/$D88*$C88,2)) -> 0 | P88: =IF($D88=0,0,ROUND(O88/$D88*$C88,2)) -> 0 | R88: =IF($D88=0,0,ROUND(Q88/$D88*$C88,2)) -> 0 | T88: =IF($D88=0,0,ROUND(S88/$D88*$C88,2)) -> 0 | V88: =IF($D88=0,0,ROUND(U88/$D88*$C88,2)) -> 0 | X88: =IF($D88=0,0,ROUND(W88/$D88*$C88,2)) -> 0 | Z88: =IF($D88=0,0,ROUND(Y88/$D88*$C88,2)) -> 0 | AA88: =D88-E88 -> 0
A89: 9 | E89: =G89+I89+K89+M89+O89+Q89+S89+U89+W89+Y89 -> 0 | F89: =H89+J89+L89+N89+P89+R89+T89+V89+X89+Z89 -> 0 | H89: =IF($D89=0,0,ROUND(G89/$D89*$C89,2)) -> 0 | J89: =IF($D89=0,0,ROUND(I89/$D89*$C89,2)) -> 0 | L89: =IF($D89=0,0,ROUND(K89/$D89*$C89,2)) -> 0 | N89: =IF($D89=0,0,ROUND(M89/$D89*$C89,2)) -> 0 | P89: =IF($D89=0,0,ROUND(O89/$D89*$C89,2)) -> 0 | R89: =IF($D89=0,0,ROUND(Q89/$D89*$C89,2)) -> 0 | T89: =IF($D89=0,0,ROUND(S89/$D89*$C89,2)) -> 0 | V89: =IF($D89=0,0,ROUND(U89/$D89*$C89,2)) -> 0 | X89: =IF($D89=0,0,ROUND(W89/$D89*$C89,2)) -> 0 | Z89: =IF($D89=0,0,ROUND(Y89/$D89*$C89,2)) -> 0 | AA89: =D89-E89 -> 0
A90: 10 | E90: =G90+I90+K90+M90+O90+Q90+S90+U90+W90+Y90 -> 0 | F90: =H90+J90+L90+N90+P90+R90+T90+V90+X90+Z90 -> 0 | H90: =IF($D90=0,0,ROUND(G90/$D90*$C90,2)) -> 0 | J90: =IF($D90=0,0,ROUND(I90/$D90*$C90,2)) -> 0 | L90: =IF($D90=0,0,ROUND(K90/$D90*$C90,2)) -> 0 | N90: =IF($D90=0,0,ROUND(M90/$D90*$C90,2)) -> 0 | P90: =IF($D90=0,0,ROUND(O90/$D90*$C90,2)) -> 0 | R90: =IF($D90=0,0,ROUND(Q90/$D90*$C90,2)) -> 0 | T90: =IF($D90=0,0,ROUND(S90/$D90*$C90,2)) -> 0 | V90: =IF($D90=0,0,ROUND(U90/$D90*$C90,2)) -> 0 | X90: =IF($D90=0,0,ROUND(W90/$D90*$C90,2)) -> 0 | Z90: =IF($D90=0,0,ROUND(Y90/$D90*$C90,2)) -> 0 | AA90: =D90-E90 -> 0
A91: 11 | E91: =G91+I91+K91+M91+O91+Q91+S91+U91+W91+Y91 -> 0 | F91: =H91+J91+L91+N91+P91+R91+T91+V91+X91+Z91 -> 0 | H91: =IF($D91=0,0,ROUND(G91/$D91*$C91,2)) -> 0 | J91: =IF($D91=0,0,ROUND(I91/$D91*$C91,2)) -> 0 | L91: =IF($D91=0,0,ROUND(K91/$D91*$C91,2)) -> 0 | N91: =IF($D91=0,0,ROUND(M91/$D91*$C91,2)) -> 0 | P91: =IF($D91=0,0,ROUND(O91/$D91*$C91,2)) -> 0 | R91: =IF($D91=0,0,ROUND(Q91/$D91*$C91,2)) -> 0 | T91: =IF($D91=0,0,ROUND(S91/$D91*$C91,2)) -> 0 | V91: =IF($D91=0,0,ROUND(U91/$D91*$C91,2)) -> 0 | X91: =IF($D91=0,0,ROUND(W91/$D91*$C91,2)) -> 0 | Z91: =IF($D91=0,0,ROUND(Y91/$D91*$C91,2)) -> 0 | AA91: =D91-E91 -> 0
A92: 12 | E92: =G92+I92+K92+M92+O92+Q92+S92+U92+W92+Y92 -> 0 | F92: =H92+J92+L92+N92+P92+R92+T92+V92+X92+Z92 -> 0 | H92: =IF($D92=0,0,ROUND(G92/$D92*$C92,2)) -> 0 | J92: =IF($D92=0,0,ROUND(I92/$D92*$C92,2)) -> 0 | L92: =IF($D92=0,0,ROUND(K92/$D92*$C92,2)) -> 0 | N92: =IF($D92=0,0,ROUND(M92/$D92*$C92,2)) -> 0 | P92: =IF($D92=0,0,ROUND(O92/$D92*$C92,2)) -> 0 | R92: =IF($D92=0,0,ROUND(Q92/$D92*$C92,2)) -> 0 | T92: =IF($D92=0,0,ROUND(S92/$D92*$C92,2)) -> 0 | V92: =IF($D92=0,0,ROUND(U92/$D92*$C92,2)) -> 0 | X92: =IF($D92=0,0,ROUND(W92/$D92*$C92,2)) -> 0 | Z92: =IF($D92=0,0,ROUND(Y92/$D92*$C92,2)) -> 0 | AA92: =D92-E92 -> 0
... A110: 30 | E110: =G110+I110+K110+M110+O110+Q110+S110+U110+W110+Y110 -> 0 | F110: =H110+J110+L110+N110+P110+R110+T110+V110+X110+Z110 -> 0 | H110: =IF($D110=0,0,ROUND(G110/$D110*$C110,2)) -> 0 | J110: =IF($D110=0,0,ROUND(I110/$D110*$C110,2)) -> 0 | L110: =IF($D110=0,0,ROUND(K110/$D110*$C110,2)) -> 0 | N110: =IF($D110=0,0,ROUND(M110/$D110*$C110,2)) -> 0 | P110: =IF($D110=0,0,ROUND(O110/$D110*$C110,2)) -> 0 | R110: =IF($D110=0,0,ROUND(Q110/$D110*$C110,2)) -> 0 | T110: =IF($D110=0,0,ROUND(S110/$D110*$C110,2)) -> 0 | V110: =IF($D110=0,0,ROUND(U110/$D110*$C110,2)) -> 0 | X110: =IF($D110=0,0,ROUND(W110/$D110*$C110,2)) -> 0 | Z110: =IF($D110=0,0,ROUND(Y110/$D110*$C110,2)) -> 0 | AA110: =D110-E110 -> 0
A111: 合计 | C111: =SUM(C81:C110) -> 0 | D111: =SUM(D81:D110) -> 0 | E111: =SUM(E81:E110) -> 0 | F111: =SUM(F81:F110) -> 0 | G111: =SUM(G81:G110) -> 0 | H111: =SUM(H81:H110) -> 0 | I111: =SUM(I81:I110) -> 0 | J111: =SUM(J81:J110) -> 0 | ... Z111: =SUM(Z81:Z110) -> 0
B114: 2025年4月份研发人员工资项目分摊表
A116: 序号 | B116: 姓名 | C116: 月工资 | D116: 出勤天数 | E116: 研发天数合计 | F116: 研发工资合计 | G116: =立项!$A$3 -> RD01 | I116: =立项!$A$4 -> RD02 | K116: =立项!$A$5 -> RD03 | M116: =立项!$A$6 -> RD04 | O116: =立项!$A$7 -> RD05 | Q116: =立项!$A$8 -> RD06 | S116: =立项!$A$9 -> RD07 | U116: =立项!$A$10 -> RD08 | W116: =立项!$A$11 -> RD09 | Y116: =立项!$A$12 -> RD10
G117: =立项!C3 -> 0 | I117: =立项!C4 -> 0 | K117: =立项!C5 -> 0 | M117: =立项!C6 -> 0 | O117: =立项!C7 -> 0 | Q117: =立项!C8 -> 0 | S117: =立项!C9 -> 0 | U117: =立项!C10 -> 0 | W117: =立项!C11 -> 0 | Y117: =立项!C12 -> 0
G118: 研发天数 | H118: 研发工资 | I118: 研发天数 | J118: 研发工资 | K118: 研发天数 | L118: 研发工资 | M118: 研发天数 | N118: 研发工资 | O118: 研发天数 | P118: 研发工资 | Q118: 研发天数 | R118: 研发工资 | S118: 研发天数 | T118: 研发工资 | U118: 研发天数 | V118: 研发工资 | W118: 研发天数 | X118: 研发工资 | Y118: 研发天数 | Z118: 研发工资
A119: 1 | E119: =G119+I119+K119+M119+O119+Q119+S119+U119+W119+Y119 -> 0 | F119: =H119+J119+L119+N119+P119+R119+T119+V119+X119+Z119 -> 0 | H119: =IF($D119=0,0,ROUND(G119/$D119*$C119,2)) -> 0 | J119: =IF($D119=0,0,ROUND(I119/$D119*$C119,2)) -> 0 | L119: =IF($D119=0,0,ROUND(K119/$D119*$C119,2)) -> 0 | N119: =IF($D119=0,0,ROUND(M119/$D119*$C119,2)) -> 0 | P119: =IF($D119=0,0,ROUND(O119/$D119*$C119,2)) -> 0 | R119: =IF($D119=0,0,ROUND(Q119/$D119*$C119,2)) -> 0 | T119: =IF($D119=0,0,ROUND(S119/$D119*$C119,2)) -> 0 | V119: =IF($D119=0,0,ROUND(U119/$D119*$C119,2)) -> 0 | X119: =IF($D119=0,0,ROUND(W119/$D119*$C119,2)) -> 0 | Z119: =IF($D119=0,0,ROUND(Y119/$D119*$C119,2)) -> 0 | AA119: =D119-E119 -> 0
A120: 2 | E120: =G120+I120+K120+M120+O120+Q120+S120+U120+W120+Y120 -> 0 | F120: =H120+J120+L120+N120+P120+R120+T120+V120+X120+Z120 -> 0 | H120: =IF($D120=0,0,ROUND(G120/$D120*$C120,2)) -> 0 | J120: =IF($D120=0,0,ROUND(I120/$D120*$C120,2)) -> 0 | L120: =IF($D120=0,0,ROUND(K120/$D120*$C120,2)) -> 0 | N120: =IF($D120=0,0,ROUND(M120/$D120*$C120,2)) -> 0 | P120: =IF($D120=0,0,ROUND(O120/$D120*$C120,2)) -> 0 | R120: =IF($D120=0,0,ROUND(Q120/$D120*$C120,2)) -> 0 | T120: =IF($D120=0,0,ROUND(S120/$D120*$C120,2)) -> 0 | V120: =IF($D120=0,0,ROUND(U120/$D120*$C120,2)) -> 0 | X120: =IF($D120=0,0,ROUND(W120/$D120*$C120,2)) -> 0 | Z120: =IF($D120=0,0,ROUND(Y120/$D120*$C120,2)) -> 0 | AA120: =D120-E120 -> 0
A121: 3 | E121: =G121+I121+K121+M121+O121+Q121+S121+U121+W121+Y121 -> 0 | F121: =H121+J121+L121+N121+P121+R121+T121+V121+X121+Z121 -> 0 | H121: =IF($D121=0,0,ROUND(G121/$D121*$C121,2)) -> 0 | J121: =IF($D121=0,0,ROUND(I121/$D121*$C121,2)) -> 0 | L121: =IF($D121=0,0,ROUND(K121/$D121*$C121,2)) -> 0 | N121: =IF($D121=0,0,ROUND(M121/$D121*$C121,2)) -> 0 | P121: =IF($D121=0,0,ROUND(O121/$D121*$C121,2)) -> 0 | R121: =IF($D121=0,0,ROUND(Q121/$D121*$C121,2)) -> 0 | T121: =IF($D121=0,0,ROUND(S121/$D121*$C121,2)) -> 0 | V121: =IF($D121=0,0,ROUND(U121/$D121*$C121,2)) -> 0 | X121: =IF($D121=0,0,ROUND(W121/$D121*$C121,2)) -> 0 | Z121: =IF($D121=0,0,ROUND(Y121/$D121*$C121,2)) -> 0 | AA121: =D121-E121 -> 0
A122: 4 | E122: =G122+I122+K122+M122+O122+Q122+S122+U122+W122+Y122 -> 0 | F122: =H122+J122+L122+N122+P122+R122+T122+V122+X122+Z122 -> 0 | H122: =IF($D122=0,0,ROUND(G122/$D122*$C122,2)) -> 0 | J122: =IF($D122=0,0,ROUND(I122/$D122*$C122,2)) -> 0 | L122: =IF($D122=0,0,ROUND(K122/$D122*$C122,2)) -> 0 | N122: =IF($D122=0,0,ROUND(M122/$D122*$C122,2)) -> 0 | P122: =IF($D122=0,0,ROUND(O122/$D122*$C122,2)) -> 0 | R122: =IF($D122=0,0,ROUND(Q122/$D122*$C122,2)) -> 0 | T122: =IF($D122=0,0,ROUND(S122/$D122*$C122,2)) -> 0 | V122: =IF($D122=0,0,ROUND(U122/$D122*$C122,2)) -> 0 | X122: =IF($D122=0,0,ROUND(W122/$D122*$C122,2)) -> 0 | Z122: =IF($D122=0,0,ROUND(Y122/$D122*$C122,2)) -> 0 | AA122: =D122-E122 -> 0
A123: 5 | E123: =G123+I123+K123+M123+O123+Q123+S123+U123+W123+Y123 -> 0 | F123: =H123+J123+L123+N123+P123+R123+T123+V123+X123+Z123 -> 0 | H123: =IF($D123=0,0,ROUND(G123/$D123*$C123,2)) -> 0 | J123: =IF($D123=0,0,ROUND(I123/$D123*$C123,2)) -> 0 | L123: =IF($D123=0,0,ROUND(K123/$D123*$C123,2)) -> 0 | N123: =IF($D123=0,0,ROUND(M123/$D123*$C123,2)) -> 0 | P123: =IF($D123=0,0,ROUND(O123/$D123*$C123,2)) -> 0 | R123: =IF($D123=0,0,ROUND(Q123/$D123*$C123,2)) -> 0 | T123: =IF($D123=0,0,ROUND(S123/$D123*$C123,2)) -> 0 | V123: =IF($D123=0,0,ROUND(U123/$D123*$C123,2)) -> 0 | X123: =IF($D123=0,0,ROUND(W123/$D123*$C123,2)) -> 0 | Z123: =IF($D123=0,0,ROUND(Y123/$D123*$C123,2)) -> 0 | AA123: =D123-E123 -> 0
A124: 6 | E124: =G124+I124+K124+M124+O124+Q124+S124+U124+W124+Y124 -> 0 | F124: =H124+J124+L124+N124+P124+R124+T124+V124+X124+Z124 -> 0 | H124: =IF($D124=0,0,ROUND(G124/$D124*$C124,2)) -> 0 | J124: =IF($D124=0,0,ROUND(I124/$D124*$C124,2)) -> 0 | L124: =IF($D124=0,0,ROUND(K124/$D124*$C124,2)) -> 0 | N124: =IF($D124=0,0,ROUND(M124/$D124*$C124,2)) -> 0 | P124: =IF($D124=0,0,ROUND(O124/$D124*$C124,2)) -> 0 | R124: =IF($D124=0,0,ROUND(Q124/$D124*$C124,2)) -> 0 | T124: =IF($D124=0,0,ROUND(S124/$D124*$C124,2)) -> 0 | V124: =IF($D124=0,0,ROUND(U124/$D124*$C124,2)) -> 0 | X124: =IF($D124=0,0,ROUND(W124/$D124*$C124,2)) -> 0 | Z124: =IF($D124=0,0,ROUND(Y124/$D124*$C124,2)) -> 0 | AA124: =D124-E124 -> 0
A125: 7 | E125: =G125+I125+K125+M125+O125+Q125+S125+U125+W125+Y125 -> 0 | F125: =H125+J125+L125+N125+P125+R125+T125+V125+X125+Z125 -> 0 | H125: =IF($D125=0,0,ROUND(G125/$D125*$C125,2)) -> 0 | J125: =IF($D125=0,0,ROUND(I125/$D125*$C125,2)) -> 0 | L125: =IF($D125=0,0,ROUND(K125/$D125*$C125,2)) -> 0 | N125: =IF($D125=0,0,ROUND(M125/$D125*$C125,2)) -> 0 | P125: =IF($D125=0,0,ROUND(O125/$D125*$C125,2)) -> 0 | R125: =IF($D125=0,0,ROUND(Q125/$D125*$C125,2)) -> 0 | T125: =IF($D125=0,0,ROUND(S125/$D125*$C125,2)) -> 0 | V125: =IF($D125=0,0,ROUND(U125/$D125*$C125,2)) -> 0 | X125: =IF($D125=0,0,ROUND(W125/$D125*$C125,2)) -> 0 | Z125: =IF($D125=0,0,ROUND(Y125/$D125*$C125,2)) -> 0 | AA125: =D125-E125 -> 0
A126: 8 | E126: =G126+I126+K126+M126+O126+Q126+S126+U126+W126+Y126 -> 0 | F126: =H126+J126+L126+N126+P126+R126+T126+V126+X126+Z126 -> 0 | H126: =IF($D126=0,0,ROUND(G126/$D126*$C126,2)) -> 0 | J126: =IF($D126=0,0,ROUND(I126/$D126*$C126,2)) -> 0 | L126: =IF($D126=0,0,ROUND(K126/$D126*$C126,2)) -> 0 | N126: =IF($D126=0,0,ROUND(M126/$D126*$C126,2)) -> 0 | P126: =IF($D126=0,0,ROUND(O126/$D126*$C126,2)) -> 0 | R126: =IF($D126=0,0,ROUND(Q126/$D126*$C126,2)) -> 0 | T126: =IF($D126=0,0,ROUND(S126/$D126*$C126,2)) -> 0 | V126: =IF($D126=0,0,ROUND(U126/$D126*$C126,2)) -> 0 | X126: =IF($D126=0,0,ROUND(W126/$D126*$C126,2)) -> 0 | Z126: =IF($D126=0,0,ROUND(Y126/$D126*$C126,2)) -> 0 | AA126: =D126-E126 -> 0
A127: 9 | E127: =G127+I127+K127+M127+O127+Q127+S127+U127+W127+Y127 -> 0 | F127: =H127+J127+L127+N127+P127+R127+T127+V127+X127+Z127 -> 0 | H127: =IF($D127=0,0,ROUND(G127/$D127*$C127,2)) -> 0 | J127: =IF($D127=0,0,ROUND(I127/$D127*$C127,2)) -> 0 | L127: =IF($D127=0,0,ROUND(K127/$D127*$C127,2)) -> 0 | N127: =IF($D127=0,0,ROUND(M127/$D127*$C127,2)) -> 0 | P127: =IF($D127=0,0,ROUND(O127/$D127*$C127,2)) -> 0 | R127: =IF($D127=0,0,ROUND(Q127/$D127*$C127,2)) -> 0 | T127: =IF($D127=0,0,ROUND(S127/$D127*$C127,2)) -> 0 | V127: =IF($D127=0,0,ROUND(U127/$D127*$C127,2)) -> 0 | X127: =IF($D127=0,0,ROUND(W127/$D127*$C127,2)) -> 0 | Z127: =IF($D127=0,0,ROUND(Y127/$D127*$C127,2)) -> 0 | AA127: =D127-E127 -> 0
A128: 10 | E128: =G128+I128+K128+M128+O128+Q128+S128+U128+W128+Y128 -> 0 | F128: =H128+J128+L128+N128+P128+R128+T128+V128+X128+Z128 -> 0 | H128: =IF($D128=0,0,ROUND(G128/$D128*$C128,2)) -> 0 | J128: =IF($D128=0,0,ROUND(I128/$D128*$C128,2)) -> 0 | L128: =IF($D128=0,0,ROUND(K128/$D128*$C128,2)) -> 0 | N128: =IF($D128=0,0,ROUND(M128/$D128*$C128,2)) -> 0 | P128: =IF($D128=0,0,ROUND(O128/$D128*$C128,2)) -> 0 | R128: =IF($D128=0,0,ROUND(Q128/$D128*$C128,2)) -> 0 | T128: =IF($D128=0,0,ROUND(S128/$D128*$C128,2)) -> 0 | V128: =IF($D128=0,0,ROUND(U128/$D128*$C128,2)) -> 0 | X128: =IF($D128=0,0,ROUND(W128/$D128*$C128,2)) -> 0 | Z128: =IF($D128=0,0,ROUND(Y128/$D128*$C128,2)) -> 0 | AA128: =D128-E128 -> 0
A129: 11 | E129: =G129+I129+K129+M129+O129+Q129+S129+U129+W129+Y129 -> 0 | F129: =H129+J129+L129+N129+P129+R129+T129+V129+X129+Z129 -> 0 | H129: =IF($D129=0,0,ROUND(G129/$D129*$C129,2)) -> 0 | J129: =IF($D129=0,0,ROUND(I129/$D129*$C129,2)) -> 0 | L129: =IF($D129=0,0,ROUND(K129/$D129*$C129,2)) -> 0 | N129: =IF($D129=0,0,ROUND(M129/$D129*$C129,2)) -> 0 | P129: =IF($D129=0,0,ROUND(O129/$D129*$C129,2)) -> 0 | R129: =IF($D129=0,0,ROUND(Q129/$D129*$C129,2)) -> 0 | T129: =IF($D129=0,0,ROUND(S129/$D129*$C129,2)) -> 0 | V129: =IF($D129=0,0,ROUND(U129/$D129*$C129,2)) -> 0 | X129: =IF($D129=0,0,ROUND(W129/$D129*$C129,2)) -> 0 | Z129: =IF($D129=0,0,ROUND(Y129/$D129*$C129,2)) -> 0 | AA129: =D129-E129 -> 0
A130: 12 | E130: =G130+I130+K130+M130+O130+Q130+S130+U130+W130+Y130 -> 0 | F130: =H130+J130+L130+N130+P130+R130+T130+V130+X130+Z130 -> 0 | H130: =IF($D130=0,0,ROUND(G130/$D130*$C130,2)) -> 0 | J130: =IF($D130=0,0,ROUND(I130/$D130*$C130,2)) -> 0 | L130: =IF($D130=0,0,ROUND(K130/$D130*$C130,2)) -> 0 | N130: =IF($D130=0,0,ROUND(M130/$D130*$C130,2)) -> 0 | P130: =IF($D130=0,0,ROUND(O130/$D130*$C130,2)) -> 0 | R130: =IF($D130=0,0,ROUND(Q130/$D130*$C130,2)) -> 0 | T130: =IF($D130=0,0,ROUND(S130/$D130*$C130,2)) -> 0 | V130: =IF($D130=0,0,ROUND(U130/$D130*$C130,2)) -> 0 | X130: =IF($D130=0,0,ROUND(W130/$D130*$C130,2)) -> 0 | Z130: =IF($D130=0,0,ROUND(Y130/$D130*$C130,2)) -> 0 | AA130: =D130-E130 -> 0
... A148: 30 | E148: =G148+I148+K148+M148+O148+Q148+S148+U148+W148+Y148 -> 0 | F148: =H148+J148+L148+N148+P148+R148+T148+V148+X148+Z148 -> 0 | H148: =IF($D148=0,0,ROUND(G148/$D148*$C148,2)) -> 0 | J148: =IF($D148=0,0,ROUND(I148/$D148*$C148,2)) -> 0 | L148: =IF($D148=0,0,ROUND(K148/$D148*$C148,2)) -> 0 | N148: =IF($D148=0,0,ROUND(M148/$D148*$C148,2)) -> 0 | P148: =IF($D148=0,0,ROUND(O148/$D148*$C148,2)) -> 0 | R148: =IF($D148=0,0,ROUND(Q148/$D148*$C148,2)) -> 0 | T148: =IF($D148=0,0,ROUND(S148/$D148*$C148,2)) -> 0 | V148: =IF($D148=0,0,ROUND(U148/$D148*$C148,2)) -> 0 | X148: =IF($D148=0,0,ROUND(W148/$D148*$C148,2)) -> 0 | Z148: =IF($D148=0,0,ROUND(Y148/$D148*$C148,2)) -> 0 | AA148: =D148-E148 -> 0
A149: 合计 | C149: =SUM(C119:C148) -> 0 | D149: =SUM(D119:D148) -> 0 | E149: =SUM(E119:E148) -> 0 | F149: =SUM(F119:F148) -> 0 | G149: =SUM(G119:G148) -> 0 | H149: =SUM(H119:H148) -> 0 | I149: =SUM(I119:I148) -> 0 | J149: =SUM(J119:J148) -> 0 | ... Z149: =SUM(Z119:Z148) -> 0
B152: 2025年5月份研发人员工资项目分摊表
A154: 序号 | B154: 姓名 | C154: 月工资 | D154: 出勤天数 | E154: 研发天数合计 | F154: 研发工资合计 | G154: =立项!$A$3 -> RD01 | I154: =立项!$A$4 -> RD02 | K154: =立项!$A$5 -> RD03 | M154: =立项!$A$6 -> RD04 | O154: =立项!$A$7 -> RD05 | Q154: =立项!$A$8 -> RD06 | S154: =立项!$A$9 -> RD07 | U154: =立项!$A$10 -> RD08 | W154: =立项!$A$11 -> RD09 | Y154: =立项!$A$12 -> RD10
G155: =立项!C3 -> 0 | I155: =立项!C4 -> 0 | K155: =立项!C5 -> 0 | M155: =立项!C6 -> 0 | O155: =立项!C7 -> 0 | Q155: =立项!C8 -> 0 | S155: =立项!C9 -> 0 | U155: =立项!C10 -> 0 | W155: =立项!C11 -> 0 | Y155: =立项!C12 -> 0
G156: 研发天数 | H156: 研发工资 | I156: 研发天数 | J156: 研发工资 | K156: 研发天数 | L156: 研发工资 | M156: 研发天数 | N156: 研发工资 | O156: 研发天数 | P156: 研发工资 | Q156: 研发天数 | R156: 研发工资 | S156: 研发天数 | T156: 研发工资 | U156: 研发天数 | V156: 研发工资 | W156: 研发天数 | X156: 研发工资 | Y156: 研发天数 | Z156: 研发工资
A157: 1 | E157: =G157+I157+K157+M157+O157+Q157+S157+U157+W157+Y157 -> 0 | F157: =H157+J157+L157+N157+P157+R157+T157+V157+X157+Z157 -> 0 | H157: =IF($D157=0,0,ROUND(G157/$D157*$C157,2)) -> 0 | J157: =IF($D157=0,0,ROUND(I157/$D157*$C157,2)) -> 0 | L157: =IF($D157=0,0,ROUND(K157/$D157*$C157,2)) -> 0 | N157: =IF($D157=0,0,ROUND(M157/$D157*$C157,2)) -> 0 | P157: =IF($D157=0,0,ROUND(O157/$D157*$C157,2)) -> 0 | R157: =IF($D157=0,0,ROUND(Q157/$D157*$C157,2)) -> 0 | T157: =IF($D157=0,0,ROUND(S157/$D157*$C157,2)) -> 0 | V157: =IF($D157=0,0,ROUND(U157/$D157*$C157,2)) -> 0 | X157: =IF($D157=0,0,ROUND(W157/$D157*$C157,2)) -> 0 | Z157: =IF($D157=0,0,ROUND(Y157/$D157*$C157,2)) -> 0 | AA157: =D157-E157 -> 0
A158: 2 | E158: =G158+I158+K158+M158+O158+Q158+S158+U158+W158+Y158 -> 0 | F158: =H158+J158+L158+N158+P158+R158+T158+V158+X158+Z158 -> 0 | H158: =IF($D158=0,0,ROUND(G158/$D158*$C158,2)) -> 0 | J158: =IF($D158=0,0,ROUND(I158/$D158*$C158,2)) -> 0 | L158: =IF($D158=0,0,ROUND(K158/$D158*$C158,2)) -> 0 | N158: =IF($D158=0,0,ROUND(M158/$D158*$C158,2)) -> 0 | P158: =IF($D158=0,0,ROUND(O158/$D158*$C158,2)) -> 0 | R158: =IF($D158=0,0,ROUND(Q158/$D158*$C158,2)) -> 0 | T158: =IF($D158=0,0,ROUND(S158/$D158*$C158,2)) -> 0 | V158: =IF($D158=0,0,ROUND(U158/$D158*$C158,2)) -> 0 | X158: =IF($D158=0,0,ROUND(W158/$D158*$C158,2)) -> 0 | Z158: =IF($D158=0,0,ROUND(Y158/$D158*$C158,2)) -> 0 | AA158: =D158-E158 -> 0
A159: 3 | E159: =G159+I159+K159+M159+O159+Q159+S159+U159+W159+Y159 -> 0 | F159: =H159+J159+L159+N159+P159+R159+T159+V159+X159+Z159 -> 0 | H159: =IF($D159=0,0,ROUND(G159/$D159*$C159,2)) -> 0 | J159: =IF($D159=0,0,ROUND(I159/$D159*$C159,2)) -> 0 | L159: =IF($D159=0,0,ROUND(K159/$D159*$C159,2)) -> 0 | N159: =IF($D159=0,0,ROUND(M159/$D159*$C159,2)) -> 0 | P159: =IF($D159=0,0,ROUND(O159/$D159*$C159,2)) -> 0 | R159: =IF($D159=0,0,ROUND(Q159/$D159*$C159,2)) -> 0 | T159: =IF($D159=0,0,ROUND(S159/$D159*$C159,2)) -> 0 | V159: =IF($D159=0,0,ROUND(U159/$D159*$C159,2)) -> 0 | X159: =IF($D159=0,0,ROUND(W159/$D159*$C159,2)) -> 0 | Z159: =IF($D159=0,0,ROUND(Y159/$D159*$C159,2)) -> 0 | AA159: =D159-E159 -> 0
A160: 4 | E160: =G160+I160+K160+M160+O160+Q160+S160+U160+W160+Y160 -> 0 | F160: =H160+J160+L160+N160+P160+R160+T160+V160+X160+Z160 -> 0 | H160: =IF($D160=0,0,ROUND(G160/$D160*$C160,2)) -> 0 | J160: =IF($D160=0,0,ROUND(I160/$D160*$C160,2)) -> 0 | L160: =IF($D160=0,0,ROUND(K160/$D160*$C160,2)) -> 0 | N160: =IF($D160=0,0,ROUND(M160/$D160*$C160,2)) -> 0 | P160: =IF($D160=0,0,ROUND(O160/$D160*$C160,2)) -> 0 | R160: =IF($D160=0,0,ROUND(Q160/$D160*$C160,2)) -> 0 | T160: =IF($D160=0,0,ROUND(S160/$D160*$C160,2)) -> 0 | V160: =IF($D160=0,0,ROUND(U160/$D160*$C160,2)) -> 0 | X160: =IF($D160=0,0,ROUND(W160/$D160*$C160,2)) -> 0 | Z160: =IF($D160=0,0,ROUND(Y160/$D160*$C160,2)) -> 0 | AA160: =D160-E160 -> 0
A161: 5 | E161: =G161+I161+K161+M161+O161+Q161+S161+U161+W161+Y161 -> 0 | F161: =H161+J161+L161+N161+P161+R161+T161+V161+X161+Z161 -> 0 | H161: =IF($D161=0,0,ROUND(G161/$D161*$C161,2)) -> 0 | J161: =IF($D161=0,0,ROUND(I161/$D161*$C161,2)) -> 0 | L161: =IF($D161=0,0,ROUND(K161/$D161*$C161,2)) -> 0 | N161: =IF($D161=0,0,ROUND(M161/$D161*$C161,2)) -> 0 | P161: =IF($D161=0,0,ROUND(O161/$D161*$C161,2)) -> 0 | R161: =IF($D161=0,0,ROUND(Q161/$D161*$C161,2)) -> 0 | T161: =IF($D161=0,0,ROUND(S161/$D161*$C161,2)) -> 0 | V161: =IF($D161=0,0,ROUND(U161/$D161*$C161,2)) -> 0 | X161: =IF($D161=0,0,ROUND(W161/$D161*$C161,2)) -> 0 | Z161: =IF($D161=0,0,ROUND(Y161/$D161*$C161,2)) -> 0 | AA161: =D161-E161 -> 0
A162: 6 | E162: =G162+I162+K162+M162+O162+Q162+S162+U162+W162+Y162 -> 0 | F162: =H162+J162+L162+N162+P162+R162+T162+V162+X162+Z162 -> 0 | H162: =IF($D162=0,0,ROUND(G162/$D162*$C162,2)) -> 0 | J162: =IF($D162=0,0,ROUND(I162/$D162*$C162,2)) -> 0 | L162: =IF($D162=0,0,ROUND(K162/$D162*$C162,2)) -> 0 | N162: =IF($D162=0,0,ROUND(M162/$D162*$C162,2)) -> 0 | P162: =IF($D162=0,0,ROUND(O162/$D162*$C162,2)) -> 0 | R162: =IF($D162=0,0,ROUND(Q162/$D162*$C162,2)) -> 0 | T162: =IF($D162=0,0,ROUND(S162/$D162*$C162,2)) -> 0 | V162: =IF($D162=0,0,ROUND(U162/$D162*$C162,2)) -> 0 | X162: =IF($D162=0,0,ROUND(W162/$D162*$C162,2)) -> 0 | Z162: =IF($D162=0,0,ROUND(Y162/$D162*$C162,2)) -> 0 | AA162: =D162-E162 -> 0
A163: 7 | E163: =G163+I163+K163+M163+O163+Q163+S163+U163+W163+Y163 -> 0 | F163: =H163+J163+L163+N163+P163+R163+T163+V163+X163+Z163 -> 0 | H163: =IF($D163=0,0,ROUND(G163/$D163*$C163,2)) -> 0 | J163: =IF($D163=0,0,ROUND(I163/$D163*$C163,2)) -> 0 | L163: =IF($D163=0,0,ROUND(K163/$D163*$C163,2)) -> 0 | N163: =IF($D163=0,0,ROUND(M163/$D163*$C163,2)) -> 0 | P163: =IF($D163=0,0,ROUND(O163/$D163*$C163,2)) -> 0 | R163: =IF($D163=0,0,ROUND(Q163/$D163*$C163,2)) -> 0 | T163: =IF($D163=0,0,ROUND(S163/$D163*$C163,2)) -> 0 | V163: =IF($D163=0,0,ROUND(U163/$D163*$C163,2)) -> 0 | X163: =IF($D163=0,0,ROUND(W163/$D163*$C163,2)) -> 0 | Z163: =IF($D163=0,0,ROUND(Y163/$D163*$C163,2)) -> 0 | AA163: =D163-E163 -> 0
A164: 8 | E164: =G164+I164+K164+M164+O164+Q164+S164+U164+W164+Y164 -> 0 | F164: =H164+J164+L164+N164+P164+R164+T164+V164+X164+Z164 -> 0 | H164: =IF($D164=0,0,ROUND(G164/$D164*$C164,2)) -> 0 | J164: =IF($D164=0,0,ROUND(I164/$D164*$C164,2)) -> 0 | L164: =IF($D164=0,0,ROUND(K164/$D164*$C164,2)) -> 0 | N164: =IF($D164=0,0,ROUND(M164/$D164*$C164,2)) -> 0 | P164: =IF($D164=0,0,ROUND(O164/$D164*$C164,2)) -> 0 | R164: =IF($D164=0,0,ROUND(Q164/$D164*$C164,2)) -> 0 | T164: =IF($D164=0,0,ROUND(S164/$D164*$C164,2)) -> 0 | V164: =IF($D164=0,0,ROUND(U164/$D164*$C164,2)) -> 0 | X164: =IF($D164=0,0,ROUND(W164/$D164*$C164,2)) -> 0 | Z164: =IF($D164=0,0,ROUND(Y164/$D164*$C164,2)) -> 0 | AA164: =D164-E164 -> 0
A165: 9 | E165: =G165+I165+K165+M165+O165+Q165+S165+U165+W165+Y165 -> 0 | F165: =H165+J165+L165+N165+P165+R165+T165+V165+X165+Z165 -> 0 | H165: =IF($D165=0,0,ROUND(G165/$D165*$C165,2)) -> 0 | J165: =IF($D165=0,0,ROUND(I165/$D165*$C165,2)) -> 0 | L165: =IF($D165=0,0,ROUND(K165/$D165*$C165,2)) -> 0 | N165: =IF($D165=0,0,ROUND(M165/$D165*$C165,2)) -> 0 | P165: =IF($D165=0,0,ROUND(O165/$D165*$C165,2)) -> 0 | R165: =IF($D165=0,0,ROUND(Q165/$D165*$C165,2)) -> 0 | T165: =IF($D165=0,0,ROUND(S165/$D165*$C165,2)) -> 0 | V165: =IF($D165=0,0,ROUND(U165/$D165*$C165,2)) -> 0 | X165: =IF($D165=0,0,ROUND(W165/$D165*$C165,2)) -> 0 | Z165: =IF($D165=0,0,ROUND(Y165/$D165*$C165,2)) -> 0 | AA165: =D165-E165 -> 0
A166: 10 | E166: =G166+I166+K166+M166+O166+Q166+S166+U166+W166+Y166 -> 0 | F166: =H166+J166+L166+N166+P166+R166+T166+V166+X166+Z166 -> 0 | H166: =IF($D166=0,0,ROUND(G166/$D166*$C166,2)) -> 0 | J166: =IF($D166=0,0,ROUND(I166/$D166*$C166,2)) -> 0 | L166: =IF($D166=0,0,ROUND(K166/$D166*$C166,2)) -> 0 | N166: =IF($D166=0,0,ROUND(M166/$D166*$C166,2)) -> 0 | P166: =IF($D166=0,0,ROUND(O166/$D166*$C166,2)) -> 0 | R166: =IF($D166=0,0,ROUND(Q166/$D166*$C166,2)) -> 0 | T166: =IF($D166=0,0,ROUND(S166/$D166*$C166,2)) -> 0 | V166: =IF($D166=0,0,ROUND(U166/$D166*$C166,2)) -> 0 | X166: =IF($D166=0,0,ROUND(W166/$D166*$C166,2)) -> 0 | Z166: =IF($D166=0,0,ROUND(Y166/$D166*$C166,2)) -> 0 | AA166: =D166-E166 -> 0
A167: 11 | E167: =G167+I167+K167+M167+O167+Q167+S167+U167+W167+Y167 -> 0 | F167: =H167+J167+L167+N167+P167+R167+T167+V167+X167+Z167 -> 0 | H167: =IF($D167=0,0,ROUND(G167/$D167*$C167,2)) -> 0 | J167: =IF($D167=0,0,ROUND(I167/$D167*$C167,2)) -> 0 | L167: =IF($D167=0,0,ROUND(K167/$D167*$C167,2)) -> 0 | N167: =IF($D167=0,0,ROUND(M167/$D167*$C167,2)) -> 0 | P167: =IF($D167=0,0,ROUND(O167/$D167*$C167,2)) -> 0 | R167: =IF($D167=0,0,ROUND(Q167/$D167*$C167,2)) -> 0 | T167: =IF($D167=0,0,ROUND(S167/$D167*$C167,2)) -> 0 | V167: =IF($D167=0,0,ROUND(U167/$D167*$C167,2)) -> 0 | X167: =IF($D167=0,0,ROUND(W167/$D167*$C167,2)) -> 0 | Z167: =IF($D167=0,0,ROUND(Y167/$D167*$C167,2)) -> 0 | AA167: =D167-E167 -> 0
A168: 12 | E168: =G168+I168+K168+M168+O168+Q168+S168+U168+W168+Y168 -> 0 | F168: =H168+J168+L168+N168+P168+R168+T168+V168+X168+Z168 -> 0 | H168: =IF($D168=0,0,ROUND(G168/$D168*$C168,2)) -> 0 | J168: =IF($D168=0,0,ROUND(I168/$D168*$C168,2)) -> 0 | L168: =IF($D168=0,0,ROUND(K168/$D168*$C168,2)) -> 0 | N168: =IF($D168=0,0,ROUND(M168/$D168*$C168,2)) -> 0 | P168: =IF($D168=0,0,ROUND(O168/$D168*$C168,2)) -> 0 | R168: =IF($D168=0,0,ROUND(Q168/$D168*$C168,2)) -> 0 | T168: =IF($D168=0,0,ROUND(S168/$D168*$C168,2)) -> 0 | V168: =IF($D168=0,0,ROUND(U168/$D168*$C168,2)) -> 0 | X168: =IF($D168=0,0,ROUND(W168/$D168*$C168,2)) -> 0 | Z168: =IF($D168=0,0,ROUND(Y168/$D168*$C168,2)) -> 0 | AA168: =D168-E168 -> 0
...

Sheet 研发人员考勤表
A1: 研发人员考勤表
A2: 45658
A3: 姓名 | B3: 项目名称 | C3: 1日 | D3: 2日 | E3: 3日 | F3: 4日 | G3: 5日 | H3: 6日 | I3: 7日 | J3: 8日 | K3: 9日 | L3: 10日 | M3: 11日 | N3: 12日 | O3: 13日 | P3: 14日 | Q3: 15日 | R3: 16日 | S3: 17日 | T3: 18日 | U3: 19日 | V3: 20日 | W3: 21日 | X3: 22日 | Y3: 23日 | Z3: 25日 | AA3: 25日 | AB3: 26日 | AC3: 27日 | AD3: 28日 | AE3: 29日 | AF3: 30日 | AG3: 31日 | AH3: 合计 | AI3: 22
B4: RD01 | D4: √ | E4: √ | J4: √ | K4: √ | L4: √ | Q4: √ | R4: √ | S4: √ | X4: √ | Y4: √ | Z4: √ | AE4: √ | AF4: √ | AG4: √ | AH4: =COUNTIF(C4:AG4,"√") -> 14
B5: RD02 | F5: √ | G5: √ | H5: √ | M5: √ | N5: √ | O5: √ | T5: √ | U5: √ | V5: √ | AA5: √ | AB5: √ | AC5: √ | AH5: =COUNTIF(C5:AG5,"√") -> 12
B6: RD03 | AH6: =COUNTIF(C6:AG6,"√") -> 0
B7: RD04 | AH7: =COUNTIF(C7:AG7,"√") -> 0
B8: RD05 | AH8: =COUNTIF(C8:AG8,"√") -> 0
B9: RD01 | D9: √ | E9: √ | F9: √ | G9: √ | H9: √ | J9: √ | K9: √ | L9: √ | M9: √ | N9: √ | O9: √ | Q9: √ | R9: √ | S9: √ | T9: √ | U9: √ | V9: √ | X9: √ | Y9: √ | Z9: √ | AA9: √ | AB9: √ | AC9: √ | AE9: √ | AF9: √ | AG9: √ | AH9: =COUNTIF(C9:AG9,"√") -> 26
B10: RD02 | AH10: =COUNTIF(C10:AG10,"√") -> 0
B11: RD03 | AH11: =COUNTIF(C11:AG11,"√") -> 0
B12: RD04 | AH12: =COUNTIF(C12:AG12,"√") -> 0
B13: RD05 | AH13: =COUNTIF(C13:AG13,"√") -> 0
B14: RD01 | AH14: =COUNTIF(C14:AG14,"√") -> 0
B15: RD02 | AH15: =COUNTIF(C15:AG15,"√") -> 0
B16: RD03 | AH16: =COUNTIF(C16:AG16,"√") -> 0
B17: RD04 | AH17: =COUNTIF(C17:AG17,"√") -> 0
B18: RD05 | AH18: =COUNTIF(C18:AG18,"√") -> 0
B19: RD01 | AH19: =COUNTIF(C19:AG19,"√") -> 0
B20: RD02 | AH20: =COUNTIF(C20:AG20,"√") -> 0
B21: RD03 | AH21: =COUNTIF(C21:AG21,"√") -> 0
... B23: RD05 | AH23: =COUNTIF(C23:AG23,"√") -> 0
A24: 制表： 审核： 人事主管：
A27: 研发人员考勤表
A28: 45689
A29: 姓名 | B29: 项目名称 | C29: 1日 | D29: 2日 | E29: 3日 | F29: 4日 | G29: 5日 | H29: 6日 | I29: 7日 | J29: 8日 | K29: 9日 | L29: 10日 | M29: 11日 | N29: 12日 | O29: 13日 | P29: 14日 | Q29: 15日 | R29: 16日 | S29: 17日 | T29: 18日 | U29: 19日 | V29: 20日 | W29: 21日 | X29: 22日 | Y29: 23日 | Z29: 25日 | AA29: 25日 | AB29: 26日 | AC29: 27日 | AD29: 28日 | AF29: 合计 | AI29: 18
B30: RD01 | C30: √ | D30: √ | I30: √ | J30: √ | K30: √ | V30: √ | W30: √ | AB30: √ | AC30: √ | AF30: =COUNTIF(C30:AE30,"√") -> 9
B31: RD02 | F31: √ | G31: √ | H31: √ | T31: √ | U31: √ | X31: √ | Y31: √ | Z31: √ | AD31: √ | AF31: =COUNTIF(C31:AE31,"√") -> 9
B32: RD03 | AF32: =COUNTIF(C32:AE32,"√") -> 0
B33: RD04 | AF33: =COUNTIF(C33:AE33,"√") -> 0
B34: RD05 | AF34: =COUNTIF(C34:AE34,"√") -> 0
B35: RD01 | C35: √ | D35: √ | F35: √ | G35: √ | H35: √ | I35: √ | J35: √ | K35: √ | T35: √ | U35: √ | V35: √ | W35: √ | X35: √ | Y35: √ | Z35: √ | AB35: √ | AC35: √ | AD35: √ | AF35: =COUNTIF(C35:AE35,"√") -> 18
B36: RD02 | AF36: =COUNTIF(C36:AE36,"√") -> 0
B37: RD03 | AF37: =COUNTIF(C37:AE37,"√") -> 0
B38: RD04 | AF38: =COUNTIF(C38:AE38,"√") -> 0
B39: RD05 | AF39: =COUNTIF(C39:AE39,"√") -> 0
B40: RD01 | AF40: =COUNTIF(C40:AE40,"√") -> 0
B41: RD02 | AF41: =COUNTIF(C41:AE41,"√") -> 0
B42: RD03 | AF42: =COUNTIF(C42:AE42,"√") -> 0
B43: RD04 | AF43: =COUNTIF(C43:AE43,"√") -> 0
B44: RD05 | AF44: =COUNTIF(C44:AE44,"√") -> 0
B45: RD01 | AF45: =COUNTIF(C45:AE45,"√") -> 0
B46: RD02 | AF46: =COUNTIF(C46:AE46,"√") -> 0
B47: RD03 | AF47: =COUNTIF(C47:AE47,"√") -> 0
... B49: RD05 | AF49: =COUNTIF(C49:AE49,"√") -> 0
A50: 制表： 审核： 人事主管：
A53: 研发人员考勤表
A54: 45717
A55: 姓名 | B55: 项目名称 | C55: 1日 | D55: 2日 | E55: 3日 | F55: 4日 | G55: 5日 | H55: 6日 | I55: 7日 | J55: 8日 | K55: 9日 | L55: 10日 | M55: 11日 | N55: 12日 | O55: 13日 | P55: 14日 | Q55: 15日 | R55: 16日 | S55: 17日 | T55: 18日 | U55: 19日 | V55: 20日 | W55: 21日 | X55: 22日 | Y55: 23日 | Z55: 25日 | AA55: 25日 | AB55: 26日 | AC55: 27日 | AD55: 28日 | AE55: 29日 | AF55: 30日 | AG55: 31日 | AH55: 合计 | AI55: 21
B56: RD01 | C56: √ | D56: √ | I56: √ | J56: √ | K56: √ | P56: √ | Q56: √ | R56: √ | W56: √ | X56: √ | Y56: √ | AD56: √ | AE56: √ | AF56: √ | AH56: =COUNTIF(C56:AG56,"√") -> 14
B57: RD02 | F57: √ | G57: √ | H57: √ | M57: √ | N57: √ | O57: √ | T57: √ | U57: √ | V57: √ | AA57: √ | AB57: √ | AC57: √ | AH57: =COUNTIF(C57:AG57,"√") -> 12
B58: RD03 | AH58: =COUNTIF(C58:AG58,"√") -> 0
B59: RD04 | AH59: =COUNTIF(C59:AG59,"√") -> 0
B60: RD05 | AH60: =COUNTIF(C60:AG60,"√") -> 0
B61: RD01 | C61: √ | D61: √ | F61: √ | G61: √ | H61: √ | I61: √ | J61: √ | K61: √ | M61: √ | N61: √ | O61: √ | P61: √ | Q61: √ | R61: √ | T61: √ | U61: √ | V61: √ | W61: √ | X61: √ | Y61: √ | AA61: √ | AB61: √ | AC61: √ | AD61: √ | AE61: √ | AF61: √ | AH61: =COUNTIF(C61:AG61,"√") -> 26
B62: RD02 | AH62: =COUNTIF(C62:AG62,"√") -> 0
B63: RD03 | AH63: =COUNTIF(C63:AG63,"√") -> 0
B64: RD04 | AH64: =COUNTIF(C64:AG64,"√") -> 0
B65: RD05 | AH65: =COUNTIF(C65:AG65,"√") -> 0
B66: RD01 | AH66: =COUNTIF(C66:AG66,"√") -> 0
B67: RD02 | AH67: =COUNTIF(C67:AG67,"√") -> 0
B68: RD03 | AH68: =COUNTIF(C68:AG68,"√") -> 0
B69: RD04 | AH69: =COUNTIF(C69:AG69,"√") -> 0
B70: RD05 | AH70: =COUNTIF(C70:AG70,"√") -> 0
B71: RD01 | AH71: =COUNTIF(C71:AG71,"√") -> 0
B72: RD02 | AH72: =COUNTIF(C72:AG72,"√") -> 0
B73: RD03 | AH73: =COUNTIF(C73:AG73,"√") -> 0
... B75: RD05 | AH75: =COUNTIF(C75:AG75,"√") -> 0
A76: 制表： 审核： 人事主管：
A79: 研发人员考勤表
A80: 45748
A81: 姓名 | B81: 项目名称 | C81: 1日 | D81: 2日 | E81: 3日 | F81: 4日 | G81: 5日 | H81: 6日 | I81: 7日 | J81: 8日 | K81: 9日 | L81: 10日 | M81: 11日 | N81: 12日 | O81: 13日 | P81: 14日 | Q81: 15日 | R81: 16日 | S81: 17日 | T81: 18日 | U81: 19日 | V81: 20日 | W81: 21日 | X81: 22日 | Y81: 23日 | Z81: 25日 | AA81: 25日 | AB81: 26日 | AC81: 27日 | AD81: 28日 | AE81: 29日 | AF81: 30日 | AG81: 合计 | AI81: 22
B82: RD01 | C82: √ | D82: √ | E82: √ | L82: √ | M82: √ | N82: √ | O82: √ | T82: √ | U82: √ | V82: √ | AA82: √ | AB82: √ | AG82: =COUNTIF(C82:AF82,"√") -> 12
B83: RD02 | I83: √ | J83: √ | K83: √ | Q83: √ | R83: √ | S83: √ | X83: √ | Y83: √ | Z83: √ | AD83: √ | AE83: √ | AF83: √ | AG83: =COUNTIF(C83:AF83,"√") -> 12
B84: RD03 | AG84: =COUNTIF(C84:AF84,"√") -> 0
B85: RD04 | AG85: =COUNTIF(C85:AF85,"√") -> 0
B86: RD05 | AG86: =COUNTIF(C86:AF86,"√") -> 0
B87: RD01 | C87: √ | D87: √ | E87: √ | I87: √ | J87: √ | K87: √ | L87: √ | M87: √ | N87: √ | O87: √ | Q87: √ | R87: √ | S87: √ | T87: √ | U87: √ | V87: √ | X87: √ | Y87: √ | Z87: √ | AA87: √ | AB87: √ | AD87: √ | AE87: √ | AF87: √ | AG87: =COUNTIF(C87:AF87,"√") -> 24
B88: RD02 | AG88: =COUNTIF(C88:AF88,"√") -> 0
B89: RD03 | AG89: =COUNTIF(C89:AF89,"√") -> 0
B90: RD04 | AG90: =COUNTIF(C90:AF90,"√") -> 0
B91: RD05 | AG91: =COUNTIF(C91:AF91,"√") -> 0
B92: RD01 | AG92: =COUNTIF(C92:AF92,"√") -> 0
B93: RD02 | AG93: =COUNTIF(C93:AF93,"√") -> 0
B94: RD03 | AG94: =COUNTIF(C94:AF94,"√") -> 0
B95: RD04 | AG95: =COUNTIF(C95:AF95,"√") -> 0
B96: RD05 | AG96: =COUNTIF(C96:AF96,"√") -> 0
B97: RD01 | AG97: =COUNTIF(C97:AF97,"√") -> 0
B98: RD02 | AG98: =COUNTIF(C98:AF98,"√") -> 0
B99: RD03 | AG99: =COUNTIF(C99:AF99,"√") -> 0
... B101: RD05 | AG101: =COUNTIF(C101:AF101,"√") -> 0
A102: 制表： 审核： 人事主管：
A105: 研发人员考勤表
A106: 45778
A107: 姓名 | B107: 项目名称 | C107: 1日 | D107: 2日 | E107: 3日 | F107: 4日 | G107: 5日 | H107: 6日 | I107: 7日 | J107: 8日 | K107: 9日 | L107: 10日 | M107: 11日 | N107: 12日 | O107: 13日 | P107: 14日 | Q107: 15日 | R107: 16日 | S107: 17日 | T107: 18日 | U107: 19日 | V107: 20日 | W107: 21日 | X107: 22日 | Y107: 23日 | Z107: 25日 | AA107: 25日 | AB107: 26日 | AC107: 27日 | AD107: 28日 | AE107: 29日 | AF107: 30日 | AG107: 31日 | AH107: 合计 | AI107: 21
B108: RD01 | H108: √ | I108: √ | J108: √ | O108: √ | P108: √ | Q108: √ | V108: √ | W108: √ | X108: √ | AC108: √ | AD108: √ | AE108: √ | AH108: =COUNTIF(C108:AG108,"√") -> 12
B109: RD02 | F109: √ | G109: √ | K109: √ | L109: √ | M109: √ | R109: √ | S109: √ | T109: √ | Y109: √ | Z109: √ | AA109: √ | AF109: √ | AG109: √ | AH109: =COUNTIF(C109:AG109,"√") -> 13
B110: RD03 | AH110: =COUNTIF(C110:AG110,"√") -> 0
B111: RD04 | AH111: =COUNTIF(C111:AG111,"√") -> 0
B112: RD05 | AH112: =COUNTIF(C112:AG112,"√") -> 0
...

Sheet 研发人员出勤考勤表
A2: 2023年1月份研发人员考勤表
A4: 姓名 | B4: 星期日 | C4: 星期一 | D4: 星期二 | E4: 星期三 | F4: 星期四 | G4: 星期五 | H4: 星期六 | I4: 星期日 | J4: 星期一 | K4: 星期二 | L4: 星期三 | M4: 星期四 | N4: 星期五 | O4: 星期六 | P4: 星期日 | Q4: 星期一 | R4: 星期二 | S4: 星期三 | T4: 星期四 | U4: 星期五 | V4: 星期六 | W4: 星期日 | X4: 星期一 | Y4: 星期二 | Z4: 星期三 | AA4: 星期四 | AB4: 星期五 | AC4: 星期六 | AD4: 星期日 | AE4: 星期一 | AF4: 星期二 | AG4: 研发天数 | AH4: 出勤天数 | AI4: 研发天数验证 | AJ4: 出勤天数验证
B5: 1 | C5: 2 | D5: 3 | E5: 4 | F5: 5 | G5: 6 | H5: 7 | I5: 8 | J5: 9 | K5: 10 | L5: 11 | M5: 12 | N5: 13 | O5: 14 | P5: 15 | Q5: 16 | R5: 17 | S5: 18 | T5: 19 | U5: 20 | V5: 21 | W5: 22 | X5: 23 | Y5: 24 | Z5: 25 | AA5: 26 | AB5: 27 | AC5: 28 | AD5: 29 | AE5: 30 | AF5: 31
A6: ='人员人工-研发人员工资'!B6 -> 0 | B6: × | C6: × | D6: ● | E6: ● | F6: ● | G6: √ | H6: × | I6: × | J6: ● | K6: ● | L6: ● | M6: ● | N6: √ | O6: × | P6: × | Q6: ▲ | R6: ▲ | S6: ▲ | T6: ▲ | U6: ▲ | V6: × | W6: × | X6: × | Y6: × | Z6: × | AA6: × | AB6: × | AC6: ■ | AD6: ■ | AE6: ■ | AF6: ■ | AG6: =COUNTIF(B6:AF6,"●")+COUNTIF(B6:AF6,"▲")+COUNTIF(B6:AF6,"■")+COUNTIF(B6:AF6,"★")+COUNTIF(B6:AF6,"◆")+COUNTIF(B6:AF6,"✽")+COUNTIF(B6:AF6,"❖")+COUNTIF(B6:AF6,"✪")+COUNTIF(B6:AF6,"✿")+COUNTIF(B6:AF6,"✤") -> 16 | AH6: =COUNTIF(B6:AF6,"●")+COUNTIF(B6:AF6,"▲")+COUNTIF(B6:AF6,"■")+COUNTIF(B6:AF6,"★")+COUNTIF(B6:AF6,"◆")+COUNTIF(B6:AF6,"✽")+COUNTIF(B6:AF6,"❖")+COUNTIF(B6:AF6,"✪")+COUNTIF(B6:AF6,"✿")+COUNTIF(B6:AF6,"✤")+COUNTIF(B6:AF6,"√") -> 18 | AI6: =AG6-'人员人工-研发人员工资'!E6 -> 16 | AJ6: =AH6-'人员人工-研发人员工资'!D6 -> 18
A7: ='人员人工-研发人员工资'!B7 -> 0 | AG7: =COUNTIF(B7:AF7,"●")+COUNTIF(B7:AF7,"▲")+COUNTIF(B7:AF7,"■")+COUNTIF(B7:AF7,"★")+COUNTIF(B7:AF7,"◆")+COUNTIF(B7:AF7,"✽")+COUNTIF(B7:AF7,"❖")+COUNTIF(B7:AF7,"✪")+COUNTIF(B7:AF7,"✿")+COUNTIF(B7:AF7,"✤") -> 0 | AH7: =COUNTIF(B7:AF7,"●")+COUNTIF(B7:AF7,"▲")+COUNTIF(B7:AF7,"■")+COUNTIF(B7:AF7,"★")+COUNTIF(B7:AF7,"◆")+COUNTIF(B7:AF7,"✽")+COUNTIF(B7:AF7,"❖")+COUNTIF(B7:AF7,"✪")+COUNTIF(B7:AF7,"✿")+COUNTIF(B7:AF7,"✤")+COUNTIF(B7:AF7,"√") -> 0 | AI7: =AG7-'人员人工-研发人员工资'!E7 -> 0 | AJ7: =AH7-'人员人工-研发人员工资'!D7 -> 0
A8: ='人员人工-研发人员工资'!B8 -> 0 | AG8: =COUNTIF(B8:AF8,"●")+COUNTIF(B8:AF8,"▲")+COUNTIF(B8:AF8,"■")+COUNTIF(B8:AF8,"★")+COUNTIF(B8:AF8,"◆")+COUNTIF(B8:AF8,"✽")+COUNTIF(B8:AF8,"❖")+COUNTIF(B8:AF8,"✪")+COUNTIF(B8:AF8,"✿")+COUNTIF(B8:AF8,"✤") -> 0 | AH8: =COUNTIF(B8:AF8,"●")+COUNTIF(B8:AF8,"▲")+COUNTIF(B8:AF8,"■")+COUNTIF(B8:AF8,"★")+COUNTIF(B8:AF8,"◆")+COUNTIF(B8:AF8,"✽")+COUNTIF(B8:AF8,"❖")+COUNTIF(B8:AF8,"✪")+COUNTIF(B8:AF8,"✿")+COUNTIF(B8:AF8,"✤")+COUNTIF(B8:AF8,"√") -> 0 | AI8: =AG8-'人员人工-研发人员工资'!E8 -> 0 | AJ8: =AH8-'人员人工-研发人员工资'!D8 -> 0
A9: ='人员人工-研发人员工资'!B9 -> 0 | AG9: =COUNTIF(B9:AF9,"●")+COUNTIF(B9:AF9,"▲")+COUNTIF(B9:AF9,"■")+COUNTIF(B9:AF9,"★")+COUNTIF(B9:AF9,"◆")+COUNTIF(B9:AF9,"✽")+COUNTIF(B9:AF9,"❖")+COUNTIF(B9:AF9,"✪")+COUNTIF(B9:AF9,"✿")+COUNTIF(B9:AF9,"✤") -> 0 | AH9: =COUNTIF(B9:AF9,"●")+COUNTIF(B9:AF9,"▲")+COUNTIF(B9:AF9,"■")+COUNTIF(B9:AF9,"★")+COUNTIF(B9:AF9,"◆")+COUNTIF(B9:AF9,"✽")+COUNTIF(B9:AF9,"❖")+COUNTIF(B9:AF9,"✪")+COUNTIF(B9:AF9,"✿")+COUNTIF(B9:AF9,"✤")+COUNTIF(B9:AF9,"√") -> 0 | AI9: =AG9-'人员人工-研发人员工资'!E9 -> 0 | AJ9: =AH9-'人员人工-研发人员工资'!D9 -> 0
A10: ='人员人工-研发人员工资'!B10 -> 0 | AG10: =COUNTIF(B10:AF10,"●")+COUNTIF(B10:AF10,"▲")+COUNTIF(B10:AF10,"■")+COUNTIF(B10:AF10,"★")+COUNTIF(B10:AF10,"◆")+COUNTIF(B10:AF10,"✽")+COUNTIF(B10:AF10,"❖")+COUNTIF(B10:AF10,"✪")+COUNTIF(B10:AF10,"✿")+COUNTIF(B10:AF10,"✤") -> 0 | AH10: =COUNTIF(B10:AF10,"●")+COUNTIF(B10:AF10,"▲")+COUNTIF(B10:AF10,"■")+COUNTIF(B10:AF10,"★")+COUNTIF(B10:AF10,"◆")+COUNTIF(B10:AF10,"✽")+COUNTIF(B10:AF10,"❖")+COUNTIF(B10:AF10,"✪")+COUNTIF(B10:AF10,"✿")+COUNTIF(B10:AF10,"✤")+COUNTIF(B10:AF10,"√") -> 0 | AI10: =AG10-'人员人工-研发人员工资'!E10 -> 0 | AJ10: =AH10-'人员人工-研发人员工资'!D10 -> 0
A11: ='人员人工-研发人员工资'!B11 -> 0 | AG11: =COUNTIF(B11:AF11,"●")+COUNTIF(B11:AF11,"▲")+COUNTIF(B11:AF11,"■")+COUNTIF(B11:AF11,"★")+COUNTIF(B11:AF11,"◆")+COUNTIF(B11:AF11,"✽")+COUNTIF(B11:AF11,"❖")+COUNTIF(B11:AF11,"✪")+COUNTIF(B11:AF11,"✿")+COUNTIF(B11:AF11,"✤") -> 0 | AH11: =COUNTIF(B11:AF11,"●")+COUNTIF(B11:AF11,"▲")+COUNTIF(B11:AF11,"■")+COUNTIF(B11:AF11,"★")+COUNTIF(B11:AF11,"◆")+COUNTIF(B11:AF11,"✽")+COUNTIF(B11:AF11,"❖")+COUNTIF(B11:AF11,"✪")+COUNTIF(B11:AF11,"✿")+COUNTIF(B11:AF11,"✤")+COUNTIF(B11:AF11,"√") -> 0 | AI11: =AG11-'人员人工-研发人员工资'!E11 -> 0 | AJ11: =AH11-'人员人工-研发人员工资'!D11 -> 0
A12: ='人员人工-研发人员工资'!B12 -> 0 | AG12: =COUNTIF(B12:AF12,"●")+COUNTIF(B12:AF12,"▲")+COUNTIF(B12:AF12,"■")+COUNTIF(B12:AF12,"★")+COUNTIF(B12:AF12,"◆")+COUNTIF(B12:AF12,"✽")+COUNTIF(B12:AF12,"❖")+COUNTIF(B12:AF12,"✪")+COUNTIF(B12:AF12,"✿")+COUNTIF(B12:AF12,"✤") -> 0 | AH12: =COUNTIF(B12:AF12,"●")+COUNTIF(B12:AF12,"▲")+COUNTIF(B12:AF12,"■")+COUNTIF(B12:AF12,"★")+COUNTIF(B12:AF12,"◆")+COUNTIF(B12:AF12,"✽")+COUNTIF(B12:AF12,"❖")+COUNTIF(B12:AF12,"✪")+COUNTIF(B12:AF12,"✿")+COUNTIF(B12:AF12,"✤")+COUNTIF(B12:AF12,"√") -> 0 | AI12: =AG12-'人员人工-研发人员工资'!E12 -> 0 | AJ12: =AH12-'人员人工-研发人员工资'!D12 -> 0
A13: ='人员人工-研发人员工资'!B13 -> 0 | AG13: =COUNTIF(B13:AF13,"●")+COUNTIF(B13:AF13,"▲")+COUNTIF(B13:AF13,"■")+COUNTIF(B13:AF13,"★")+COUNTIF(B13:AF13,"◆")+COUNTIF(B13:AF13,"✽")+COUNTIF(B13:AF13,"❖")+COUNTIF(B13:AF13,"✪")+COUNTIF(B13:AF13,"✿")+COUNTIF(B13:AF13,"✤") -> 0 | AH13: =COUNTIF(B13:AF13,"●")+COUNTIF(B13:AF13,"▲")+COUNTIF(B13:AF13,"■")+COUNTIF(B13:AF13,"★")+COUNTIF(B13:AF13,"◆")+COUNTIF(B13:AF13,"✽")+COUNTIF(B13:AF13,"❖")+COUNTIF(B13:AF13,"✪")+COUNTIF(B13:AF13,"✿")+COUNTIF(B13:AF13,"✤")+COUNTIF(B13:AF13,"√") -> 0 | AI13: =AG13-'人员人工-研发人员工资'!E13 -> 0 | AJ13: =AH13-'人员人工-研发人员工资'!D13 -> 0
A14: ='人员人工-研发人员工资'!B14 -> 0 | AG14: =COUNTIF(B14:AF14,"●")+COUNTIF(B14:AF14,"▲")+COUNTIF(B14:AF14,"■")+COUNTIF(B14:AF14,"★")+COUNTIF(B14:AF14,"◆")+COUNTIF(B14:AF14,"✽")+COUNTIF(B14:AF14,"❖")+COUNTIF(B14:AF14,"✪")+COUNTIF(B14:AF14,"✿")+COUNTIF(B14:AF14,"✤") -> 0 | AH14: =COUNTIF(B14:AF14,"●")+COUNTIF(B14:AF14,"▲")+COUNTIF(B14:AF14,"■")+COUNTIF(B14:AF14,"★")+COUNTIF(B14:AF14,"◆")+COUNTIF(B14:AF14,"✽")+COUNTIF(B14:AF14,"❖")+COUNTIF(B14:AF14,"✪")+COUNTIF(B14:AF14,"✿")+COUNTIF(B14:AF14,"✤")+COUNTIF(B14:AF14,"√") -> 0 | AI14: =AG14-'人员人工-研发人员工资'!E14 -> 0 | AJ14: =AH14-'人员人工-研发人员工资'!D14 -> 0
A15: ='人员人工-研发人员工资'!B15 -> 0 | AG15: =COUNTIF(B15:AF15,"●")+COUNTIF(B15:AF15,"▲")+COUNTIF(B15:AF15,"■")+COUNTIF(B15:AF15,"★")+COUNTIF(B15:AF15,"◆")+COUNTIF(B15:AF15,"✽")+COUNTIF(B15:AF15,"❖")+COUNTIF(B15:AF15,"✪")+COUNTIF(B15:AF15,"✿")+COUNTIF(B15:AF15,"✤") -> 0 | AH15: =COUNTIF(B15:AF15,"●")+COUNTIF(B15:AF15,"▲")+COUNTIF(B15:AF15,"■")+COUNTIF(B15:AF15,"★")+COUNTIF(B15:AF15,"◆")+COUNTIF(B15:AF15,"✽")+COUNTIF(B15:AF15,"❖")+COUNTIF(B15:AF15,"✪")+COUNTIF(B15:AF15,"✿")+COUNTIF(B15:AF15,"✤")+COUNTIF(B15:AF15,"√") -> 0 | AI15: =AG15-'人员人工-研发人员工资'!E15 -> 0 | AJ15: =AH15-'人员人工-研发人员工资'!D15 -> 0
A16: ='人员人工-研发人员工资'!B16 -> 0 | AG16: =COUNTIF(B16:AF16,"●")+COUNTIF(B16:AF16,"▲")+COUNTIF(B16:AF16,"■")+COUNTIF(B16:AF16,"★")+COUNTIF(B16:AF16,"◆")+COUNTIF(B16:AF16,"✽")+COUNTIF(B16:AF16,"❖")+COUNTIF(B16:AF16,"✪")+COUNTIF(B16:AF16,"✿")+COUNTIF(B16:AF16,"✤") -> 0 | AH16: =COUNTIF(B16:AF16,"●")+COUNTIF(B16:AF16,"▲")+COUNTIF(B16:AF16,"■")+COUNTIF(B16:AF16,"★")+COUNTIF(B16:AF16,"◆")+COUNTIF(B16:AF16,"✽")+COUNTIF(B16:AF16,"❖")+COUNTIF(B16:AF16,"✪")+COUNTIF(B16:AF16,"✿")+COUNTIF(B16:AF16,"✤")+COUNTIF(B16:AF16,"√") -> 0 | AI16: =AG16-'人员人工-研发人员工资'!E16 -> 0 | AJ16: =AH16-'人员人工-研发人员工资'!D16 -> 0
A17: ='人员人工-研发人员工资'!B17 -> 0 | AG17: =COUNTIF(B17:AF17,"●")+COUNTIF(B17:AF17,"▲")+COUNTIF(B17:AF17,"■")+COUNTIF(B17:AF17,"★")+COUNTIF(B17:AF17,"◆")+COUNTIF(B17:AF17,"✽")+COUNTIF(B17:AF17,"❖")+COUNTIF(B17:AF17,"✪")+COUNTIF(B17:AF17,"✿")+COUNTIF(B17:AF17,"✤") -> 0 | AH17: =COUNTIF(B17:AF17,"●")+COUNTIF(B17:AF17,"▲")+COUNTIF(B17:AF17,"■")+COUNTIF(B17:AF17,"★")+COUNTIF(B17:AF17,"◆")+COUNTIF(B17:AF17,"✽")+COUNTIF(B17:AF17,"❖")+COUNTIF(B17:AF17,"✪")+COUNTIF(B17:AF17,"✿")+COUNTIF(B17:AF17,"✤")+COUNTIF(B17:AF17,"√") -> 0 | AI17: =AG17-'人员人工-研发人员工资'!E17 -> 0 | AJ17: =AH17-'人员人工-研发人员工资'!D17 -> 0
A18: ='人员人工-研发人员工资'!B18 -> 0 | AG18: =COUNTIF(B18:AF18,"●")+COUNTIF(B18:AF18,"▲")+COUNTIF(B18:AF18,"■")+COUNTIF(B18:AF18,"★")+COUNTIF(B18:AF18,"◆")+COUNTIF(B18:AF18,"✽")+COUNTIF(B18:AF18,"❖")+COUNTIF(B18:AF18,"✪")+COUNTIF(B18:AF18,"✿")+COUNTIF(B18:AF18,"✤") -> 0 | AH18: =COUNTIF(B18:AF18,"●")+COUNTIF(B18:AF18,"▲")+COUNTIF(B18:AF18,"■")+COUNTIF(B18:AF18,"★")+COUNTIF(B18:AF18,"◆")+COUNTIF(B18:AF18,"✽")+COUNTIF(B18:AF18,"❖")+COUNTIF(B18:AF18,"✪")+COUNTIF(B18:AF18,"✿")+COUNTIF(B18:AF18,"✤")+COUNTIF(B18:AF18,"√") -> 0 | AI18: =AG18-'人员人工-研发人员工资'!E18 -> 0 | AJ18: =AH18-'人员人工-研发人员工资'!D18 -> 0
... A35: ='人员人工-研发人员工资'!B35 -> 0 | AG35: =COUNTIF(B35:AF35,"●")+COUNTIF(B35:AF35,"▲")+COUNTIF(B35:AF35,"■")+COUNTIF(B35:AF35,"★")+COUNTIF(B35:AF35,"◆")+COUNTIF(B35:AF35,"✽")+COUNTIF(B35:AF35,"❖")+COUNTIF(B35:AF35,"✪")+COUNTIF(B35:AF35,"✿")+COUNTIF(B35:AF35,"✤") -> 0 | AH35: =COUNTIF(B35:AF35,"●")+COUNTIF(B35:AF35,"▲")+COUNTIF(B35:AF35,"■")+COUNTIF(B35:AF35,"★")+COUNTIF(B35:AF35,"◆")+COUNTIF(B35:AF35,"✽")+COUNTIF(B35:AF35,"❖")+COUNTIF(B35:AF35,"✪")+COUNTIF(B35:AF35,"✿")+COUNTIF(B35:AF35,"✤")+COUNTIF(B35:AF35,"√") -> 0 | AI35: =AG35-'人员人工-研发人员工资'!E35 -> 0 | AJ35: =AH35-'人员人工-研发人员工资'!D35 -> 0
A36: 注： | B36: ● | C36: ▲ | D36: ■ | E36: ★ | F36: ◆ | G36: ✽ | H36: ❖ | I36: ✪ | J36: ✿ | K36: ✤ | L36: √ | M36: ×
B37: 1 | C37: 2 | D37: 3 | E37: 4 | F37: 5 | G37: 6 | H37: 7 | I37: 8 | J37: 9 | K37: 10 | L37: 其他出勤 | M37: 未出勤
A39: 2023年2月份研发人员考勤表
A41: 姓名 | B41: 星期三 | C41: 星期四 | D41: 星期五 | E41: 星期六 | F41: 星期日 | G41: 星期一 | H41: 星期二 | I41: 星期三 | J41: 星期四 | K41: 星期五 | L41: 星期六 | M41: 星期日 | N41: 星期一 | O41: 星期二 | P41: 星期三 | Q41: 星期四 | R41: 星期五 | S41: 星期六 | T41: 星期日 | U41: 星期一 | V41: 星期二 | W41: 星期三 | X41: 星期四 | Y41: 星期五 | Z41: 星期六 | AA41: 星期日 | AB41: 星期一 | AC41: 星期二 | AG41: 研发天数 | AH41: 出勤天数 | AI41: 研发天数验证 | AJ41: 出勤天数验证
B42: 1 | C42: 2 | D42: 3 | E42: 4 | F42: 5 | G42: 6 | H42: 7 | I42: 8 | J42: 9 | K42: 10 | L42: 11 | M42: 12 | N42: 13 | O42: 14 | P42: 15 | Q42: 16 | R42: 17 | S42: 18 | T42: 19 | U42: 20 | V42: 21 | W42: 22 | X42: 23 | Y42: 24 | Z42: 25 | AA42: 26 | AB42: 27 | AC42: 28
A43: ='人员人工-研发人员工资'!B43 -> 0 | B43: ● | C43: ● | D43: ● | E43: × | F43: × | G43: ● | H43: ● | I43: √ | J43: ▲ | K43: ▲ | L43: × | M43: × | N43: ▲ | O43: ▲ | P43: ▲ | Q43: √ | R43: √ | S43: × | T43: × | U43: ■ | V43: ■ | W43: ■ | X43: ■ | Y43: ■ | Z43: × | AA43: × | AB43: √ | AC43: √ | AG43: =COUNTIF(B43:AF43,"●")+COUNTIF(B43:AF43,"▲")+COUNTIF(B43:AF43,"■")+COUNTIF(B43:AF43,"★")+COUNTIF(B43:AF43,"◆")+COUNTIF(B43:AF43,"✽")+COUNTIF(B43:AF43,"❖")+COUNTIF(B43:AF43,"✪")+COUNTIF(B43:AF43,"✿")+COUNTIF(B43:AF43,"✤") -> 15 | AH43: =COUNTIF(B43:AF43,"●")+COUNTIF(B43:AF43,"▲")+COUNTIF(B43:AF43,"■")+COUNTIF(B43:AF43,"★")+COUNTIF(B43:AF43,"◆")+COUNTIF(B43:AF43,"✽")+COUNTIF(B43:AF43,"❖")+COUNTIF(B43:AF43,"✪")+COUNTIF(B43:AF43,"✿")+COUNTIF(B43:AF43,"✤")+COUNTIF(B43:AF43,"√") -> 20 | AI43: =AG43-'人员人工-研发人员工资'!E43 -> 15 | AJ43: =AH43-'人员人工-研发人员工资'!D43 -> 20
A44: ='人员人工-研发人员工资'!B44 -> 0 | AG44: =COUNTIF(B44:AF44,"●")+COUNTIF(B44:AF44,"▲")+COUNTIF(B44:AF44,"■")+COUNTIF(B44:AF44,"★")+COUNTIF(B44:AF44,"◆")+COUNTIF(B44:AF44,"✽")+COUNTIF(B44:AF44,"❖")+COUNTIF(B44:AF44,"✪")+COUNTIF(B44:AF44,"✿")+COUNTIF(B44:AF44,"✤") -> 0 | AH44: =COUNTIF(B44:AF44,"●")+COUNTIF(B44:AF44,"▲")+COUNTIF(B44:AF44,"■")+COUNTIF(B44:AF44,"★")+COUNTIF(B44:AF44,"◆")+COUNTIF(B44:AF44,"✽")+COUNTIF(B44:AF44,"❖")+COUNTIF(B44:AF44,"✪")+COUNTIF(B44:AF44,"✿")+COUNTIF(B44:AF44,"✤")+COUNTIF(B44:AF44,"√") -> 0 | AI44: =AG44-'人员人工-研发人员工资'!E44 -> 0 | AJ44: =AH44-'人员人工-研发人员工资'!D44 -> 0
A45: ='人员人工-研发人员工资'!B45 -> 0 | AG45: =COUNTIF(B45:AF45,"●")+COUNTIF(B45:AF45,"▲")+COUNTIF(B45:AF45,"■")+COUNTIF(B45:AF45,"★")+COUNTIF(B45:AF45,"◆")+COUNTIF(B45:AF45,"✽")+COUNTIF(B45:AF45,"❖")+COUNTIF(B45:AF45,"✪")+COUNTIF(B45:AF45,"✿")+COUNTIF(B45:AF45,"✤") -> 0 | AH45: =COUNTIF(B45:AF45,"●")+COUNTIF(B45:AF45,"▲")+COUNTIF(B45:AF45,"■")+COUNTIF(B45:AF45,"★")+COUNTIF(B45:AF45,"◆")+COUNTIF(B45:AF45,"✽")+COUNTIF(B45:AF45,"❖")+COUNTIF(B45:AF45,"✪")+COUNTIF(B45:AF45,"✿")+COUNTIF(B45:AF45,"✤")+COUNTIF(B45:AF45,"√") -> 0 | AI45: =AG45-'人员人工-研发人员工资'!E45 -> 0 | AJ45: =AH45-'人员人工-研发人员工资'!D45 -> 0
A46: ='人员人工-研发人员工资'!B46 -> 0 | AG46: =COUNTIF(B46:AF46,"●")+COUNTIF(B46:AF46,"▲")+COUNTIF(B46:AF46,"■")+COUNTIF(B46:AF46,"★")+COUNTIF(B46:AF46,"◆")+COUNTIF(B46:AF46,"✽")+COUNTIF(B46:AF46,"❖")+COUNTIF(B46:AF46,"✪")+COUNTIF(B46:AF46,"✿")+COUNTIF(B46:AF46,"✤") -> 0 | AH46: =COUNTIF(B46:AF46,"●")+COUNTIF(B46:AF46,"▲")+COUNTIF(B46:AF46,"■")+COUNTIF(B46:AF46,"★")+COUNTIF(B46:AF46,"◆")+COUNTIF(B46:AF46,"✽")+COUNTIF(B46:AF46,"❖")+COUNTIF(B46:AF46,"✪")+COUNTIF(B46:AF46,"✿")+COUNTIF(B46:AF46,"✤")+COUNTIF(B46:AF46,"√") -> 0 | AI46: =AG46-'人员人工-研发人员工资'!E46 -> 0 | AJ46: =AH46-'人员人工-研发人员工资'!D46 -> 0
A47: ='人员人工-研发人员工资'!B47 -> 0 | AG47: =COUNTIF(B47:AF47,"●")+COUNTIF(B47:AF47,"▲")+COUNTIF(B47:AF47,"■")+COUNTIF(B47:AF47,"★")+COUNTIF(B47:AF47,"◆")+COUNTIF(B47:AF47,"✽")+COUNTIF(B47:AF47,"❖")+COUNTIF(B47:AF47,"✪")+COUNTIF(B47:AF47,"✿")+COUNTIF(B47:AF47,"✤") -> 0 | AH47: =COUNTIF(B47:AF47,"●")+COUNTIF(B47:AF47,"▲")+COUNTIF(B47:AF47,"■")+COUNTIF(B47:AF47,"★")+COUNTIF(B47:AF47,"◆")+COUNTIF(B47:AF47,"✽")+COUNTIF(B47:AF47,"❖")+COUNTIF(B47:AF47,"✪")+COUNTIF(B47:AF47,"✿")+COUNTIF(B47:AF47,"✤")+COUNTIF(B47:AF47,"√") -> 0 | AI47: =AG47-'人员人工-研发人员工资'!E47 -> 0 | AJ47: =AH47-'人员人工-研发人员工资'!D47 -> 0
A48: ='人员人工-研发人员工资'!B48 -> 0 | AG48: =COUNTIF(B48:AF48,"●")+COUNTIF(B48:AF48,"▲")+COUNTIF(B48:AF48,"■")+COUNTIF(B48:AF48,"★")+COUNTIF(B48:AF48,"◆")+COUNTIF(B48:AF48,"✽")+COUNTIF(B48:AF48,"❖")+COUNTIF(B48:AF48,"✪")+COUNTIF(B48:AF48,"✿")+COUNTIF(B48:AF48,"✤") -> 0 | AH48: =COUNTIF(B48:AF48,"●")+COUNTIF(B48:AF48,"▲")+COUNTIF(B48:AF48,"■")+COUNTIF(B48:AF48,"★")+COUNTIF(B48:AF48,"◆")+COUNTIF(B48:AF48,"✽")+COUNTIF(B48:AF48,"❖")+COUNTIF(B48:AF48,"✪")+COUNTIF(B48:AF48,"✿")+COUNTIF(B48:AF48,"✤")+COUNTIF(B48:AF48,"√") -> 0 | AI48: =AG48-'人员人工-研发人员工资'!E48 -> 0 | AJ48: =AH48-'人员人工-研发人员工资'!D48 -> 0
A49: ='人员人工-研发人员工资'!B49 -> 0 | AG49: =COUNTIF(B49:AF49,"●")+COUNTIF(B49:AF49,"▲")+COUNTIF(B49:AF49,"■")+COUNTIF(B49:AF49,"★")+COUNTIF(B49:AF49,"◆")+COUNTIF(B49:AF49,"✽")+COUNTIF(B49:AF49,"❖")+COUNTIF(B49:AF49,"✪")+COUNTIF(B49:AF49,"✿")+COUNTIF(B49:AF49,"✤") -> 0 | AH49: =COUNTIF(B49:AF49,"●")+COUNTIF(B49:AF49,"▲")+COUNTIF(B49:AF49,"■")+COUNTIF(B49:AF49,"★")+COUNTIF(B49:AF49,"◆")+COUNTIF(B49:AF49,"✽")+COUNTIF(B49:AF49,"❖")+COUNTIF(B49:AF49,"✪")+COUNTIF(B49:AF49,"✿")+COUNTIF(B49:AF49,"✤")+COUNTIF(B49:AF49,"√") -> 0 | AI49: =AG49-'人员人工-研发人员工资'!E49 -> 0 | AJ49: =AH49-'人员人工-研发人员工资'!D49 -> 0
A50: ='人员人工-研发人员工资'!B50 -> 0 | AG50: =COUNTIF(B50:AF50,"●")+COUNTIF(B50:AF50,"▲")+COUNTIF(B50:AF50,"■")+COUNTIF(B50:AF50,"★")+COUNTIF(B50:AF50,"◆")+COUNTIF(B50:AF50,"✽")+COUNTIF(B50:AF50,"❖")+COUNTIF(B50:AF50,"✪")+COUNTIF(B50:AF50,"✿")+COUNTIF(B50:AF50,"✤") -> 0 | AH50: =COUNTIF(B50:AF50,"●")+COUNTIF(B50:AF50,"▲")+COUNTIF(B50:AF50,"■")+COUNTIF(B50:AF50,"★")+COUNTIF(B50:AF50,"◆")+COUNTIF(B50:AF50,"✽")+COUNTIF(B50:AF50,"❖")+COUNTIF(B50:AF50,"✪")+COUNTIF(B50:AF50,"✿")+COUNTIF(B50:AF50,"✤")+COUNTIF(B50:AF50,"√") -> 0 | AI50: =AG50-'人员人工-研发人员工资'!E50 -> 0 | AJ50: =AH50-'人员人工-研发人员工资'!D50 -> 0
A51: ='人员人工-研发人员工资'!B51 -> 0 | AG51: =COUNTIF(B51:AF51,"●")+COUNTIF(B51:AF51,"▲")+COUNTIF(B51:AF51,"■")+COUNTIF(B51:AF51,"★")+COUNTIF(B51:AF51,"◆")+COUNTIF(B51:AF51,"✽")+COUNTIF(B51:AF51,"❖")+COUNTIF(B51:AF51,"✪")+COUNTIF(B51:AF51,"✿")+COUNTIF(B51:AF51,"✤") -> 0 | AH51: =COUNTIF(B51:AF51,"●")+COUNTIF(B51:AF51,"▲")+COUNTIF(B51:AF51,"■")+COUNTIF(B51:AF51,"★")+COUNTIF(B51:AF51,"◆")+COUNTIF(B51:AF51,"✽")+COUNTIF(B51:AF51,"❖")+COUNTIF(B51:AF51,"✪")+COUNTIF(B51:AF51,"✿")+COUNTIF(B51:AF51,"✤")+COUNTIF(B51:AF51,"√") -> 0 | AI51: =AG51-'人员人工-研发人员工资'!E51 -> 0 | AJ51: =AH51-'人员人工-研发人员工资'!D51 -> 0
A52: ='人员人工-研发人员工资'!B52 -> 0 | AG52: =COUNTIF(B52:AF52,"●")+COUNTIF(B52:AF52,"▲")+COUNTIF(B52:AF52,"■")+COUNTIF(B52:AF52,"★")+COUNTIF(B52:AF52,"◆")+COUNTIF(B52:AF52,"✽")+COUNTIF(B52:AF52,"❖")+COUNTIF(B52:AF52,"✪")+COUNTIF(B52:AF52,"✿")+COUNTIF(B52:AF52,"✤") -> 0 | AH52: =COUNTIF(B52:AF52,"●")+COUNTIF(B52:AF52,"▲")+COUNTIF(B52:AF52,"■")+COUNTIF(B52:AF52,"★")+COUNTIF(B52:AF52,"◆")+COUNTIF(B52:AF52,"✽")+COUNTIF(B52:AF52,"❖")+COUNTIF(B52:AF52,"✪")+COUNTIF(B52:AF52,"✿")+COUNTIF(B52:AF52,"✤")+COUNTIF(B52:AF52,"√") -> 0 | AI52: =AG52-'人员人工-研发人员工资'!E52 -> 0 | AJ52: =AH52-'人员人工-研发人员工资'!D52 -> 0
A53: ='人员人工-研发人员工资'!B53 -> 0 | AG53: =COUNTIF(B53:AF53,"●")+COUNTIF(B53:AF53,"▲")+COUNTIF(B53:AF53,"■")+COUNTIF(B53:AF53,"★")+COUNTIF(B53:AF53,"◆")+COUNTIF(B53:AF53,"✽")+COUNTIF(B53:AF53,"❖")+COUNTIF(B53:AF53,"✪")+COUNTIF(B53:AF53,"✿")+COUNTIF(B53:AF53,"✤") -> 0 | AH53: =COUNTIF(B53:AF53,"●")+COUNTIF(B53:AF53,"▲")+COUNTIF(B53:AF53,"■")+COUNTIF(B53:AF53,"★")+COUNTIF(B53:AF53,"◆")+COUNTIF(B53:AF53,"✽")+COUNTIF(B53:AF53,"❖")+COUNTIF(B53:AF53,"✪")+COUNTIF(B53:AF53,"✿")+COUNTIF(B53:AF53,"✤")+COUNTIF(B53:AF53,"√") -> 0 | AI53: =AG53-'人员人工-研发人员工资'!E53 -> 0 | AJ53: =AH53-'人员人工-研发人员工资'!D53 -> 0
A54: ='人员人工-研发人员工资'!B54 -> 0 | AG54: =COUNTIF(B54:AF54,"●")+COUNTIF(B54:AF54,"▲")+COUNTIF(B54:AF54,"■")+COUNTIF(B54:AF54,"★")+COUNTIF(B54:AF54,"◆")+COUNTIF(B54:AF54,"✽")+COUNTIF(B54:AF54,"❖")+COUNTIF(B54:AF54,"✪")+COUNTIF(B54:AF54,"✿")+COUNTIF(B54:AF54,"✤") -> 0 | AH54: =COUNTIF(B54:AF54,"●")+COUNTIF(B54:AF54,"▲")+COUNTIF(B54:AF54,"■")+COUNTIF(B54:AF54,"★")+COUNTIF(B54:AF54,"◆")+COUNTIF(B54:AF54,"✽")+COUNTIF(B54:AF54,"❖")+COUNTIF(B54:AF54,"✪")+COUNTIF(B54:AF54,"✿")+COUNTIF(B54:AF54,"✤")+COUNTIF(B54:AF54,"√") -> 0 | AI54: =AG54-'人员人工-研发人员工资'!E54 -> 0 | AJ54: =AH54-'人员人工-研发人员工资'!D54 -> 0
A55: ='人员人工-研发人员工资'!B55 -> 0 | AG55: =COUNTIF(B55:AF55,"●")+COUNTIF(B55:AF55,"▲")+COUNTIF(B55:AF55,"■")+COUNTIF(B55:AF55,"★")+COUNTIF(B55:AF55,"◆")+COUNTIF(B55:AF55,"✽")+COUNTIF(B55:AF55,"❖")+COUNTIF(B55:AF55,"✪")+COUNTIF(B55:AF55,"✿")+COUNTIF(B55:AF55,"✤") -> 0 | AH55: =COUNTIF(B55:AF55,"●")+COUNTIF(B55:AF55,"▲")+COUNTIF(B55:AF55,"■")+COUNTIF(B55:AF55,"★")+COUNTIF(B55:AF55,"◆")+COUNTIF(B55:AF55,"✽")+COUNTIF(B55:AF55,"❖")+COUNTIF(B55:AF55,"✪")+COUNTIF(B55:AF55,"✿")+COUNTIF(B55:AF55,"✤")+COUNTIF(B55:AF55,"√") -> 0 | AI55: =AG55-'人员人工-研发人员工资'!E55 -> 0 | AJ55: =AH55-'人员人工-研发人员工资'!D55 -> 0
... A72: ='人员人工-研发人员工资'!B72 -> 0 | AG72: =COUNTIF(B72:AF72,"●")+COUNTIF(B72:AF72,"▲")+COUNTIF(B72:AF72,"■")+COUNTIF(B72:AF72,"★")+COUNTIF(B72:AF72,"◆")+COUNTIF(B72:AF72,"✽")+COUNTIF(B72:AF72,"❖")+COUNTIF(B72:AF72,"✪")+COUNTIF(B72:AF72,"✿")+COUNTIF(B72:AF72,"✤") -> 0 | AH72: =COUNTIF(B72:AF72,"●")+COUNTIF(B72:AF72,"▲")+COUNTIF(B72:AF72,"■")+COUNTIF(B72:AF72,"★")+COUNTIF(B72:AF72,"◆")+COUNTIF(B72:AF72,"✽")+COUNTIF(B72:AF72,"❖")+COUNTIF(B72:AF72,"✪")+COUNTIF(B72:AF72,"✿")+COUNTIF(B72:AF72,"✤")+COUNTIF(B72:AF72,"√") -> 0 | AI72: =AG72-'人员人工-研发人员工资'!E72 -> 0 | AJ72: =AH72-'人员人工-研发人员工资'!D72 -> 0
A73: 注： | B73: ● | C73: ▲ | D73: ■ | E73: ★ | F73: ◆ | G73: ✽ | H73: ❖ | I73: ✪ | J73: ✿ | K73: ✤ | L73: √ | M73: ×
B74: 1 | C74: 2 | D74: 3 | E74: 4 | F74: 5 | G74: 6 | H74: 7 | I74: 8 | J74: 9 | K74: 10 | L74: 其他出勤 | M74: 未出勤
A77: 2023年3月份研发人员考勤表
A79: 姓名 | B79: 星期三 | C79: 星期四 | D79: 星期五 | E79: 星期六 | F79: 星期日 | G79: 星期一 | H79: 星期二 | I79: 星期三 | J79: 星期四 | K79: 星期五 | L79: 星期六 | M79: 星期日 | N79: 星期一 | O79: 星期二 | P79: 星期三 | Q79: 星期四 | R79: 星期五 | S79: 星期六 | T79: 星期日 | U79: 星期一 | V79: 星期二 | W79: 星期三 | X79: 星期四 | Y79: 星期五 | Z79: 星期六 | AA79: 星期日 | AB79: 星期一 | AC79: 星期二 | AD79: 星期三 | AE79: 星期四 | AF79: 星期五 | AG79: 研发天数 | AH79: 出勤天数 | AI79: 研发天数验证 | AJ79: 出勤天数验证
B80: 1 | C80: 2 | D80: 3 | E80: 4 | F80: 5 | G80: 6 | H80: 7 | I80: 8 | J80: 9 | K80: 10 | L80: 11 | M80: 12 | N80: 13 | O80: 14 | P80: 15 | Q80: 16 | R80: 17 | S80: 18 | T80: 19 | U80: 20 | V80: 21 | W80: 22 | X80: 23 | Y80: 24 | Z80: 25 | AA80: 26 | AB80: 27 | AC80: 28 | AD80: 29 | AE80: 30 | AF80: 31
A81: ='人员人工-研发人员工资'!B81 -> 0 | B81: ● | C81: ● | D81: ● | E81: × | F81: × | G81: ● | H81: ● | I81: ● | J81: √ | K81: √ | L81: × | M81: × | N81: ▲ | O81: ▲ | P81: ▲ | Q81: ▲ | R81: ▲ | S81: × | T81: × | U81: √ | V81: √ | W81: ■ | X81: ■ | Y81: ■ | Z81: × | AA81: × | AB81: ■ | AC81: ■ | AD81: ■ | AE81: ■ | AF81: √ | AG81: =COUNTIF(B81:AF81,"●")+COUNTIF(B81:AF81,"▲")+COUNTIF(B81:AF81,"■")+COUNTIF(B81:AF81,"★")+COUNTIF(B81:AF81,"◆")+COUNTIF(B81:AF81,"✽")+COUNTIF(B81:AF81,"❖")+COUNTIF(B81:AF81,"✪")+COUNTIF(B81:AF81,"✿")+COUNTIF(B81:AF81,"✤") -> 18 | AH81: =COUNTIF(B81:AF81,"●")+COUNTIF(B81:AF81,"▲")+COUNTIF(B81:AF81,"■")+COUNTIF(B81:AF81,"★")+COUNTIF(B81:AF81,"◆")+COUNTIF(B81:AF81,"✽")+COUNTIF(B81:AF81,"❖")+COUNTIF(B81:AF81,"✪")+COUNTIF(B81:AF81,"✿")+COUNTIF(B81:AF81,"✤")+COUNTIF(B81:AF81,"√") -> 23 | AI81: =AG81-'人员人工-研发人员工资'!E81 -> 18 | AJ81: =AH81-'人员人工-研发人员工资'!D81 -> 23
A82: ='人员人工-研发人员工资'!B82 -> 0 | AG82: =COUNTIF(B82:AF82,"●")+COUNTIF(B82:AF82,"▲")+COUNTIF(B82:AF82,"■")+COUNTIF(B82:AF82,"★")+COUNTIF(B82:AF82,"◆")+COUNTIF(B82:AF82,"✽")+COUNTIF(B82:AF82,"❖")+COUNTIF(B82:AF82,"✪")+COUNTIF(B82:AF82,"✿")+COUNTIF(B82:AF82,"✤") -> 0 | AH82: =COUNTIF(B82:AF82,"●")+COUNTIF(B82:AF82,"▲")+COUNTIF(B82:AF82,"■")+COUNTIF(B82:AF82,"★")+COUNTIF(B82:AF82,"◆")+COUNTIF(B82:AF82,"✽")+COUNTIF(B82:AF82,"❖")+COUNTIF(B82:AF82,"✪")+COUNTIF(B82:AF82,"✿")+COUNTIF(B82:AF82,"✤")+COUNTIF(B82:AF82,"√") -> 0 | AI82: =AG82-'人员人工-研发人员工资'!E82 -> 0 | AJ82: =AH82-'人员人工-研发人员工资'!D82 -> 0
A83: ='人员人工-研发人员工资'!B83 -> 0 | AG83: =COUNTIF(B83:AF83,"●")+COUNTIF(B83:AF83,"▲")+COUNTIF(B83:AF83,"■")+COUNTIF(B83:AF83,"★")+COUNTIF(B83:AF83,"◆")+COUNTIF(B83:AF83,"✽")+COUNTIF(B83:AF83,"❖")+COUNTIF(B83:AF83,"✪")+COUNTIF(B83:AF83,"✿")+COUNTIF(B83:AF83,"✤") -> 0 | AH83: =COUNTIF(B83:AF83,"●")+COUNTIF(B83:AF83,"▲")+COUNTIF(B83:AF83,"■")+COUNTIF(B83:AF83,"★")+COUNTIF(B83:AF83,"◆")+COUNTIF(B83:AF83,"✽")+COUNTIF(B83:AF83,"❖")+COUNTIF(B83:AF83,"✪")+COUNTIF(B83:AF83,"✿")+COUNTIF(B83:AF83,"✤")+COUNTIF(B83:AF83,"√") -> 0 | AI83: =AG83-'人员人工-研发人员工资'!E83 -> 0 | AJ83: =AH83-'人员人工-研发人员工资'!D83 -> 0
A84: ='人员人工-研发人员工资'!B84 -> 0 | AG84: =COUNTIF(B84:AF84,"●")+COUNTIF(B84:AF84,"▲")+COUNTIF(B84:AF84,"■")+COUNTIF(B84:AF84,"★")+COUNTIF(B84:AF84,"◆")+COUNTIF(B84:AF84,"✽")+COUNTIF(B84:AF84,"❖")+COUNTIF(B84:AF84,"✪")+COUNTIF(B84:AF84,"✿")+COUNTIF(B84:AF84,"✤") -> 0 | AH84: =COUNTIF(B84:AF84,"●")+COUNTIF(B84:AF84,"▲")+COUNTIF(B84:AF84,"■")+COUNTIF(B84:AF84,"★")+COUNTIF(B84:AF84,"◆")+COUNTIF(B84:AF84,"✽")+COUNTIF(B84:AF84,"❖")+COUNTIF(B84:AF84,"✪")+COUNTIF(B84:AF84,"✿")+COUNTIF(B84:AF84,"✤")+COUNTIF(B84:AF84,"√") -> 0 | AI84: =AG84-'人员人工-研发人员工资'!E84 -> 0 | AJ84: =AH84-'人员人工-研发人员工资'!D84 -> 0
A85: ='人员人工-研发人员工资'!B85 -> 0 | AG85: =COUNTIF(B85:AF85,"●")+COUNTIF(B85:AF85,"▲")+COUNTIF(B85:AF85,"■")+COUNTIF(B85:AF85,"★")+COUNTIF(B85:AF85,"◆")+COUNTIF(B85:AF85,"✽")+COUNTIF(B85:AF85,"❖")+COUNTIF(B85:AF85,"✪")+COUNTIF(B85:AF85,"✿")+COUNTIF(B85:AF85,"✤") -> 0 | AH85: =COUNTIF(B85:AF85,"●")+COUNTIF(B85:AF85,"▲")+COUNTIF(B85:AF85,"■")+COUNTIF(B85:AF85,"★")+COUNTIF(B85:AF85,"◆")+COUNTIF(B85:AF85,"✽")+COUNTIF(B85:AF85,"❖")+COUNTIF(B85:AF85,"✪")+COUNTIF(B85:AF85,"✿")+COUNTIF(B85:AF85,"✤")+COUNTIF(B85:AF85,"√") -> 0 | AI85: =AG85-'人员人工-研发人员工资'!E85 -> 0 | AJ85: =AH85-'人员人工-研发人员工资'!D85 -> 0
A86: ='人员人工-研发人员工资'!B86 -> 0 | AG86: =COUNTIF(B86:AF86,"●")+COUNTIF(B86:AF86,"▲")+COUNTIF(B86:AF86,"■")+COUNTIF(B86:AF86,"★")+COUNTIF(B86:AF86,"◆")+COUNTIF(B86:AF86,"✽")+COUNTIF(B86:AF86,"❖")+COUNTIF(B86:AF86,"✪")+COUNTIF(B86:AF86,"✿")+COUNTIF(B86:AF86,"✤") -> 0 | AH86: =COUNTIF(B86:AF86,"●")+COUNTIF(B86:AF86,"▲")+COUNTIF(B86:AF86,"■")+COUNTIF(B86:AF86,"★")+COUNTIF(B86:AF86,"◆")+COUNTIF(B86:AF86,"✽")+COUNTIF(B86:AF86,"❖")+COUNTIF(B86:AF86,"✪")+COUNTIF(B86:AF86,"✿")+COUNTIF(B86:AF86,"✤")+COUNTIF(B86:AF86,"√") -> 0 | AI86: =AG86-'人员人工-研发人员工资'!E86 -> 0 | AJ86: =AH86-'人员人工-研发人员工资'!D86 -> 0
A87: ='人员人工-研发人员工资'!B87 -> 0 | AG87: =COUNTIF(B87:AF87,"●")+COUNTIF(B87:AF87,"▲")+COUNTIF(B87:AF87,"■")+COUNTIF(B87:AF87,"★")+COUNTIF(B87:AF87,"◆")+COUNTIF(B87:AF87,"✽")+COUNTIF(B87:AF87,"❖")+COUNTIF(B87:AF87,"✪")+COUNTIF(B87:AF87,"✿")+COUNTIF(B87:AF87,"✤") -> 0 | AH87: =COUNTIF(B87:AF87,"●")+COUNTIF(B87:AF87,"▲")+COUNTIF(B87:AF87,"■")+COUNTIF(B87:AF87,"★")+COUNTIF(B87:AF87,"◆")+COUNTIF(B87:AF87,"✽")+COUNTIF(B87:AF87,"❖")+COUNTIF(B87:AF87,"✪")+COUNTIF(B87:AF87,"✿")+COUNTIF(B87:AF87,"✤")+COUNTIF(B87:AF87,"√") -> 0 | AI87: =AG87-'人员人工-研发人员工资'!E87 -> 0 | AJ87: =AH87-'人员人工-研发人员工资'!D87 -> 0
A88: ='人员人工-研发人员工资'!B88 -> 0 | AG88: =COUNTIF(B88:AF88,"●")+COUNTIF(B88:AF88,"▲")+COUNTIF(B88:AF88,"■")+COUNTIF(B88:AF88,"★")+COUNTIF(B88:AF88,"◆")+COUNTIF(B88:AF88,"✽")+COUNTIF(B88:AF88,"❖")+COUNTIF(B88:AF88,"✪")+COUNTIF(B88:AF88,"✿")+COUNTIF(B88:AF88,"✤") -> 0 | AH88: =COUNTIF(B88:AF88,"●")+COUNTIF(B88:AF88,"▲")+COUNTIF(B88:AF88,"■")+COUNTIF(B88:AF88,"★")+COUNTIF(B88:AF88,"◆")+COUNTIF(B88:AF88,"✽")+COUNTIF(B88:AF88,"❖")+COUNTIF(B88:AF88,"✪")+COUNTIF(B88:AF88,"✿")+COUNTIF(B88:AF88,"✤")+COUNTIF(B88:AF88,"√") -> 0 | AI88: =AG88-'人员人工-研发人员工资'!E88 -> 0 | AJ88: =AH88-'人员人工-研发人员工资'!D88 -> 0
A89: ='人员人工-研发人员工资'!B89 -> 0 | AG89: =COUNTIF(B89:AF89,"●")+COUNTIF(B89:AF89,"▲")+COUNTIF(B89:AF89,"■")+COUNTIF(B89:AF89,"★")+COUNTIF(B89:AF89,"◆")+COUNTIF(B89:AF89,"✽")+COUNTIF(B89:AF89,"❖")+COUNTIF(B89:AF89,"✪")+COUNTIF(B89:AF89,"✿")+COUNTIF(B89:AF89,"✤") -> 0 | AH89: =COUNTIF(B89:AF89,"●")+COUNTIF(B89:AF89,"▲")+COUNTIF(B89:AF89,"■")+COUNTIF(B89:AF89,"★")+COUNTIF(B89:AF89,"◆")+COUNTIF(B89:AF89,"✽")+COUNTIF(B89:AF89,"❖")+COUNTIF(B89:AF89,"✪")+COUNTIF(B89:AF89,"✿")+COUNTIF(B89:AF89,"✤")+COUNTIF(B89:AF89,"√") -> 0 | AI89: =AG89-'人员人工-研发人员工资'!E89 -> 0 | AJ89: =AH89-'人员人工-研发人员工资'!D89 -> 0
A90: ='人员人工-研发人员工资'!B90 -> 0 | AG90: =COUNTIF(B90:AF90,"●")+COUNTIF(B90:AF90,"▲")+COUNTIF(B90:AF90,"■")+COUNTIF(B90:AF90,"★")+COUNTIF(B90:AF90,"◆")+COUNTIF(B90:AF90,"✽")+COUNTIF(B90:AF90,"❖")+COUNTIF(B90:AF90,"✪")+COUNTIF(B90:AF90,"✿")+COUNTIF(B90:AF90,"✤") -> 0 | AH90: =COUNTIF(B90:AF90,"●")+COUNTIF(B90:AF90,"▲")+COUNTIF(B90:AF90,"■")+COUNTIF(B90:AF90,"★")+COUNTIF(B90:AF90,"◆")+COUNTIF(B90:AF90,"✽")+COUNTIF(B90:AF90,"❖")+COUNTIF(B90:AF90,"✪")+COUNTIF(B90:AF90,"✿")+COUNTIF(B90:AF90,"✤")+COUNTIF(B90:AF90,"√") -> 0 | AI90: =AG90-'人员人工-研发人员工资'!E90 -> 0 | AJ90: =AH90-'人员人工-研发人员工资'!D90 -> 0
A91: ='人员人工-研发人员工资'!B91 -> 0 | AG91: =COUNTIF(B91:AF91,"●")+COUNTIF(B91:AF91,"▲")+COUNTIF(B91:AF91,"■")+COUNTIF(B91:AF91,"★")+COUNTIF(B91:AF91,"◆")+COUNTIF(B91:AF91,"✽")+COUNTIF(B91:AF91,"❖")+COUNTIF(B91:AF91,"✪")+COUNTIF(B91:AF91,"✿")+COUNTIF(B91:AF91,"✤") -> 0 | AH91: =COUNTIF(B91:AF91,"●")+COUNTIF(B91:AF91,"▲")+COUNTIF(B91:AF91,"■")+COUNTIF(B91:AF91,"★")+COUNTIF(B91:AF91,"◆")+COUNTIF(B91:AF91,"✽")+COUNTIF(B91:AF91,"❖")+COUNTIF(B91:AF91,"✪")+COUNTIF(B91:AF91,"✿")+COUNTIF(B91:AF91,"✤")+COUNTIF(B91:AF91,"√") -> 0 | AI91: =AG91-'人员人工-研发人员工资'!E91 -> 0 | AJ91: =AH91-'人员人工-研发人员工资'!D91 -> 0
A92: ='人员人工-研发人员工资'!B92 -> 0 | AG92: =COUNTIF(B92:AF92,"●")+COUNTIF(B92:AF92,"▲")+COUNTIF(B92:AF92,"■")+COUNTIF(B92:AF92,"★")+COUNTIF(B92:AF92,"◆")+COUNTIF(B92:AF92,"✽")+COUNTIF(B92:AF92,"❖")+COUNTIF(B92:AF92,"✪")+COUNTIF(B92:AF92,"✿")+COUNTIF(B92:AF92,"✤") -> 0 | AH92: =COUNTIF(B92:AF92,"●")+COUNTIF(B92:AF92,"▲")+COUNTIF(B92:AF92,"■")+COUNTIF(B92:AF92,"★")+COUNTIF(B92:AF92,"◆")+COUNTIF(B92:AF92,"✽")+COUNTIF(B92:AF92,"❖")+COUNTIF(B92:AF92,"✪")+COUNTIF(B92:AF92,"✿")+COUNTIF(B92:AF92,"✤")+COUNTIF(B92:AF92,"√") -> 0 | AI92: =AG92-'人员人工-研发人员工资'!E92 -> 0 | AJ92: =AH92-'人员人工-研发人员工资'!D92 -> 0
A93: ='人员人工-研发人员工资'!B93 -> 0 | AG93: =COUNTIF(B93:AF93,"●")+COUNTIF(B93:AF93,"▲")+COUNTIF(B93:AF93,"■")+COUNTIF(B93:AF93,"★")+COUNTIF(B93:AF93,"◆")+COUNTIF(B93:AF93,"✽")+COUNTIF(B93:AF93,"❖")+COUNTIF(B93:AF93,"✪")+COUNTIF(B93:AF93,"✿")+COUNTIF(B93:AF93,"✤") -> 0 | AH93: =COUNTIF(B93:AF93,"●")+COUNTIF(B93:AF93,"▲")+COUNTIF(B93:AF93,"■")+COUNTIF(B93:AF93,"★")+COUNTIF(B93:AF93,"◆")+COUNTIF(B93:AF93,"✽")+COUNTIF(B93:AF93,"❖")+COUNTIF(B93:AF93,"✪")+COUNTIF(B93:AF93,"✿")+COUNTIF(B93:AF93,"✤")+COUNTIF(B93:AF93,"√") -> 0 | AI93: =AG93-'人员人工-研发人员工资'!E93 -> 0 | AJ93: =AH93-'人员人工-研发人员工资'!D93 -> 0
... A110: ='人员人工-研发人员工资'!B110 -> 0 | AG110: =COUNTIF(B110:AF110,"●")+COUNTIF(B110:AF110,"▲")+COUNTIF(B110:AF110,"■")+COUNTIF(B110:AF110,"★")+COUNTIF(B110:AF110,"◆")+COUNTIF(B110:AF110,"✽")+COUNTIF(B110:AF110,"❖")+COUNTIF(B110:AF110,"✪")+COUNTIF(B110:AF110,"✿")+COUNTIF(B110:AF110,"✤") -> 0 | AH110: =COUNTIF(B110:AF110,"●")+COUNTIF(B110:AF110,"▲")+COUNTIF(B110:AF110,"■")+COUNTIF(B110:AF110,"★")+COUNTIF(B110:AF110,"◆")+COUNTIF(B110:AF110,"✽")+COUNTIF(B110:AF110,"❖")+COUNTIF(B110:AF110,"✪")+COUNTIF(B110:AF110,"✿")+COUNTIF(B110:AF110,"✤")+COUNTIF(B110:AF110,"√") -> 0 | AI110: =AG110-'人员人工-研发人员工资'!E110 -> 0 | AJ110: =AH110-'人员人工-研发人员工资'!D110 -> 0
A111: 注： | B111: ● | C111: ▲ | D111: ■ | E111: ★ | F111: ◆ | G111: ✽ | H111: ❖ | I111: ✪ | J111: ✿ | K111: ✤ | L111: √ | M111: ×
B112: 1 | C112: 2 | D112: 3 | E112: 4 | F112: 5 | G112: 6 | H112: 7 | I112: 8 | J112: 9 | K112: 10 | L112: 其他出勤 | M112: 未出勤
A115: 2023年4月份研发人员考勤表
A117: 姓名 | B117: 星期六 | C117: 星期日 | D117: 星期一 | E117: 星期二 | F117: 星期三 | G117: 星期四 | H117: 星期五 | I117: 星期六 | J117: 星期日 | K117: 星期一 | L117: 星期二 | M117: 星期三 | N117: 星期四 | O117: 星期五 | P117: 星期六 | Q117: 星期日 | R117: 星期一 | S117: 星期二 | T117: 星期三 | U117: 星期四 | V117: 星期五 | W117: 星期六 | X117: 星期日 | Y117: 星期一 | Z117: 星期二 | AA117: 星期三 | AB117: 星期四 | AC117: 星期五 | AD117: 星期六 | AE117: 星期日 | AG117: 研发天数 | AH117: 出勤天数 | AI117: 研发天数验证 | AJ117: 出勤天数验证
B118: 1 | C118: 2 | D118: 3 | E118: 4 | F118: 5 | G118: 6 | H118: 7 | I118: 8 | J118: 9 | K118: 10 | L118: 11 | M118: 12 | N118: 13 | O118: 14 | P118: 15 | Q118: 16 | R118: 17 | S118: 18 | T118: 19 | U118: 20 | V118: 21 | W118: 22 | X118: 23 | Y118: 24 | Z118: 25 | AA118: 26 | AB118: 27 | AC118: 28 | AD118: 29 | AE118: 30
A119: ='人员人工-研发人员工资'!B119 -> 0 | B119: × | C119: × | D119: ● | E119: ● | F119: × | G119: ● | H119: ● | I119: × | J119: × | K119: ▲ | L119: ▲ | M119: ▲ | N119: ▲ | O119: ▲ | P119: × | Q119: × | R119: √ | S119: √ | T119: ■ | U119: ■ | V119: ■ | W119: × | X119: ■ | Y119: ■ | Z119: ■ | AA119: ■ | AB119: ■ | AC119: √ | AD119: × | AE119: × | AG119: =COUNTIF(B119:AF119,"●")+COUNTIF(B119:AF119,"▲")+COUNTIF(B119:AF119,"■")+COUNTIF(B119:AF119,"★")+COUNTIF(B119:AF119,"◆")+COUNTIF(B119:AF119,"✽")+COUNTIF(B119:AF119,"❖")+COUNTIF(B119:AF119,"✪")+COUNTIF(B119:AF119,"✿")+COUNTIF(B119:AF119,"✤") -> 17 | AH119: =COUNTIF(B119:AF119,"●")+COUNTIF(B119:AF119,"▲")+COUNTIF(B119:AF119,"■")+COUNTIF(B119:AF119,"★")+COUNTIF(B119:AF119,"◆")+COUNTIF(B119:AF119,"✽")+COUNTIF(B119:AF119,"❖")+COUNTIF(B119:AF119,"✪")+COUNTIF(B119:AF119,"✿")+COUNTIF(B119:AF119,"✤")+COUNTIF(B119:AF119,"√") -> 20 | AI119: =AG119-'人员人工-研发人员工资'!E119 -> 17 | AJ119: =AH119-'人员人工-研发人员工资'!D119 -> 20
A120: ='人员人工-研发人员工资'!B120 -> 0 | AG120: =COUNTIF(B120:AF120,"●")+COUNTIF(B120:AF120,"▲")+COUNTIF(B120:AF120,"■")+COUNTIF(B120:AF120,"★")+COUNTIF(B120:AF120,"◆")+COUNTIF(B120:AF120,"✽")+COUNTIF(B120:AF120,"❖")+COUNTIF(B120:AF120,"✪")+COUNTIF(B120:AF120,"✿")+COUNTIF(B120:AF120,"✤") -> 0 | AH120: =COUNTIF(B120:AF120,"●")+COUNTIF(B120:AF120,"▲")+COUNTIF(B120:AF120,"■")+COUNTIF(B120:AF120,"★")+COUNTIF(B120:AF120,"◆")+COUNTIF(B120:AF120,"✽")+COUNTIF(B120:AF120,"❖")+COUNTIF(B120:AF120,"✪")+COUNTIF(B120:AF120,"✿")+COUNTIF(B120:AF120,"✤")+COUNTIF(B120:AF120,"√") -> 0 | AI120: =AG120-'人员人工-研发人员工资'!E120 -> 0 | AJ120: =AH120-'人员人工-研发人员工资'!D120 -> 0
A121: ='人员人工-研发人员工资'!B121 -> 0 | AG121: =COUNTIF(B121:AF121,"●")+COUNTIF(B121:AF121,"▲")+COUNTIF(B121:AF121,"■")+COUNTIF(B121:AF121,"★")+COUNTIF(B121:AF121,"◆")+COUNTIF(B121:AF121,"✽")+COUNTIF(B121:AF121,"❖")+COUNTIF(B121:AF121,"✪")+COUNTIF(B121:AF121,"✿")+COUNTIF(B121:AF121,"✤") -> 0 | AH121: =COUNTIF(B121:AF121,"●")+COUNTIF(B121:AF121,"▲")+COUNTIF(B121:AF121,"■")+COUNTIF(B121:AF121,"★")+COUNTIF(B121:AF121,"◆")+COUNTIF(B121:AF121,"✽")+COUNTIF(B121:AF121,"❖")+COUNTIF(B121:AF121,"✪")+COUNTIF(B121:AF121,"✿")+COUNTIF(B121:AF121,"✤")+COUNTIF(B121:AF121,"√") -> 0 | AI121: =AG121-'人员人工-研发人员工资'!E121 -> 0 | AJ121: =AH121-'人员人工-研发人员工资'!D121 -> 0
A122: ='人员人工-研发人员工资'!B122 -> 0 | AG122: =COUNTIF(B122:AF122,"●")+COUNTIF(B122:AF122,"▲")+COUNTIF(B122:AF122,"■")+COUNTIF(B122:AF122,"★")+COUNTIF(B122:AF122,"◆")+COUNTIF(B122:AF122,"✽")+COUNTIF(B122:AF122,"❖")+COUNTIF(B122:AF122,"✪")+COUNTIF(B122:AF122,"✿")+COUNTIF(B122:AF122,"✤") -> 0 | AH122: =COUNTIF(B122:AF122,"●")+COUNTIF(B122:AF122,"▲")+COUNTIF(B122:AF122,"■")+COUNTIF(B122:AF122,"★")+COUNTIF(B122:AF122,"◆")+COUNTIF(B122:AF122,"✽")+COUNTIF(B122:AF122,"❖")+COUNTIF(B122:AF122,"✪")+COUNTIF(B122:AF122,"✿")+COUNTIF(B122:AF122,"✤")+COUNTIF(B122:AF122,"√") -> 0 | AI122: =AG122-'人员人工-研发人员工资'!E122 -> 0 | AJ122: =AH122-'人员人工-研发人员工资'!D122 -> 0
A123: ='人员人工-研发人员工资'!B123 -> 0 | AG123: =COUNTIF(B123:AF123,"●")+COUNTIF(B123:AF123,"▲")+COUNTIF(B123:AF123,"■")+COUNTIF(B123:AF123,"★")+COUNTIF(B123:AF123,"◆")+COUNTIF(B123:AF123,"✽")+COUNTIF(B123:AF123,"❖")+COUNTIF(B123:AF123,"✪")+COUNTIF(B123:AF123,"✿")+COUNTIF(B123:AF123,"✤") -> 0 | AH123: =COUNTIF(B123:AF123,"●")+COUNTIF(B123:AF123,"▲")+COUNTIF(B123:AF123,"■")+COUNTIF(B123:AF123,"★")+COUNTIF(B123:AF123,"◆")+COUNTIF(B123:AF123,"✽")+COUNTIF(B123:AF123,"❖")+COUNTIF(B123:AF123,"✪")+COUNTIF(B123:AF123,"✿")+COUNTIF(B123:AF123,"✤")+COUNTIF(B123:AF123,"√") -> 0 | AI123: =AG123-'人员人工-研发人员工资'!E123 -> 0 | AJ123: =AH123-'人员人工-研发人员工资'!D123 -> 0
A124: ='人员人工-研发人员工资'!B124 -> 0 | AG124: =COUNTIF(B124:AF124,"●")+COUNTIF(B124:AF124,"▲")+COUNTIF(B124:AF124,"■")+COUNTIF(B124:AF124,"★")+COUNTIF(B124:AF124,"◆")+COUNTIF(B124:AF124,"✽")+COUNTIF(B124:AF124,"❖")+COUNTIF(B124:AF124,"✪")+COUNTIF(B124:AF124,"✿")+COUNTIF(B124:AF124,"✤") -> 0 | AH124: =COUNTIF(B124:AF124,"●")+COUNTIF(B124:AF124,"▲")+COUNTIF(B124:AF124,"■")+COUNTIF(B124:AF124,"★")+COUNTIF(B124:AF124,"◆")+COUNTIF(B124:AF124,"✽")+COUNTIF(B124:AF124,"❖")+COUNTIF(B124:AF124,"✪")+COUNTIF(B124:AF124,"✿")+COUNTIF(B124:AF124,"✤")+COUNTIF(B124:AF124,"√") -> 0 | AI124: =AG124-'人员人工-研发人员工资'!E124 -> 0 | AJ124: =AH124-'人员人工-研发人员工资'!D124 -> 0
A125: ='人员人工-研发人员工资'!B125 -> 0 | AG125: =COUNTIF(B125:AF125,"●")+COUNTIF(B125:AF125,"▲")+COUNTIF(B125:AF125,"■")+COUNTIF(B125:AF125,"★")+COUNTIF(B125:AF125,"◆")+COUNTIF(B125:AF125,"✽")+COUNTIF(B125:AF125,"❖")+COUNTIF(B125:AF125,"✪")+COUNTIF(B125:AF125,"✿")+COUNTIF(B125:AF125,"✤") -> 0 | AH125: =COUNTIF(B125:AF125,"●")+COUNTIF(B125:AF125,"▲")+COUNTIF(B125:AF125,"■")+COUNTIF(B125:AF125,"★")+COUNTIF(B125:AF125,"◆")+COUNTIF(B125:AF125,"✽")+COUNTIF(B125:AF125,"❖")+COUNTIF(B125:AF125,"✪")+COUNTIF(B125:AF125,"✿")+COUNTIF(B125:AF125,"✤")+COUNTIF(B125:AF125,"√") -> 0 | AI125: =AG125-'人员人工-研发人员工资'!E125 -> 0 | AJ125: =AH125-'人员人工-研发人员工资'!D125 -> 0
A126: ='人员人工-研发人员工资'!B126 -> 0 | AG126: =COUNTIF(B126:AF126,"●")+COUNTIF(B126:AF126,"▲")+COUNTIF(B126:AF126,"■")+COUNTIF(B126:AF126,"★")+COUNTIF(B126:AF126,"◆")+COUNTIF(B126:AF126,"✽")+COUNTIF(B126:AF126,"❖")+COUNTIF(B126:AF126,"✪")+COUNTIF(B126:AF126,"✿")+COUNTIF(B126:AF126,"✤") -> 0 | AH126: =COUNTIF(B126:AF126,"●")+COUNTIF(B126:AF126,"▲")+COUNTIF(B126:AF126,"■")+COUNTIF(B126:AF126,"★")+COUNTIF(B126:AF126,"◆")+COUNTIF(B126:AF126,"✽")+COUNTIF(B126:AF126,"❖")+COUNTIF(B126:AF126,"✪")+COUNTIF(B126:AF126,"✿")+COUNTIF(B126:AF126,"✤")+COUNTIF(B126:AF126,"√") -> 0 | AI126: =AG126-'人员人工-研发人员工资'!E126 -> 0 | AJ126: =AH126-'人员人工-研发人员工资'!D126 -> 0
A127: ='人员人工-研发人员工资'!B127 -> 0 | AG127: =COUNTIF(B127:AF127,"●")+COUNTIF(B127:AF127,"▲")+COUNTIF(B127:AF127,"■")+COUNTIF(B127:AF127,"★")+COUNTIF(B127:AF127,"◆")+COUNTIF(B127:AF127,"✽")+COUNTIF(B127:AF127,"❖")+COUNTIF(B127:AF127,"✪")+COUNTIF(B127:AF127,"✿")+COUNTIF(B127:AF127,"✤") -> 0 | AH127: =COUNTIF(B127:AF127,"●")+COUNTIF(B127:AF127,"▲")+COUNTIF(B127:AF127,"■")+COUNTIF(B127:AF127,"★")+COUNTIF(B127:AF127,"◆")+COUNTIF(B127:AF127,"✽")+COUNTIF(B127:AF127,"❖")+COUNTIF(B127:AF127,"✪")+COUNTIF(B127:AF127,"✿")+COUNTIF(B127:AF127,"✤")+COUNTIF(B127:AF127,"√") -> 0 | AI127: =AG127-'人员人工-研发人员工资'!E127 -> 0 | AJ127: =AH127-'人员人工-研发人员工资'!D127 -> 0
A128: ='人员人工-研发人员工资'!B128 -> 0 | AG128: =COUNTIF(B128:AF128,"●")+COUNTIF(B128:AF128,"▲")+COUNTIF(B128:AF128,"■")+COUNTIF(B128:AF128,"★")+COUNTIF(B128:AF128,"◆")+COUNTIF(B128:AF128,"✽")+COUNTIF(B128:AF128,"❖")+COUNTIF(B128:AF128,"✪")+COUNTIF(B128:AF128,"✿")+COUNTIF(B128:AF128,"✤") -> 0 | AH128: =COUNTIF(B128:AF128,"●")+COUNTIF(B128:AF128,"▲")+COUNTIF(B128:AF128,"■")+COUNTIF(B128:AF128,"★")+COUNTIF(B128:AF128,"◆")+COUNTIF(B128:AF128,"✽")+COUNTIF(B128:AF128,"❖")+COUNTIF(B128:AF128,"✪")+COUNTIF(B128:AF128,"✿")+COUNTIF(B128:AF128,"✤")+COUNTIF(B128:AF128,"√") -> 0 | AI128: =AG128-'人员人工-研发人员工资'!E128 -> 0 | AJ128: =AH128-'人员人工-研发人员工资'!D128 -> 0
A129: ='人员人工-研发人员工资'!B129 -> 0 | AG129: =COUNTIF(B129:AF129,"●")+COUNTIF(B129:AF129,"▲")+COUNTIF(B129:AF129,"■")+COUNTIF(B129:AF129,"★")+COUNTIF(B129:AF129,"◆")+COUNTIF(B129:AF129,"✽")+COUNTIF(B129:AF129,"❖")+COUNTIF(B129:AF129,"✪")+COUNTIF(B129:AF129,"✿")+COUNTIF(B129:AF129,"✤") -> 0 | AH129: =COUNTIF(B129:AF129,"●")+COUNTIF(B129:AF129,"▲")+COUNTIF(B129:AF129,"■")+COUNTIF(B129:AF129,"★")+COUNTIF(B129:AF129,"◆")+COUNTIF(B129:AF129,"✽")+COUNTIF(B129:AF129,"❖")+COUNTIF(B129:AF129,"✪")+COUNTIF(B129:AF129,"✿")+COUNTIF(B129:AF129,"✤")+COUNTIF(B129:AF129,"√") -> 0 | AI129: =AG129-'人员人工-研发人员工资'!E129 -> 0 | AJ129: =AH129-'人员人工-研发人员工资'!D129 -> 0
A130: ='人员人工-研发人员工资'!B130 -> 0 | AG130: =COUNTIF(B130:AF130,"●")+COUNTIF(B130:AF130,"▲")+COUNTIF(B130:AF130,"■")+COUNTIF(B130:AF130,"★")+COUNTIF(B130:AF130,"◆")+COUNTIF(B130:AF130,"✽")+COUNTIF(B130:AF130,"❖")+COUNTIF(B130:AF130,"✪")+COUNTIF(B130:AF130,"✿")+COUNTIF(B130:AF130,"✤") -> 0 | AH130: =COUNTIF(B130:AF130,"●")+COUNTIF(B130:AF130,"▲")+COUNTIF(B130:AF130,"■")+COUNTIF(B130:AF130,"★")+COUNTIF(B130:AF130,"◆")+COUNTIF(B130:AF130,"✽")+COUNTIF(B130:AF130,"❖")+COUNTIF(B130:AF130,"✪")+COUNTIF(B130:AF130,"✿")+COUNTIF(B130:AF130,"✤")+COUNTIF(B130:AF130,"√") -> 0 | AI130: =AG130-'人员人工-研发人员工资'!E130 -> 0 | AJ130: =AH130-'人员人工-研发人员工资'!D130 -> 0
A131: ='人员人工-研发人员工资'!B131 -> 0 | AG131: =COUNTIF(B131:AF131,"●")+COUNTIF(B131:AF131,"▲")+COUNTIF(B131:AF131,"■")+COUNTIF(B131:AF131,"★")+COUNTIF(B131:AF131,"◆")+COUNTIF(B131:AF131,"✽")+COUNTIF(B131:AF131,"❖")+COUNTIF(B131:AF131,"✪")+COUNTIF(B131:AF131,"✿")+COUNTIF(B131:AF131,"✤") -> 0 | AH131: =COUNTIF(B131:AF131,"●")+COUNTIF(B131:AF131,"▲")+COUNTIF(B131:AF131,"■")+COUNTIF(B131:AF131,"★")+COUNTIF(B131:AF131,"◆")+COUNTIF(B131:AF131,"✽")+COUNTIF(B131:AF131,"❖")+COUNTIF(B131:AF131,"✪")+COUNTIF(B131:AF131,"✿")+COUNTIF(B131:AF131,"✤")+COUNTIF(B131:AF131,"√") -> 0 | AI131: =AG131-'人员人工-研发人员工资'!E131 -> 0 | AJ131: =AH131-'人员人工-研发人员工资'!D131 -> 0
... A148: ='人员人工-研发人员工资'!B148 -> 0 | AG148: =COUNTIF(B148:AF148,"●")+COUNTIF(B148:AF148,"▲")+COUNTIF(B148:AF148,"■")+COUNTIF(B148:AF148,"★")+COUNTIF(B148:AF148,"◆")+COUNTIF(B148:AF148,"✽")+COUNTIF(B148:AF148,"❖")+COUNTIF(B148:AF148,"✪")+COUNTIF(B148:AF148,"✿")+COUNTIF(B148:AF148,"✤") -> 0 | AH148: =COUNTIF(B148:AF148,"●")+COUNTIF(B148:AF148,"▲")+COUNTIF(B148:AF148,"■")+COUNTIF(B148:AF148,"★")+COUNTIF(B148:AF148,"◆")+COUNTIF(B148:AF148,"✽")+COUNTIF(B148:AF148,"❖")+COUNTIF(B148:AF148,"✪")+COUNTIF(B148:AF148,"✿")+COUNTIF(B148:AF148,"✤")+COUNTIF(B148:AF148,"√") -> 0 | AI148: =AG148-'人员人工-研发人员工资'!E148 -> 0 | AJ148: =AH148-'人员人工-研发人员工资'!D148 -> 0
A149: 注： | B149: ● | C149: ▲ | D149: ■ | E149: ★ | F149: ◆ | G149: ✽ | H149: ❖ | I149: ✪ | J149: ✿ | K149: ✤ | L149: √ | M149: ×
B150: 1 | C150: 2 | D150: 3 | E150: 4 | F150: 5 | G150: 6 | H150: 7 | I150: 8 | J150: 9 | K150: 10 | L150: 其他出勤 | M150: 未出勤
A153: 2023年5月份研发人员考勤表
A155: 姓名 | B155: 星期一 | C155: 星期二 | D155: 星期三 | E155: 星期四 | F155: 星期五 | G155: 星期六 | H155: 星期日 | I155: 星期一 | J155: 星期二 | K155: 星期三 | L155: 星期四 | M155: 星期五 | N155: 星期六 | O155: 星期日 | P155: 星期一 | Q155: 星期二 | R155: 星期三 | S155: 星期四 | T155: 星期五 | U155: 星期六 | V155: 星期日 | W155: 星期一 | X155: 星期二 | Y155: 星期三 | Z155: 星期四 | AA155: 星期五 | AB155: 星期六 | AC155: 星期日 | AD155: 星期一 | AE155: 星期二 | AF155: 星期三 | AG155: 研发天数 | AH155: 出勤天数 | AI155: 研发天数验证 | AJ155: 出勤天数验证
B156: 1 | C156: 2 | D156: 3 | E156: 4 | F156: 5 | G156: 6 | H156: 7 | I156: 8 | J156: 9 | K156: 10 | L156: 11 | M156: 12 | N156: 13 | O156: 14 | P156: 15 | Q156: 16 | R156: 17 | S156: 18 | T156: 19 | U156: 20 | V156: 21 | W156: 22 | X156: 23 | Y156: 24 | Z156: 25 | AA156: 26 | AB156: 27 | AC156: 28 | AD156: 29 | AE156: 30 | AF156: 31
A157: ='人员人工-研发人员工资'!B157 -> 0 | B157: × | C157: × | D157: × | E157: ● | F157: ● | G157: ● | H157: × | I157: ● | J157: ● | K157: ● | L157: √ | M157: √ | N157: × | O157: × | P157: ▲ | Q157: ▲ | R157: ▲ | S157: ▲ | T157: ▲ | U157: × | V157: × | W157: √ | X157: √ | Y157: ■ | Z157: ■ | AA157: ■ | AB157: × | AC157: × | AD157: ■ | AE157: ■ | AF157: ■ | AG157: =COUNTIF(B157:AF157,"●")+COUNTIF(B157:AF157,"▲")+COUNTIF(B157:AF157,"■")+COUNTIF(B157:AF157,"★")+COUNTIF(B157:AF157,"◆")+COUNTIF(B157:AF157,"✽")+COUNTIF(B157:AF157,"❖")+COUNTIF(B157:AF157,"✪")+COUNTIF(B157:AF157,"✿")+COUNTIF(B157:AF157,"✤") -> 17 | AH157: =COUNTIF(B157:AF157,"●")+COUNTIF(B157:AF157,"▲")+COUNTIF(B157:AF157,"■")+COUNTIF(B157:AF157,"★")+COUNTIF(B157:AF157,"◆")+COUNTIF(B157:AF157,"✽")+COUNTIF(B157:AF157,"❖")+COUNTIF(B157:AF157,"✪")+COUNTIF(B157:AF157,"✿")+COUNTIF(B157:AF157,"✤")+COUNTIF(B157:AF157,"√") -> 21 | AI157: =AG157-'人员人工-研发人员工资'!E157 -> 17 | AJ157: =AH157-'人员人工-研发人员工资'!D157 -> 21
A158: ='人员人工-研发人员工资'!B158 -> 0 | AG158: =COUNTIF(B158:AF158,"●")+COUNTIF(B158:AF158,"▲")+COUNTIF(B158:AF158,"■")+COUNTIF(B158:AF158,"★")+COUNTIF(B158:AF158,"◆")+COUNTIF(B158:AF158,"✽")+COUNTIF(B158:AF158,"❖")+COUNTIF(B158:AF158,"✪")+COUNTIF(B158:AF158,"✿")+COUNTIF(B158:AF158,"✤") -> 0 | AH158: =COUNTIF(B158:AF158,"●")+COUNTIF(B158:AF158,"▲")+COUNTIF(B158:AF158,"■")+COUNTIF(B158:AF158,"★")+COUNTIF(B158:AF158,"◆")+COUNTIF(B158:AF158,"✽")+COUNTIF(B158:AF158,"❖")+COUNTIF(B158:AF158,"✪")+COUNTIF(B158:AF158,"✿")+COUNTIF(B158:AF158,"✤")+COUNTIF(B158:AF158,"√") -> 0 | AI158: =AG158-'人员人工-研发人员工资'!E158 -> 0 | AJ158: =AH158-'人员人工-研发人员工资'!D158 -> 0
A159: ='人员人工-研发人员工资'!B159 -> 0 | AG159: =COUNTIF(B159:AF159,"●")+COUNTIF(B159:AF159,"▲")+COUNTIF(B159:AF159,"■")+COUNTIF(B159:AF159,"★")+COUNTIF(B159:AF159,"◆")+COUNTIF(B159:AF159,"✽")+COUNTIF(B159:AF159,"❖")+COUNTIF(B159:AF159,"✪")+COUNTIF(B159:AF159,"✿")+COUNTIF(B159:AF159,"✤") -> 0 | AH159: =COUNTIF(B159:AF159,"●")+COUNTIF(B159:AF159,"▲")+COUNTIF(B159:AF159,"■")+COUNTIF(B159:AF159,"★")+COUNTIF(B159:AF159,"◆")+COUNTIF(B159:AF159,"✽")+COUNTIF(B159:AF159,"❖")+COUNTIF(B159:AF159,"✪")+COUNTIF(B159:AF159,"✿")+COUNTIF(B159:AF159,"✤")+COUNTIF(B159:AF159,"√") -> 0 | AI159: =AG159-'人员人工-研发人员工资'!E159 -> 0 | AJ159: =AH159-'人员人工-研发人员工资'!D159 -> 0
A160: ='人员人工-研发人员工资'!B160 -> 0 | AG160: =COUNTIF(B160:AF160,"●")+COUNTIF(B160:AF160,"▲")+COUNTIF(B160:AF160,"■")+COUNTIF(B160:AF160,"★")+COUNTIF(B160:AF160,"◆")+COUNTIF(B160:AF160,"✽")+COUNTIF(B160:AF160,"❖")+COUNTIF(B160:AF160,"✪")+COUNTIF(B160:AF160,"✿")+COUNTIF(B160:AF160,"✤") -> 0 | AH160: =COUNTIF(B160:AF160,"●")+COUNTIF(B160:AF160,"▲")+COUNTIF(B160:AF160,"■")+COUNTIF(B160:AF160,"★")+COUNTIF(B160:AF160,"◆")+COUNTIF(B160:AF160,"✽")+COUNTIF(B160:AF160,"❖")+COUNTIF(B160:AF160,"✪")+COUNTIF(B160:AF160,"✿")+COUNTIF(B160:AF160,"✤")+COUNTIF(B160:AF160,"√") -> 0 | AI160: =AG160-'人员人工-研发人员工资'!E160 -> 0 | AJ160: =AH160-'人员人工-研发人员工资'!D160 -> 0
A161: ='人员人工-研发人员工资'!B161 -> 0 | AG161: =COUNTIF(B161:AF161,"●")+COUNTIF(B161:AF161,"▲")+COUNTIF(B161:AF161,"■")+COUNTIF(B161:AF161,"★")+COUNTIF(B161:AF161,"◆")+COUNTIF(B161:AF161,"✽")+COUNTIF(B161:AF161,"❖")+COUNTIF(B161:AF161,"✪")+COUNTIF(B161:AF161,"✿")+COUNTIF(B161:AF161,"✤") -> 0 | AH161: =COUNTIF(B161:AF161,"●")+COUNTIF(B161:AF161,"▲")+COUNTIF(B161:AF161,"■")+COUNTIF(B161:AF161,"★")+COUNTIF(B161:AF161,"◆")+COUNTIF(B161:AF161,"✽")+COUNTIF(B161:AF161,"❖")+COUNTIF(B161:AF161,"✪")+COUNTIF(B161:AF161,"✿")+COUNTIF(B161:AF161,"✤")+COUNTIF(B161:AF161,"√") -> 0 | AI161: =AG161-'人员人工-研发人员工资'!E161 -> 0 | AJ161: =AH161-'人员人工-研发人员工资'!D161 -> 0
A162: ='人员人工-研发人员工资'!B162 -> 0 | AG162: =COUNTIF(B162:AF162,"●")+COUNTIF(B162:AF162,"▲")+COUNTIF(B162:AF162,"■")+COUNTIF(B162:AF162,"★")+COUNTIF(B162:AF162,"◆")+COUNTIF(B162:AF162,"✽")+COUNTIF(B162:AF162,"❖")+COUNTIF(B162:AF162,"✪")+COUNTIF(B162:AF162,"✿")+COUNTIF(B162:AF162,"✤") -> 0 | AH162: =COUNTIF(B162:AF162,"●")+COUNTIF(B162:AF162,"▲")+COUNTIF(B162:AF162,"■")+COUNTIF(B162:AF162,"★")+COUNTIF(B162:AF162,"◆")+COUNTIF(B162:AF162,"✽")+COUNTIF(B162:AF162,"❖")+COUNTIF(B162:AF162,"✪")+COUNTIF(B162:AF162,"✿")+COUNTIF(B162:AF162,"✤")+COUNTIF(B162:AF162,"√") -> 0 | AI162: =AG162-'人员人工-研发人员工资'!E162 -> 0 | AJ162: =AH162-'人员人工-研发人员工资'!D162 -> 0
A163: ='人员人工-研发人员工资'!B163 -> 0 | AG163: =COUNTIF(B163:AF163,"●")+COUNTIF(B163:AF163,"▲")+COUNTIF(B163:AF163,"■")+COUNTIF(B163:AF163,"★")+COUNTIF(B163:AF163,"◆")+COUNTIF(B163:AF163,"✽")+COUNTIF(B163:AF163,"❖")+COUNTIF(B163:AF163,"✪")+COUNTIF(B163:AF163,"✿")+COUNTIF(B163:AF163,"✤") -> 0 | AH163: =COUNTIF(B163:AF163,"●")+COUNTIF(B163:AF163,"▲")+COUNTIF(B163:AF163,"■")+COUNTIF(B163:AF163,"★")+COUNTIF(B163:AF163,"◆")+COUNTIF(B163:AF163,"✽")+COUNTIF(B163:AF163,"❖")+COUNTIF(B163:AF163,"✪")+COUNTIF(B163:AF163,"✿")+COUNTIF(B163:AF163,"✤")+COUNTIF(B163:AF163,"√") -> 0 | AI163: =AG163-'人员人工-研发人员工资'!E163 -> 0 | AJ163: =AH163-'人员人工-研发人员工资'!D163 -> 0
A164: ='人员人工-研发人员工资'!B164 -> 0 | AG164: =COUNTIF(B164:AF164,"●")+COUNTIF(B164:AF164,"▲")+COUNTIF(B164:AF164,"■")+COUNTIF(B164:AF164,"★")+COUNTIF(B164:AF164,"◆")+COUNTIF(B164:AF164,"✽")+COUNTIF(B164:AF164,"❖")+COUNTIF(B164:AF164,"✪")+COUNTIF(B164:AF164,"✿")+COUNTIF(B164:AF164,"✤") -> 0 | AH164: =COUNTIF(B164:AF164,"●")+COUNTIF(B164:AF164,"▲")+COUNTIF(B164:AF164,"■")+COUNTIF(B164:AF164,"★")+COUNTIF(B164:AF164,"◆")+COUNTIF(B164:AF164,"✽")+COUNTIF(B164:AF164,"❖")+COUNTIF(B164:AF164,"✪")+COUNTIF(B164:AF164,"✿")+COUNTIF(B164:AF164,"✤")+COUNTIF(B164:AF164,"√") -> 0 | AI164: =AG164-'人员人工-研发人员工资'!E164 -> 0 | AJ164: =AH164-'人员人工-研发人员工资'!D164 -> 0
A165: ='人员人工-研发人员工资'!B165 -> 0 | AG165: =COUNTIF(B165:AF165,"●")+COUNTIF(B165:AF165,"▲")+COUNTIF(B165:AF165,"■")+COUNTIF(B165:AF165,"★")+COUNTIF(B165:AF165,"◆")+COUNTIF(B165:AF165,"✽")+COUNTIF(B165:AF165,"❖")+COUNTIF(B165:AF165,"✪")+COUNTIF(B165:AF165,"✿")+COUNTIF(B165:AF165,"✤") -> 0 | AH165: =COUNTIF(B165:AF165,"●")+COUNTIF(B165:AF165,"▲")+COUNTIF(B165:AF165,"■")+COUNTIF(B165:AF165,"★")+COUNTIF(B165:AF165,"◆")+COUNTIF(B165:AF165,"✽")+COUNTIF(B165:AF165,"❖")+COUNTIF(B165:AF165,"✪")+COUNTIF(B165:AF165,"✿")+COUNTIF(B165:AF165,"✤")+COUNTIF(B165:AF165,"√") -> 0 | AI165: =AG165-'人员人工-研发人员工资'!E165 -> 0 | AJ165: =AH165-'人员人工-研发人员工资'!D165 -> 0
A166: ='人员人工-研发人员工资'!B166 -> 0 | AG166: =COUNTIF(B166:AF166,"●")+COUNTIF(B166:AF166,"▲")+COUNTIF(B166:AF166,"■")+COUNTIF(B166:AF166,"★")+COUNTIF(B166:AF166,"◆")+COUNTIF(B166:AF166,"✽")+COUNTIF(B166:AF166,"❖")+COUNTIF(B166:AF166,"✪")+COUNTIF(B166:AF166,"✿")+COUNTIF(B166:AF166,"✤") -> 0 | AH166: =COUNTIF(B166:AF166,"●")+COUNTIF(B166:AF166,"▲")+COUNTIF(B166:AF166,"■")+COUNTIF(B166:AF166,"★")+COUNTIF(B166:AF166,"◆")+COUNTIF(B166:AF166,"✽")+COUNTIF(B166:AF166,"❖")+COUNTIF(B166:AF166,"✪")+COUNTIF(B166:AF166,"✿")+COUNTIF(B166:AF166,"✤")+COUNTIF(B166:AF166,"√") -> 0 | AI166: =AG166-'人员人工-研发人员工资'!E166 -> 0 | AJ166: =AH166-'人员人工-研发人员工资'!D166 -> 0
A167: ='人员人工-研发人员工资'!B167 -> 0 | AG167: =COUNTIF(B167:AF167,"●")+COUNTIF(B167:AF167,"▲")+COUNTIF(B167:AF167,"■")+COUNTIF(B167:AF167,"★")+COUNTIF(B167:AF167,"◆")+COUNTIF(B167:AF167,"✽")+COUNTIF(B167:AF167,"❖")+COUNTIF(B167:AF167,"✪")+COUNTIF(B167:AF167,"✿")+COUNTIF(B167:AF167,"✤") -> 0 | AH167: =COUNTIF(B167:AF167,"●")+COUNTIF(B167:AF167,"▲")+COUNTIF(B167:AF167,"■")+COUNTIF(B167:AF167,"★")+COUNTIF(B167:AF167,"◆")+COUNTIF(B167:AF167,"✽")+COUNTIF(B167:AF167,"❖")+COUNTIF(B167:AF167,"✪")+COUNTIF(B167:AF167,"✿")+COUNTIF(B167:AF167,"✤")+COUNTIF(B167:AF167,"√") -> 0 | AI167: =AG167-'人员人工-研发人员工资'!E167 -> 0 | AJ167: =AH167-'人员人工-研发人员工资'!D167 -> 0
A168: ='人员人工-研发人员工资'!B168 -> 0 | AG168: =COUNTIF(B168:AF168,"●")+COUNTIF(B168:AF168,"▲")+COUNTIF(B168:AF168,"■")+COUNTIF(B168:AF168,"★")+COUNTIF(B168:AF168,"◆")+COUNTIF(B168:AF168,"✽")+COUNTIF(B168:AF168,"❖")+COUNTIF(B168:AF168,"✪")+COUNTIF(B168:AF168,"✿")+COUNTIF(B168:AF168,"✤") -> 0 | AH168: =COUNTIF(B168:AF168,"●")+COUNTIF(B168:AF168,"▲")+COUNTIF(B168:AF168,"■")+COUNTIF(B168:AF168,"★")+COUNTIF(B168:AF168,"◆")+COUNTIF(B168:AF168,"✽")+COUNTIF(B168:AF168,"❖")+COUNTIF(B168:AF168,"✪")+COUNTIF(B168:AF168,"✿")+COUNTIF(B168:AF168,"✤")+COUNTIF(B168:AF168,"√") -> 0 | AI168: =AG168-'人员人工-研发人员工资'!E168 -> 0 | AJ168: =AH168-'人员人工-研发人员工资'!D168 -> 0
A169: ='人员人工-研发人员工资'!B169 -> 0 | AG169: =COUNTIF(B169:AF169,"●")+COUNTIF(B169:AF169,"▲")+COUNTIF(B169:AF169,"■")+COUNTIF(B169:AF169,"★")+COUNTIF(B169:AF169,"◆")+COUNTIF(B169:AF169,"✽")+COUNTIF(B169:AF169,"❖")+COUNTIF(B169:AF169,"✪")+COUNTIF(B169:AF169,"✿")+COUNTIF(B169:AF169,"✤") -> 0 | AH169: =COUNTIF(B169:AF169,"●")+COUNTIF(B169:AF169,"▲")+COUNTIF(B169:AF169,"■")+COUNTIF(B169:AF169,"★")+COUNTIF(B169:AF169,"◆")+COUNTIF(B169:AF169,"✽")+COUNTIF(B169:AF169,"❖")+COUNTIF(B169:AF169,"✪")+COUNTIF(B169:AF169,"✿")+COUNTIF(B169:AF169,"✤")+COUNTIF(B169:AF169,"√") -> 0 | AI169: =AG169-'人员人工-研发人员工资'!E169 -> 0 | AJ169: =AH169-'人员人工-研发人员工资'!D169 -> 0
... A186: ='人员人工-研发人员工资'!B186 -> 0 | AG186: =COUNTIF(B186:AF186,"●")+COUNTIF(B186:AF186,"▲")+COUNTIF(B186:AF186,"■")+COUNTIF(B186:AF186,"★")+COUNTIF(B186:AF186,"◆")+COUNTIF(B186:AF186,"✽")+COUNTIF(B186:AF186,"❖")+COUNTIF(B186:AF186,"✪")+COUNTIF(B186:AF186,"✿")+COUNTIF(B186:AF186,"✤") -> 0 | AH186: =COUNTIF(B186:AF186,"●")+COUNTIF(B186:AF186,"▲")+COUNTIF(B186:AF186,"■")+COUNTIF(B186:AF186,"★")+COUNTIF(B186:AF186,"◆")+COUNTIF(B186:AF186,"✽")+COUNTIF(B186:AF186,"❖")+COUNTIF(B186:AF186,"✪")+COUNTIF(B186:AF186,"✿")+COUNTIF(B186:AF186,"✤")+COUNTIF(B186:AF186,"√") -> 0 | AI186: =AG186-'人员人工-研发人员工资'!E186 -> 0 | AJ186: =AH186-'人员人工-研发人员工资'!D186 -> 0
A187: 注： | B187: ● | C187: ▲ | D187: ■ | E187: ★ | F187: ◆ | G187: ✽ | H187: ❖ | I187: ✪ | J187: ✿ | K187: ✤ | L187: √ | M187: ×
B188: 1 | C188: 2 | D188: 3 | E188: 4 | F188: 5 | G188: 6 | H188: 7 | I188: 8 | J188: 9 | K188: 10 | L188: 其他出勤 | M188: 未出勤
A190: 2023年6月份研发人员考勤表
A192: 姓名 | B192: 星期四 | C192: 星期五 | D192: 星期六 | E192: 星期日 | F192: 星期一 | G192: 星期二 | H192: 星期三 | I192: 星期四 | J192: 星期五 | K192: 星期六 | L192: 星期日 | M192: 星期一 | N192: 星期二 | O192: 星期三 | P192: 星期四 | Q192: 星期五 | R192: 星期六 | S192: 星期日 | T192: 星期一 | U192: 星期二 | V192: 星期三 | W192: 星期四 | X192: 星期五 | Y192: 星期六 | Z192: 星期日 | AA192: 星期一 | AB192: 星期二 | AC192: 星期三 | AD192: 星期四 | AE192: 星期五 | AG192: 研发天数 | AH192: 出勤天数 | AI192: 研发天数验证 | AJ192: 出勤天数验证
B193: 1 | C193: 2 | D193: 3 | E193: 4 | F193: 5 | G193: 6 | H193: 7 | I193: 8 | J193: 9 | K193: 10 | L193: 11 | M193: 12 | N193: 13 | O193: 14 | P193: 15 | Q193: 16 | R193: 17 | S193: 18 | T193: 19 | U193: 20 | V193: 21 | W193: 22 | X193: 23 | Y193: 24 | Z193: 25 | AA193: 26 | AB193: 27 | AC193: 28 | AD193: 29 | AE193: 30
A194: ='人员人工-研发人员工资'!B194 -> 0 | B194: √ | C194: √ | D194: × | E194: × | F194: ● | G194: ● | H194: ● | I194: ● | J194: ● | K194: × | L194: × | M194: ▲ | N194: ▲ | O194: ▲ | P194: ▲ | Q194: ▲ | R194: × | S194: × | T194: ▲ | U194: ▲ | V194: √ | W194: × | X194: × | Y194: × | Z194: √ | AA194: ■ | AB194: ■ | AC194: ■ | AD194: ■ | AE194: ■ | AG194: =COUNTIF(B194:AF194,"●")+COUNTIF(B194:AF194,"▲")+COUNTIF(B194:AF194,"■")+COUNTIF(B194:AF194,"★")+COUNTIF(B194:AF194,"◆")+COUNTIF(B194:AF194,"✽")+COUNTIF(B194:AF194,"❖")+COUNTIF(B194:AF194,"✪")+COUNTIF(B194:AF194,"✿")+COUNTIF(B194:AF194,"✤") -> 17 | AH194: =COUNTIF(B194:AF194,"●")+COUNTIF(B194:AF194,"▲")+COUNTIF(B194:AF194,"■")+COUNTIF(B194:AF194,"★")+COUNTIF(B194:AF194,"◆")+COUNTIF(B194:AF194,"✽")+COUNTIF(B194:AF194,"❖")+COUNTIF(B194:AF194,"✪")+COUNTIF(B194:AF194,"✿")+COUNTIF(B194:AF194,"✤")+COUNTIF(B194:AF194,"√") -> 21 | AI194: =AG194-'人员人工-研发人员工资'!E194 -> 17 | AJ194: =AH194-'人员人工-研发人员工资'!D194 -> 21
A195: ='人员人工-研发人员工资'!B195 -> 0 | AG195: =COUNTIF(B195:AF195,"●")+COUNTIF(B195:AF195,"▲")+COUNTIF(B195:AF195,"■")+COUNTIF(B195:AF195,"★")+COUNTIF(B195:AF195,"◆")+COUNTIF(B195:AF195,"✽")+COUNTIF(B195:AF195,"❖")+COUNTIF(B195:AF195,"✪")+COUNTIF(B195:AF195,"✿")+COUNTIF(B195:AF195,"✤") -> 0 | AH195: =COUNTIF(B195:AF195,"●")+COUNTIF(B195:AF195,"▲")+COUNTIF(B195:AF195,"■")+COUNTIF(B195:AF195,"★")+COUNTIF(B195:AF195,"◆")+COUNTIF(B195:AF195,"✽")+COUNTIF(B195:AF195,"❖")+COUNTIF(B195:AF195,"✪")+COUNTIF(B195:AF195,"✿")+COUNTIF(B195:AF195,"✤")+COUNTIF(B195:AF195,"√") -> 0 | AI195: =AG195-'人员人工-研发人员工资'!E195 -> 0 | AJ195: =AH195-'人员人工-研发人员工资'!D195 -> 0
...

Sheet 人员人工-研发人员社保
B1: 2025年1月份研发人员社保项目分摊表
A3: 序号 | B3: 姓名 | C3: 月社保 | D3: 出勤天数 | E3: 研发天数合计 | F3: 研发社保合计 | G3: =立项!$A$3 -> RD01 | I3: =立项!$A$4 -> RD02 | K3: =立项!$A$5 -> RD03 | M3: =立项!$A$6 -> RD04 | O3: =立项!$A$7 -> RD05 | Q3: =立项!$A$8 -> RD06 | S3: =立项!$A$9 -> RD07 | U3: =立项!$A$10 -> RD08 | W3: =立项!$A$11 -> RD09 | Y3: =立项!$A$12 -> RD10
G4: =立项!C3 -> 0 | I4: =立项!C4 -> 0 | K4: =立项!C5 -> 0 | M4: =立项!C6 -> 0 | O4: =立项!C7 -> 0 | Q4: =立项!C8 -> 0 | S4: =立项!C9 -> 0 | U4: =立项!C10 -> 0 | W4: =立项!C11 -> 0 | Y4: =立项!C12 -> 0
G5: 研发天数 | H5: 研发社保 | I5: 研发天数 | J5: 研发社保 | K5: 研发天数 | L5: 研发社保 | M5: 研发天数 | N5: 研发社保 | O5: 研发天数 | P5: 研发社保 | Q5: 研发天数 | R5: 研发社保 | S5: 研发天数 | T5: 研发社保 | U5: 研发天数 | V5: 研发社保 | W5: 研发天数 | X5: 研发社保 | Y5: 研发天数 | Z5: 研发社保
A6: 1 | B6: ='人员人工-研发人员工资'!B6 -> 0 | D6: ='人员人工-研发人员工资'!D6 -> 0 | E6: =G6+I6+K6+M6+O6+Q6+S6+U6+W6+Y6 -> 0 | F6: =H6+J6+L6+N6+P6+R6+T6+V6+X6+Z6 -> 0 | G6: ='人员人工-研发人员工资'!G6 -> 0 | H6: =IF($D6=0,0,ROUND(G6/$D6*$C6,2)) -> 0 | I6: ='人员人工-研发人员工资'!I6 -> 0 | J6: =IF($D6=0,0,ROUND(I6/$D6*$C6,2)) -> 0 | K6: ='人员人工-研发人员工资'!K6 -> 0 | L6: =IF($D6=0,0,ROUND(K6/$D6*$C6,2)) -> 0 | M6: ='人员人工-研发人员工资'!M6 -> 0 | N6: =IF($D6=0,0,ROUND(M6/$D6*$C6,2)) -> 0 | O6: ='人员人工-研发人员工资'!O6 -> 0 | P6: =IF($D6=0,0,ROUND(O6/$D6*$C6,2)) -> 0 | Q6: ='人员人工-研发人员工资'!Q6 -> 0 | R6: =IF($D6=0,0,ROUND(Q6/$D6*$C6,2)) -> 0 | S6: ='人员人工-研发人员工资'!S6 -> 0 | T6: =IF($D6=0,0,ROUND(S6/$D6*$C6,2)) -> 0 | U6: ='人员人工-研发人员工资'!U6 -> 0 | V6: =IF($D6=0,0,ROUND(U6/$D6*$C6,2)) -> 0 | W6: ='人员人工-研发人员工资'!W6 -> 0 | X6: =IF($D6=0,0,ROUND(W6/$D6*$C6,2)) -> 0 | Y6: ='人员人工-研发人员工资'!Y6 -> 0 | Z6: =IF($D6=0,0,ROUND(Y6/$D6*$C6,2)) -> 0
A7: 2 | B7: ='人员人工-研发人员工资'!B7 -> 0 | D7: ='人员人工-研发人员工资'!D7 -> 0 | E7: =G7+I7+K7+M7+O7+Q7+S7+U7+W7+Y7 -> 0 | F7: =H7+J7+L7+N7+P7+R7+T7+V7+X7+Z7 -> 0 | G7: ='人员人工-研发人员工资'!G7 -> 0 | H7: =IF($D7=0,0,ROUND(G7/$D7*$C7,2)) -> 0 | I7: ='人员人工-研发人员工资'!I7 -> 0 | J7: =IF($D7=0,0,ROUND(I7/$D7*$C7,2)) -> 0 | K7: ='人员人工-研发人员工资'!K7 -> 0 | L7: =IF($D7=0,0,ROUND(K7/$D7*$C7,2)) -> 0 | M7: ='人员人工-研发人员工资'!M7 -> 0 | N7: =IF($D7=0,0,ROUND(M7/$D7*$C7,2)) -> 0 | O7: ='人员人工-研发人员工资'!O7 -> 0 | P7: =IF($D7=0,0,ROUND(O7/$D7*$C7,2)) -> 0 | Q7: ='人员人工-研发人员工资'!Q7 -> 0 | R7: =IF($D7=0,0,ROUND(Q7/$D7*$C7,2)) -> 0 | S7: ='人员人工-研发人员工资'!S7 -> 0 | T7: =IF($D7=0,0,ROUND(S7/$D7*$C7,2)) -> 0 | U7: ='人员人工-研发人员工资'!U7 -> 0 | V7: =IF($D7=0,0,ROUND(U7/$D7*$C7,2)) -> 0 | W7: ='人员人工-研发人员工资'!W7 -> 0 | X7: =IF($D7=0,0,ROUND(W7/$D7*$C7,2)) -> 0 | Y7: ='人员人工-研发人员工资'!Y7 -> 0 | Z7: =IF($D7=0,0,ROUND(Y7/$D7*$C7,2)) -> 0
A8: 3 | B8: ='人员人工-研发人员工资'!B8 -> 0 | D8: ='人员人工-研发人员工资'!D8 -> 0 | E8: =G8+I8+K8+M8+O8+Q8+S8+U8+W8+Y8 -> 0 | F8: =H8+J8+L8+N8+P8+R8+T8+V8+X8+Z8 -> 0 | G8: ='人员人工-研发人员工资'!G8 -> 0 | H8: =IF($D8=0,0,ROUND(G8/$D8*$C8,2)) -> 0 | I8: ='人员人工-研发人员工资'!I8 -> 0 | J8: =IF($D8=0,0,ROUND(I8/$D8*$C8,2)) -> 0 | K8: ='人员人工-研发人员工资'!K8 -> 0 | L8: =IF($D8=0,0,ROUND(K8/$D8*$C8,2)) -> 0 | M8: ='人员人工-研发人员工资'!M8 -> 0 | N8: =IF($D8=0,0,ROUND(M8/$D8*$C8,2)) -> 0 | O8: ='人员人工-研发人员工资'!O8 -> 0 | P8: =IF($D8=0,0,ROUND(O8/$D8*$C8,2)) -> 0 | Q8: ='人员人工-研发人员工资'!Q8 -> 0 | R8: =IF($D8=0,0,ROUND(Q8/$D8*$C8,2)) -> 0 | S8: ='人员人工-研发人员工资'!S8 -> 0 | T8: =IF($D8=0,0,ROUND(S8/$D8*$C8,2)) -> 0 | U8: ='人员人工-研发人员工资'!U8 -> 0 | V8: =IF($D8=0,0,ROUND(U8/$D8*$C8,2)) -> 0 | W8: ='人员人工-研发人员工资'!W8 -> 0 | X8: =IF($D8=0,0,ROUND(W8/$D8*$C8,2)) -> 0 | Y8: ='人员人工-研发人员工资'!Y8 -> 0 | Z8: =IF($D8=0,0,ROUND(Y8/$D8*$C8,2)) -> 0
A9: 4 | B9: ='人员人工-研发人员工资'!B9 -> 0 | D9: ='人员人工-研发人员工资'!D9 -> 0 | E9: =G9+I9+K9+M9+O9+Q9+S9+U9+W9+Y9 -> 0 | F9: =H9+J9+L9+N9+P9+R9+T9+V9+X9+Z9 -> 0 | G9: ='人员人工-研发人员工资'!G9 -> 0 | H9: =IF($D9=0,0,ROUND(G9/$D9*$C9,2)) -> 0 | I9: ='人员人工-研发人员工资'!I9 -> 0 | J9: =IF($D9=0,0,ROUND(I9/$D9*$C9,2)) -> 0 | K9: ='人员人工-研发人员工资'!K9 -> 0 | L9: =IF($D9=0,0,ROUND(K9/$D9*$C9,2)) -> 0 | M9: ='人员人工-研发人员工资'!M9 -> 0 | N9: =IF($D9=0,0,ROUND(M9/$D9*$C9,2)) -> 0 | O9: ='人员人工-研发人员工资'!O9 -> 0 | P9: =IF($D9=0,0,ROUND(O9/$D9*$C9,2)) -> 0 | Q9: ='人员人工-研发人员工资'!Q9 -> 0 | R9: =IF($D9=0,0,ROUND(Q9/$D9*$C9,2)) -> 0 | S9: ='人员人工-研发人员工资'!S9 -> 0 | T9: =IF($D9=0,0,ROUND(S9/$D9*$C9,2)) -> 0 | U9: ='人员人工-研发人员工资'!U9 -> 0 | V9: =IF($D9=0,0,ROUND(U9/$D9*$C9,2)) -> 0 | W9: ='人员人工-研发人员工资'!W9 -> 0 | X9: =IF($D9=0,0,ROUND(W9/$D9*$C9,2)) -> 0 | Y9: ='人员人工-研发人员工资'!Y9 -> 0 | Z9: =IF($D9=0,0,ROUND(Y9/$D9*$C9,2)) -> 0
A10: 5 | B10: ='人员人工-研发人员工资'!B10 -> 0 | D10: ='人员人工-研发人员工资'!D10 -> 0 | E10: =G10+I10+K10+M10+O10+Q10+S10+U10+W10+Y10 -> 0 | F10: =H10+J10+L10+N10+P10+R10+T10+V10+X10+Z10 -> 0 | G10: ='人员人工-研发人员工资'!G10 -> 0 | H10: =IF($D10=0,0,ROUND(G10/$D10*$C10,2)) -> 0 | I10: ='人员人工-研发人员工资'!I10 -> 0 | J10: =IF($D10=0,0,ROUND(I10/$D10*$C10,2)) -> 0 | K10: ='人员人工-研发人员工资'!K10 -> 0 | L10: =IF($D10=0,0,ROUND(K10/$D10*$C10,2)) -> 0 | M10: ='人员人工-研发人员工资'!M10 -> 0 | N10: =IF($D10=0,0,ROUND(M10/$D10*$C10,2)) -> 0 | O10: ='人员人工-研发人员工资'!O10 -> 0 | P10: =IF($D10=0,0,ROUND(O10/$D10*$C10,2)) -> 0 | Q10: ='人员人工-研发人员工资'!Q10 -> 0 | R10: =IF($D10=0,0,ROUND(Q10/$D10*$C10,2)) -> 0 | S10: ='人员人工-研发人员工资'!S10 -> 0 | T10: =IF($D10=0,0,ROUND(S10/$D10*$C10,2)) -> 0 | U10: ='人员人工-研发人员工资'!U10 -> 0 | V10: =IF($D10=0,0,ROUND(U10/$D10*$C10,2)) -> 0 | W10: ='人员人工-研发人员工资'!W10 -> 0 | X10: =IF($D10=0,0,ROUND(W10/$D10*$C10,2)) -> 0 | Y10: ='人员人工-研发人员工资'!Y10 -> 0 | Z10: =IF($D10=0,0,ROUND(Y10/$D10*$C10,2)) -> 0
A11: 6 | B11: ='人员人工-研发人员工资'!B11 -> 0 | D11: ='人员人工-研发人员工资'!D11 -> 0 | E11: =G11+I11+K11+M11+O11+Q11+S11+U11+W11+Y11 -> 0 | F11: =H11+J11+L11+N11+P11+R11+T11+V11+X11+Z11 -> 0 | G11: ='人员人工-研发人员工资'!G11 -> 0 | H11: =IF($D11=0,0,ROUND(G11/$D11*$C11,2)) -> 0 | I11: ='人员人工-研发人员工资'!I11 -> 0 | J11: =IF($D11=0,0,ROUND(I11/$D11*$C11,2)) -> 0 | K11: ='人员人工-研发人员工资'!K11 -> 0 | L11: =IF($D11=0,0,ROUND(K11/$D11*$C11,2)) -> 0 | M11: ='人员人工-研发人员工资'!M11 -> 0 | N11: =IF($D11=0,0,ROUND(M11/$D11*$C11,2)) -> 0 | O11: ='人员人工-研发人员工资'!O11 -> 0 | P11: =IF($D11=0,0,ROUND(O11/$D11*$C11,2)) -> 0 | Q11: ='人员人工-研发人员工资'!Q11 -> 0 | R11: =IF($D11=0,0,ROUND(Q11/$D11*$C11,2)) -> 0 | S11: ='人员人工-研发人员工资'!S11 -> 0 | T11: =IF($D11=0,0,ROUND(S11/$D11*$C11,2)) -> 0 | U11: ='人员人工-研发人员工资'!U11 -> 0 | V11: =IF($D11=0,0,ROUND(U11/$D11*$C11,2)) -> 0 | W11: ='人员人工-研发人员工资'!W11 -> 0 | X11: =IF($D11=0,0,ROUND(W11/$D11*$C11,2)) -> 0 | Y11: ='人员人工-研发人员工资'!Y11 -> 0 | Z11: =IF($D11=0,0,ROUND(Y11/$D11*$C11,2)) -> 0
A12: 7 | B12: ='人员人工-研发人员工资'!B12 -> 0 | D12: ='人员人工-研发人员工资'!D12 -> 0 | E12: =G12+I12+K12+M12+O12+Q12+S12+U12+W12+Y12 -> 0 | F12: =H12+J12+L12+N12+P12+R12+T12+V12+X12+Z12 -> 0 | G12: ='人员人工-研发人员工资'!G12 -> 0 | H12: =IF($D12=0,0,ROUND(G12/$D12*$C12,2)) -> 0 | I12: ='人员人工-研发人员工资'!I12 -> 0 | J12: =IF($D12=0,0,ROUND(I12/$D12*$C12,2)) -> 0 | K12: ='人员人工-研发人员工资'!K12 -> 0 | L12: =IF($D12=0,0,ROUND(K12/$D12*$C12,2)) -> 0 | M12: ='人员人工-研发人员工资'!M12 -> 0 | N12: =IF($D12=0,0,ROUND(M12/$D12*$C12,2)) -> 0 | O12: ='人员人工-研发人员工资'!O12 -> 0 | P12: =IF($D12=0,0,ROUND(O12/$D12*$C12,2)) -> 0 | Q12: ='人员人工-研发人员工资'!Q12 -> 0 | R12: =IF($D12=0,0,ROUND(Q12/$D12*$C12,2)) -> 0 | S12: ='人员人工-研发人员工资'!S12 -> 0 | T12: =IF($D12=0,0,ROUND(S12/$D12*$C12,2)) -> 0 | U12: ='人员人工-研发人员工资'!U12 -> 0 | V12: =IF($D12=0,0,ROUND(U12/$D12*$C12,2)) -> 0 | W12: ='人员人工-研发人员工资'!W12 -> 0 | X12: =IF($D12=0,0,ROUND(W12/$D12*$C12,2)) -> 0 | Y12: ='人员人工-研发人员工资'!Y12 -> 0 | Z12: =IF($D12=0,0,ROUND(Y12/$D12*$C12,2)) -> 0
A13: 8 | B13: ='人员人工-研发人员工资'!B13 -> 0 | D13: ='人员人工-研发人员工资'!D13 -> 0 | E13: =G13+I13+K13+M13+O13+Q13+S13+U13+W13+Y13 -> 0 | F13: =H13+J13+L13+N13+P13+R13+T13+V13+X13+Z13 -> 0 | G13: ='人员人工-研发人员工资'!G13 -> 0 | H13: =IF($D13=0,0,ROUND(G13/$D13*$C13,2)) -> 0 | I13: ='人员人工-研发人员工资'!I13 -> 0 | J13: =IF($D13=0,0,ROUND(I13/$D13*$C13,2)) -> 0 | K13: ='人员人工-研发人员工资'!K13 -> 0 | L13: =IF($D13=0,0,ROUND(K13/$D13*$C13,2)) -> 0 | M13: ='人员人工-研发人员工资'!M13 -> 0 | N13: =IF($D13=0,0,ROUND(M13/$D13*$C13,2)) -> 0 | O13: ='人员人工-研发人员工资'!O13 -> 0 | P13: =IF($D13=0,0,ROUND(O13/$D13*$C13,2)) -> 0 | Q13: ='人员人工-研发人员工资'!Q13 -> 0 | R13: =IF($D13=0,0,ROUND(Q13/$D13*$C13,2)) -> 0 | S13: ='人员人工-研发人员工资'!S13 -> 0 | T13: =IF($D13=0,0,ROUND(S13/$D13*$C13,2)) -> 0 | U13: ='人员人工-研发人员工资'!U13 -> 0 | V13: =IF($D13=0,0,ROUND(U13/$D13*$C13,2)) -> 0 | W13: ='人员人工-研发人员工资'!W13 -> 0 | X13: =IF($D13=0,0,ROUND(W13/$D13*$C13,2)) -> 0 | Y13: ='人员人工-研发人员工资'!Y13 -> 0 | Z13: =IF($D13=0,0,ROUND(Y13/$D13*$C13,2)) -> 0
A14: 9 | B14: ='人员人工-研发人员工资'!B14 -> 0 | D14: ='人员人工-研发人员工资'!D14 -> 0 | E14: =G14+I14+K14+M14+O14+Q14+S14+U14+W14+Y14 -> 0 | F14: =H14+J14+L14+N14+P14+R14+T14+V14+X14+Z14 -> 0 | G14: ='人员人工-研发人员工资'!G14 -> 0 | H14: =IF($D14=0,0,ROUND(G14/$D14*$C14,2)) -> 0 | I14: ='人员人工-研发人员工资'!I14 -> 0 | J14: =IF($D14=0,0,ROUND(I14/$D14*$C14,2)) -> 0 | K14: ='人员人工-研发人员工资'!K14 -> 0 | L14: =IF($D14=0,0,ROUND(K14/$D14*$C14,2)) -> 0 | M14: ='人员人工-研发人员工资'!M14 -> 0 | N14: =IF($D14=0,0,ROUND(M14/$D14*$C14,2)) -> 0 | O14: ='人员人工-研发人员工资'!O14 -> 0 | P14: =IF($D14=0,0,ROUND(O14/$D14*$C14,2)) -> 0 | Q14: ='人员人工-研发人员工资'!Q14 -> 0 | R14: =IF($D14=0,0,ROUND(Q14/$D14*$C14,2)) -> 0 | S14: ='人员人工-研发人员工资'!S14 -> 0 | T14: =IF($D14=0,0,ROUND(S14/$D14*$C14,2)) -> 0 | U14: ='人员人工-研发人员工资'!U14 -> 0 | V14: =IF($D14=0,0,ROUND(U14/$D14*$C14,2)) -> 0 | W14: ='人员人工-研发人员工资'!W14 -> 0 | X14: =IF($D14=0,0,ROUND(W14/$D14*$C14,2)) -> 0 | Y14: ='人员人工-研发人员工资'!Y14 -> 0 | Z14: =IF($D14=0,0,ROUND(Y14/$D14*$C14,2)) -> 0
A15: 10 | B15: ='人员人工-研发人员工资'!B15 -> 0 | D15: ='人员人工-研发人员工资'!D15 -> 0 | E15: =G15+I15+K15+M15+O15+Q15+S15+U15+W15+Y15 -> 0 | F15: =H15+J15+L15+N15+P15+R15+T15+V15+X15+Z15 -> 0 | G15: ='人员人工-研发人员工资'!G15 -> 0 | H15: =IF($D15=0,0,ROUND(G15/$D15*$C15,2)) -> 0 | I15: ='人员人工-研发人员工资'!I15 -> 0 | J15: =IF($D15=0,0,ROUND(I15/$D15*$C15,2)) -> 0 | K15: ='人员人工-研发人员工资'!K15 -> 0 | L15: =IF($D15=0,0,ROUND(K15/$D15*$C15,2)) -> 0 | M15: ='人员人工-研发人员工资'!M15 -> 0 | N15: =IF($D15=0,0,ROUND(M15/$D15*$C15,2)) -> 0 | O15: ='人员人工-研发人员工资'!O15 -> 0 | P15: =IF($D15=0,0,ROUND(O15/$D15*$C15,2)) -> 0 | Q15: ='人员人工-研发人员工资'!Q15 -> 0 | R15: =IF($D15=0,0,ROUND(Q15/$D15*$C15,2)) -> 0 | S15: ='人员人工-研发人员工资'!S15 -> 0 | T15: =IF($D15=0,0,ROUND(S15/$D15*$C15,2)) -> 0 | U15: ='人员人工-研发人员工资'!U15 -> 0 | V15: =IF($D15=0,0,ROUND(U15/$D15*$C15,2)) -> 0 | W15: ='人员人工-研发人员工资'!W15 -> 0 | X15: =IF($D15=0,0,ROUND(W15/$D15*$C15,2)) -> 0 | Y15: ='人员人工-研发人员工资'!Y15 -> 0 | Z15: =IF($D15=0,0,ROUND(Y15/$D15*$C15,2)) -> 0
A16: 11 | B16: ='人员人工-研发人员工资'!B16 -> 0 | D16: ='人员人工-研发人员工资'!D16 -> 0 | E16: =G16+I16+K16+M16+O16+Q16+S16+U16+W16+Y16 -> 0 | F16: =H16+J16+L16+N16+P16+R16+T16+V16+X16+Z16 -> 0 | G16: ='人员人工-研发人员工资'!G16 -> 0 | H16: =IF($D16=0,0,ROUND(G16/$D16*$C16,2)) -> 0 | I16: ='人员人工-研发人员工资'!I16 -> 0 | J16: =IF($D16=0,0,ROUND(I16/$D16*$C16,2)) -> 0 | K16: ='人员人工-研发人员工资'!K16 -> 0 | L16: =IF($D16=0,0,ROUND(K16/$D16*$C16,2)) -> 0 | M16: ='人员人工-研发人员工资'!M16 -> 0 | N16: =IF($D16=0,0,ROUND(M16/$D16*$C16,2)) -> 0 | O16: ='人员人工-研发人员工资'!O16 -> 0 | P16: =IF($D16=0,0,ROUND(O16/$D16*$C16,2)) -> 0 | Q16: ='人员人工-研发人员工资'!Q16 -> 0 | R16: =IF($D16=0,0,ROUND(Q16/$D16*$C16,2)) -> 0 | S16: ='人员人工-研发人员工资'!S16 -> 0 | T16: =IF($D16=0,0,ROUND(S16/$D16*$C16,2)) -> 0 | U16: ='人员人工-研发人员工资'!U16 -> 0 | V16: =IF($D16=0,0,ROUND(U16/$D16*$C16,2)) -> 0 | W16: ='人员人工-研发人员工资'!W16 -> 0 | X16: =IF($D16=0,0,ROUND(W16/$D16*$C16,2)) -> 0 | Y16: ='人员人工-研发人员工资'!Y16 -> 0 | Z16: =IF($D16=0,0,ROUND(Y16/$D16*$C16,2)) -> 0
A17: 12 | B17: ='人员人工-研发人员工资'!B17 -> 0 | D17: ='人员人工-研发人员工资'!D17 -> 0 | E17: =G17+I17+K17+M17+O17+Q17+S17+U17+W17+Y17 -> 0 | F17: =H17+J17+L17+N17+P17+R17+T17+V17+X17+Z17 -> 0 | G17: ='人员人工-研发人员工资'!G17 -> 0 | H17: =IF($D17=0,0,ROUND(G17/$D17*$C17,2)) -> 0 | I17: ='人员人工-研发人员工资'!I17 -> 0 | J17: =IF($D17=0,0,ROUND(I17/$D17*$C17,2)) -> 0 | K17: ='人员人工-研发人员工资'!K17 -> 0 | L17: =IF($D17=0,0,ROUND(K17/$D17*$C17,2)) -> 0 | M17: ='人员人工-研发人员工资'!M17 -> 0 | N17: =IF($D17=0,0,ROUND(M17/$D17*$C17,2)) -> 0 | O17: ='人员人工-研发人员工资'!O17 -> 0 | P17: =IF($D17=0,0,ROUND(O17/$D17*$C17,2)) -> 0 | Q17: ='人员人工-研发人员工资'!Q17 -> 0 | R17: =IF($D17=0,0,ROUND(Q17/$D17*$C17,2)) -> 0 | S17: ='人员人工-研发人员工资'!S17 -> 0 | T17: =IF($D17=0,0,ROUND(S17/$D17*$C17,2)) -> 0 | U17: ='人员人工-研发人员工资'!U17 -> 0 | V17: =IF($D17=0,0,ROUND(U17/$D17*$C17,2)) -> 0 | W17: ='人员人工-研发人员工资'!W17 -> 0 | X17: =IF($D17=0,0,ROUND(W17/$D17*$C17,2)) -> 0 | Y17: ='人员人工-研发人员工资'!Y17 -> 0 | Z17: =IF($D17=0,0,ROUND(Y17/$D17*$C17,2)) -> 0
... A23: 18 | B23: ='人员人工-研发人员工资'!B23 -> 0 | D23: ='人员人工-研发人员工资'!D23 -> 0 | E23: =G23+I23+K23+M23+O23+Q23+S23+U23+W23+Y23 -> 0 | F23: =H23+J23+L23+N23+P23+R23+T23+V23+X23+Z23 -> 0 | G23: ='人员人工-研发人员工资'!G23 -> 0 | H23: =IF($D23=0,0,ROUND(G23/$D23*$C23,2)) -> 0 | I23: ='人员人工-研发人员工资'!I23 -> 0 | J23: =IF($D23=0,0,ROUND(I23/$D23*$C23,2)) -> 0 | K23: ='人员人工-研发人员工资'!K23 -> 0 | L23: =IF($D23=0,0,ROUND(K23/$D23*$C23,2)) -> 0 | M23: ='人员人工-研发人员工资'!M23 -> 0 | N23: =IF($D23=0,0,ROUND(M23/$D23*$C23,2)) -> 0 | O23: ='人员人工-研发人员工资'!O23 -> 0 | P23: =IF($D23=0,0,ROUND(O23/$D23*$C23,2)) -> 0 | Q23: ='人员人工-研发人员工资'!Q23 -> 0 | R23: =IF($D23=0,0,ROUND(Q23/$D23*$C23,2)) -> 0 | S23: ='人员人工-研发人员工资'!S23 -> 0 | T23: =IF($D23=0,0,ROUND(S23/$D23*$C23,2)) -> 0 | U23: ='人员人工-研发人员工资'!U23 -> 0 | V23: =IF($D23=0,0,ROUND(U23/$D23*$C23,2)) -> 0 | W23: ='人员人工-研发人员工资'!W23 -> 0 | X23: =IF($D23=0,0,ROUND(W23/$D23*$C23,2)) -> 0 | Y23: ='人员人工-研发人员工资'!Y23 -> 0 | Z23: =IF($D23=0,0,ROUND(Y23/$D23*$C23,2)) -> 0
A24: 19 | B24: ='人员人工-研发人员工资'!B25 -> 0 | D24: ='人员人工-研发人员工资'!D25 -> 0 | E24: =G25+I25+K25+M25+O25+Q25+S25+U25+W25+Y25 -> 0 | F24: =H25+J25+L25+N25+P25+R25+T25+V25+X25+Z25 -> 0 | G24: ='人员人工-研发人员工资'!G25 -> 0 | H24: =IF($D25=0,0,ROUND(G25/$D25*$C25,2)) -> 0 | I24: ='人员人工-研发人员工资'!I25 -> 0 | J24: =IF($D25=0,0,ROUND(I25/$D25*$C25,2)) -> 0 | K24: ='人员人工-研发人员工资'!K25 -> 0 | L24: =IF($D25=0,0,ROUND(K25/$D25*$C25,2)) -> 0 | M24: ='人员人工-研发人员工资'!M25 -> 0 | N24: =IF($D25=0,0,ROUND(M25/$D25*$C25,2)) -> 0 | O24: ='人员人工-研发人员工资'!O25 -> 0 | P24: =IF($D25=0,0,ROUND(O25/$D25*$C25,2)) -> 0 | Q24: ='人员人工-研发人员工资'!Q25 -> 0 | R24: =IF($D25=0,0,ROUND(Q25/$D25*$C25,2)) -> 0 | S24: ='人员人工-研发人员工资'!S25 -> 0 | T24: =IF($D25=0,0,ROUND(S25/$D25*$C25,2)) -> 0 | U24: ='人员人工-研发人员工资'!U25 -> 0 | V24: =IF($D25=0,0,ROUND(U25/$D25*$C25,2)) -> 0 | W24: ='人员人工-研发人员工资'!W25 -> 0 | X24: =IF($D25=0,0,ROUND(W25/$D25*$C25,2)) -> 0 | Y24: ='人员人工-研发人员工资'!Y25 -> 0 | Z24: =IF($D25=0,0,ROUND(Y25/$D25*$C25,2)) -> 0
A25: 20 | B25: ='人员人工-研发人员工资'!B25 -> 0 | D25: ='人员人工-研发人员工资'!D25 -> 0 | E25: =G25+I25+K25+M25+O25+Q25+S25+U25+W25+Y25 -> 0 | F25: =H25+J25+L25+N25+P25+R25+T25+V25+X25+Z25 -> 0 | G25: ='人员人工-研发人员工资'!G25 -> 0 | H25: =IF($D25=0,0,ROUND(G25/$D25*$C25,2)) -> 0 | I25: ='人员人工-研发人员工资'!I25 -> 0 | J25: =IF($D25=0,0,ROUND(I25/$D25*$C25,2)) -> 0 | K25: ='人员人工-研发人员工资'!K25 -> 0 | L25: =IF($D25=0,0,ROUND(K25/$D25*$C25,2)) -> 0 | M25: ='人员人工-研发人员工资'!M25 -> 0 | N25: =IF($D25=0,0,ROUND(M25/$D25*$C25,2)) -> 0 | O25: ='人员人工-研发人员工资'!O25 -> 0 | P25: =IF($D25=0,0,ROUND(O25/$D25*$C25,2)) -> 0 | Q25: ='人员人工-研发人员工资'!Q25 -> 0 | R25: =IF($D25=0,0,ROUND(Q25/$D25*$C25,2)) -> 0 | S25: ='人员人工-研发人员工资'!S25 -> 0 | T25: =IF($D25=0,0,ROUND(S25/$D25*$C25,2)) -> 0 | U25: ='人员人工-研发人员工资'!U25 -> 0 | V25: =IF($D25=0,0,ROUND(U25/$D25*$C25,2)) -> 0 | W25: ='人员人工-研发人员工资'!W25 -> 0 | X25: =IF($D25=0,0,ROUND(W25/$D25*$C25,2)) -> 0 | Y25: ='人员人工-研发人员工资'!Y25 -> 0 | Z25: =IF($D25=0,0,ROUND(Y25/$D25*$C25,2)) -> 0
A26: 21 | B26: ='人员人工-研发人员工资'!B26 -> 0 | D26: ='人员人工-研发人员工资'!D26 -> 0 | E26: =G26+I26+K26+M26+O26+Q26+S26+U26+W26+Y26 -> 0 | F26: =H26+J26+L26+N26+P26+R26+T26+V26+X26+Z26 -> 0 | G26: ='人员人工-研发人员工资'!G26 -> 0 | H26: =IF($D26=0,0,ROUND(G26/$D26*$C26,2)) -> 0 | I26: ='人员人工-研发人员工资'!I26 -> 0 | J26: =IF($D26=0,0,ROUND(I26/$D26*$C26,2)) -> 0 | K26: ='人员人工-研发人员工资'!K26 -> 0 | L26: =IF($D26=0,0,ROUND(K26/$D26*$C26,2)) -> 0 | M26: ='人员人工-研发人员工资'!M26 -> 0 | N26: =IF($D26=0,0,ROUND(M26/$D26*$C26,2)) -> 0 | O26: ='人员人工-研发人员工资'!O26 -> 0 | P26: =IF($D26=0,0,ROUND(O26/$D26*$C26,2)) -> 0 | Q26: ='人员人工-研发人员工资'!Q26 -> 0 | R26: =IF($D26=0,0,ROUND(Q26/$D26*$C26,2)) -> 0 | S26: ='人员人工-研发人员工资'!S26 -> 0 | T26: =IF($D26=0,0,ROUND(S26/$D26*$C26,2)) -> 0 | U26: ='人员人工-研发人员工资'!U26 -> 0 | V26: =IF($D26=0,0,ROUND(U26/$D26*$C26,2)) -> 0 | W26: ='人员人工-研发人员工资'!W26 -> 0 | X26: =IF($D26=0,0,ROUND(W26/$D26*$C26,2)) -> 0 | Y26: ='人员人工-研发人员工资'!Y26 -> 0 | Z26: =IF($D26=0,0,ROUND(Y26/$D26*$C26,2)) -> 0
A27: 22 | B27: ='人员人工-研发人员工资'!B27 -> 0 | D27: ='人员人工-研发人员工资'!D27 -> 0 | E27: =G27+I27+K27+M27+O27+Q27+S27+U27+W27+Y27 -> 0 | F27: =H27+J27+L27+N27+P27+R27+T27+V27+X27+Z27 -> 0 | G27: ='人员人工-研发人员工资'!G27 -> 0 | H27: =IF($D27=0,0,ROUND(G27/$D27*$C27,2)) -> 0 | I27: ='人员人工-研发人员工资'!I27 -> 0 | J27: =IF($D27=0,0,ROUND(I27/$D27*$C27,2)) -> 0 | K27: ='人员人工-研发人员工资'!K27 -> 0 | L27: =IF($D27=0,0,ROUND(K27/$D27*$C27,2)) -> 0 | M27: ='人员人工-研发人员工资'!M27 -> 0 | N27: =IF($D27=0,0,ROUND(M27/$D27*$C27,2)) -> 0 | O27: ='人员人工-研发人员工资'!O27 -> 0 | P27: =IF($D27=0,0,ROUND(O27/$D27*$C27,2)) -> 0 | Q27: ='人员人工-研发人员工资'!Q27 -> 0 | R27: =IF($D27=0,0,ROUND(Q27/$D27*$C27,2)) -> 0 | S27: ='人员人工-研发人员工资'!S27 -> 0 | T27: =IF($D27=0,0,ROUND(S27/$D27*$C27,2)) -> 0 | U27: ='人员人工-研发人员工资'!U27 -> 0 | V27: =IF($D27=0,0,ROUND(U27/$D27*$C27,2)) -> 0 | W27: ='人员人工-研发人员工资'!W27 -> 0 | X27: =IF($D27=0,0,ROUND(W27/$D27*$C27,2)) -> 0 | Y27: ='人员人工-研发人员工资'!Y27 -> 0 | Z27: =IF($D27=0,0,ROUND(Y27/$D27*$C27,2)) -> 0
A28: 23 | B28: ='人员人工-研发人员工资'!B28 -> 0 | D28: ='人员人工-研发人员工资'!D28 -> 0 | E28: =G28+I28+K28+M28+O28+Q28+S28+U28+W28+Y28 -> 0 | F28: =H28+J28+L28+N28+P28+R28+T28+V28+X28+Z28 -> 0 | G28: ='人员人工-研发人员工资'!G28 -> 0 | H28: =IF($D28=0,0,ROUND(G28/$D28*$C28,2)) -> 0 | I28: ='人员人工-研发人员工资'!I28 -> 0 | J28: =IF($D28=0,0,ROUND(I28/$D28*$C28,2)) -> 0 | K28: ='人员人工-研发人员工资'!K28 -> 0 | L28: =IF($D28=0,0,ROUND(K28/$D28*$C28,2)) -> 0 | M28: ='人员人工-研发人员工资'!M28 -> 0 | N28: =IF($D28=0,0,ROUND(M28/$D28*$C28,2)) -> 0 | O28: ='人员人工-研发人员工资'!O28 -> 0 | P28: =IF($D28=0,0,ROUND(O28/$D28*$C28,2)) -> 0 | Q28: ='人员人工-研发人员工资'!Q28 -> 0 | R28: =IF($D28=0,0,ROUND(Q28/$D28*$C28,2)) -> 0 | S28: ='人员人工-研发人员工资'!S28 -> 0 | T28: =IF($D28=0,0,ROUND(S28/$D28*$C28,2)) -> 0 | U28: ='人员人工-研发人员工资'!U28 -> 0 | V28: =IF($D28=0,0,ROUND(U28/$D28*$C28,2)) -> 0 | W28: ='人员人工-研发人员工资'!W28 -> 0 | X28: =IF($D28=0,0,ROUND(W28/$D28*$C28,2)) -> 0 | Y28: ='人员人工-研发人员工资'!Y28 -> 0 | Z28: =IF($D28=0,0,ROUND(Y28/$D28*$C28,2)) -> 0
A29: 25 | B29: ='人员人工-研发人员工资'!B29 -> 0 | D29: ='人员人工-研发人员工资'!D29 -> 0 | E29: =G29+I29+K29+M29+O29+Q29+S29+U29+W29+Y29 -> 0 | F29: =H29+J29+L29+N29+P29+R29+T29+V29+X29+Z29 -> 0 | G29: ='人员人工-研发人员工资'!G29 -> 0 | H29: =IF($D29=0,0,ROUND(G29/$D29*$C29,2)) -> 0 | I29: ='人员人工-研发人员工资'!I29 -> 0 | J29: =IF($D29=0,0,ROUND(I29/$D29*$C29,2)) -> 0 | K29: ='人员人工-研发人员工资'!K29 -> 0 | L29: =IF($D29=0,0,ROUND(K29/$D29*$C29,2)) -> 0 | M29: ='人员人工-研发人员工资'!M29 -> 0 | N29: =IF($D29=0,0,ROUND(M29/$D29*$C29,2)) -> 0 | O29: ='人员人工-研发人员工资'!O29 -> 0 | P29: =IF($D29=0,0,ROUND(O29/$D29*$C29,2)) -> 0 | Q29: ='人员人工-研发人员工资'!Q29 -> 0 | R29: =IF($D29=0,0,ROUND(Q29/$D29*$C29,2)) -> 0 | S29: ='人员人工-研发人员工资'!S29 -> 0 | T29: =IF($D29=0,0,ROUND(S29/$D29*$C29,2)) -> 0 | U29: ='人员人工-研发人员工资'!U29 -> 0 | V29: =IF($D29=0,0,ROUND(U29/$D29*$C29,2)) -> 0 | W29: ='人员人工-研发人员工资'!W29 -> 0 | X29: =IF($D29=0,0,ROUND(W29/$D29*$C29,2)) -> 0 | Y29: ='人员人工-研发人员工资'!Y29 -> 0 | Z29: =IF($D29=0,0,ROUND(Y29/$D29*$C29,2)) -> 0
A30: 25 | B30: ='人员人工-研发人员工资'!B30 -> 0 | D30: ='人员人工-研发人员工资'!D30 -> 0 | E30: =G30+I30+K30+M30+O30+Q30+S30+U30+W30+Y30 -> 0 | F30: =H30+J30+L30+N30+P30+R30+T30+V30+X30+Z30 -> 0 | G30: ='人员人工-研发人员工资'!G30 -> 0 | H30: =IF($D30=0,0,ROUND(G30/$D30*$C30,2)) -> 0 | I30: ='人员人工-研发人员工资'!I30 -> 0 | J30: =IF($D30=0,0,ROUND(I30/$D30*$C30,2)) -> 0 | K30: ='人员人工-研发人员工资'!K30 -> 0 | L30: =IF($D30=0,0,ROUND(K30/$D30*$C30,2)) -> 0 | M30: ='人员人工-研发人员工资'!M30 -> 0 | N30: =IF($D30=0,0,ROUND(M30/$D30*$C30,2)) -> 0 | O30: ='人员人工-研发人员工资'!O30 -> 0 | P30: =IF($D30=0,0,ROUND(O30/$D30*$C30,2)) -> 0 | Q30: ='人员人工-研发人员工资'!Q30 -> 0 | R30: =IF($D30=0,0,ROUND(Q30/$D30*$C30,2)) -> 0 | S30: ='人员人工-研发人员工资'!S30 -> 0 | T30: =IF($D30=0,0,ROUND(S30/$D30*$C30,2)) -> 0 | U30: ='人员人工-研发人员工资'!U30 -> 0 | V30: =IF($D30=0,0,ROUND(U30/$D30*$C30,2)) -> 0 | W30: ='人员人工-研发人员工资'!W30 -> 0 | X30: =IF($D30=0,0,ROUND(W30/$D30*$C30,2)) -> 0 | Y30: ='人员人工-研发人员工资'!Y30 -> 0 | Z30: =IF($D30=0,0,ROUND(Y30/$D30*$C30,2)) -> 0
A31: 26 | B31: ='人员人工-研发人员工资'!B31 -> 0 | D31: ='人员人工-研发人员工资'!D31 -> 0 | E31: =G31+I31+K31+M31+O31+Q31+S31+U31+W31+Y31 -> 0 | F31: =H31+J31+L31+N31+P31+R31+T31+V31+X31+Z31 -> 0 | G31: ='人员人工-研发人员工资'!G31 -> 0 | H31: =IF($D31=0,0,ROUND(G31/$D31*$C31,2)) -> 0 | I31: ='人员人工-研发人员工资'!I31 -> 0 | J31: =IF($D31=0,0,ROUND(I31/$D31*$C31,2)) -> 0 | K31: ='人员人工-研发人员工资'!K31 -> 0 | L31: =IF($D31=0,0,ROUND(K31/$D31*$C31,2)) -> 0 | M31: ='人员人工-研发人员工资'!M31 -> 0 | N31: =IF($D31=0,0,ROUND(M31/$D31*$C31,2)) -> 0 | O31: ='人员人工-研发人员工资'!O31 -> 0 | P31: =IF($D31=0,0,ROUND(O31/$D31*$C31,2)) -> 0 | Q31: ='人员人工-研发人员工资'!Q31 -> 0 | R31: =IF($D31=0,0,ROUND(Q31/$D31*$C31,2)) -> 0 | S31: ='人员人工-研发人员工资'!S31 -> 0 | T31: =IF($D31=0,0,ROUND(S31/$D31*$C31,2)) -> 0 | U31: ='人员人工-研发人员工资'!U31 -> 0 | V31: =IF($D31=0,0,ROUND(U31/$D31*$C31,2)) -> 0 | W31: ='人员人工-研发人员工资'!W31 -> 0 | X31: =IF($D31=0,0,ROUND(W31/$D31*$C31,2)) -> 0 | Y31: ='人员人工-研发人员工资'!Y31 -> 0 | Z31: =IF($D31=0,0,ROUND(Y31/$D31*$C31,2)) -> 0
A32: 27 | B32: ='人员人工-研发人员工资'!B32 -> 0 | D32: ='人员人工-研发人员工资'!D32 -> 0 | E32: =G32+I32+K32+M32+O32+Q32+S32+U32+W32+Y32 -> 0 | F32: =H32+J32+L32+N32+P32+R32+T32+V32+X32+Z32 -> 0 | G32: ='人员人工-研发人员工资'!G32 -> 0 | H32: =IF($D32=0,0,ROUND(G32/$D32*$C32,2)) -> 0 | I32: ='人员人工-研发人员工资'!I32 -> 0 | J32: =IF($D32=0,0,ROUND(I32/$D32*$C32,2)) -> 0 | K32: ='人员人工-研发人员工资'!K32 -> 0 | L32: =IF($D32=0,0,ROUND(K32/$D32*$C32,2)) -> 0 | M32: ='人员人工-研发人员工资'!M32 -> 0 | N32: =IF($D32=0,0,ROUND(M32/$D32*$C32,2)) -> 0 | O32: ='人员人工-研发人员工资'!O32 -> 0 | P32: =IF($D32=0,0,ROUND(O32/$D32*$C32,2)) -> 0 | Q32: ='人员人工-研发人员工资'!Q32 -> 0 | R32: =IF($D32=0,0,ROUND(Q32/$D32*$C32,2)) -> 0 | S32: ='人员人工-研发人员工资'!S32 -> 0 | T32: =IF($D32=0,0,ROUND(S32/$D32*$C32,2)) -> 0 | U32: ='人员人工-研发人员工资'!U32 -> 0 | V32: =IF($D32=0,0,ROUND(U32/$D32*$C32,2)) -> 0 | W32: ='人员人工-研发人员工资'!W32 -> 0 | X32: =IF($D32=0,0,ROUND(W32/$D32*$C32,2)) -> 0 | Y32: ='人员人工-研发人员工资'!Y32 -> 0 | Z32: =IF($D32=0,0,ROUND(Y32/$D32*$C32,2)) -> 0
A33: 28 | B33: ='人员人工-研发人员工资'!B33 -> 0 | D33: ='人员人工-研发人员工资'!D33 -> 0 | E33: =G33+I33+K33+M33+O33+Q33+S33+U33+W33+Y33 -> 0 | F33: =H33+J33+L33+N33+P33+R33+T33+V33+X33+Z33 -> 0 | G33: ='人员人工-研发人员工资'!G33 -> 0 | H33: =IF($D33=0,0,ROUND(G33/$D33*$C33,2)) -> 0 | I33: ='人员人工-研发人员工资'!I33 -> 0 | J33: =IF($D33=0,0,ROUND(I33/$D33*$C33,2)) -> 0 | K33: ='人员人工-研发人员工资'!K33 -> 0 | L33: =IF($D33=0,0,ROUND(K33/$D33*$C33,2)) -> 0 | M33: ='人员人工-研发人员工资'!M33 -> 0 | N33: =IF($D33=0,0,ROUND(M33/$D33*$C33,2)) -> 0 | O33: ='人员人工-研发人员工资'!O33 -> 0 | P33: =IF($D33=0,0,ROUND(O33/$D33*$C33,2)) -> 0 | Q33: ='人员人工-研发人员工资'!Q33 -> 0 | R33: =IF($D33=0,0,ROUND(Q33/$D33*$C33,2)) -> 0 | S33: ='人员人工-研发人员工资'!S33 -> 0 | T33: =IF($D33=0,0,ROUND(S33/$D33*$C33,2)) -> 0 | U33: ='人员人工-研发人员工资'!U33 -> 0 | V33: =IF($D33=0,0,ROUND(U33/$D33*$C33,2)) -> 0 | W33: ='人员人工-研发人员工资'!W33 -> 0 | X33: =IF($D33=0,0,ROUND(W33/$D33*$C33,2)) -> 0 | Y33: ='人员人工-研发人员工资'!Y33 -> 0 | Z33: =IF($D33=0,0,ROUND(Y33/$D33*$C33,2)) -> 0
A34: 29 | B34: ='人员人工-研发人员工资'!B34 -> 0 | D34: ='人员人工-研发人员工资'!D34 -> 0 | E34: =G34+I34+K34+M34+O34+Q34+S34+U34+W34+Y34 -> 0 | F34: =H34+J34+L34+N34+P34+R34+T34+V34+X34+Z34 -> 0 | G34: ='人员人工-研发人员工资'!G34 -> 0 | H34: =IF($D34=0,0,ROUND(G34/$D34*$C34,2)) -> 0 | I34: ='人员人工-研发人员工资'!I34 -> 0 | J34: =IF($D34=0,0,ROUND(I34/$D34*$C34,2)) -> 0 | K34: ='人员人工-研发人员工资'!K34 -> 0 | L34: =IF($D34=0,0,ROUND(K34/$D34*$C34,2)) -> 0 | M34: ='人员人工-研发人员工资'!M34 -> 0 | N34: =IF($D34=0,0,ROUND(M34/$D34*$C34,2)) -> 0 | O34: ='人员人工-研发人员工资'!O34 -> 0 | P34: =IF($D34=0,0,ROUND(O34/$D34*$C34,2)) -> 0 | Q34: ='人员人工-研发人员工资'!Q34 -> 0 | R34: =IF($D34=0,0,ROUND(Q34/$D34*$C34,2)) -> 0 | S34: ='人员人工-研发人员工资'!S34 -> 0 | T34: =IF($D34=0,0,ROUND(S34/$D34*$C34,2)) -> 0 | U34: ='人员人工-研发人员工资'!U34 -> 0 | V34: =IF($D34=0,0,ROUND(U34/$D34*$C34,2)) -> 0 | W34: ='人员人工-研发人员工资'!W34 -> 0 | X34: =IF($D34=0,0,ROUND(W34/$D34*$C34,2)) -> 0 | Y34: ='人员人工-研发人员工资'!Y34 -> 0 | Z34: =IF($D34=0,0,ROUND(Y34/$D34*$C34,2)) -> 0
A35: 30 | B35: ='人员人工-研发人员工资'!B35 -> 0 | D35: ='人员人工-研发人员工资'!D35 -> 0 | E35: =G35+I35+K35+M35+O35+Q35+S35+U35+W35+Y35 -> 0 | F35: =H35+J35+L35+N35+P35+R35+T35+V35+X35+Z35 -> 0 | G35: ='人员人工-研发人员工资'!G35 -> 0 | H35: =IF($D35=0,0,ROUND(G35/$D35*$C35,2)) -> 0 | I35: ='人员人工-研发人员工资'!I35 -> 0 | J35: =IF($D35=0,0,ROUND(I35/$D35*$C35,2)) -> 0 | K35: ='人员人工-研发人员工资'!K35 -> 0 | L35: =IF($D35=0,0,ROUND(K35/$D35*$C35,2)) -> 0 | M35: ='人员人工-研发人员工资'!M35 -> 0 | N35: =IF($D35=0,0,ROUND(M35/$D35*$C35,2)) -> 0 | O35: ='人员人工-研发人员工资'!O35 -> 0 | P35: =IF($D35=0,0,ROUND(O35/$D35*$C35,2)) -> 0 | Q35: ='人员人工-研发人员工资'!Q35 -> 0 | R35: =IF($D35=0,0,ROUND(Q35/$D35*$C35,2)) -> 0 | S35: ='人员人工-研发人员工资'!S35 -> 0 | T35: =IF($D35=0,0,ROUND(S35/$D35*$C35,2)) -> 0 | U35: ='人员人工-研发人员工资'!U35 -> 0 | V35: =IF($D35=0,0,ROUND(U35/$D35*$C35,2)) -> 0 | W35: ='人员人工-研发人员工资'!W35 -> 0 | X35: =IF($D35=0,0,ROUND(W35/$D35*$C35,2)) -> 0 | Y35: ='人员人工-研发人员工资'!Y35 -> 0 | Z35: =IF($D35=0,0,ROUND(Y35/$D35*$C35,2)) -> 0
A36: 合计 | C36: =SUM(C6:C35) -> 0 | D36: =SUM(D6:D35) -> 0 | E36: =SUM(E6:E35) -> 0 | F36: =SUM(F6:F35) -> 0 | G36: =SUM(G6:G35) -> 0 | H36: =SUM(H6:H35) -> 0 | I36: =SUM(I6:I35) -> 0 | J36: =SUM(J6:J35) -> 0 | ... Z36: =SUM(Z6:Z35) -> 0
B38: 2025年2月份研发人员社保项目分摊表
A40: 序号 | B40: 姓名 | C40: 月社保 | D40: 出勤天数 | E40: 研发天数合计 | F40: 研发社保合计 | G40: =立项!$A$3 -> RD01 | I40: =立项!$A$4 -> RD02 | K40: =立项!$A$5 -> RD03 | M40: =立项!$A$6 -> RD04 | O40: =立项!$A$7 -> RD05 | Q40: =立项!$A$8 -> RD06 | S40: =立项!$A$9 -> RD07 | U40: =立项!$A$10 -> RD08 | W40: =立项!$A$11 -> RD09 | Y40: =立项!$A$12 -> RD10
G41: =立项!C3 -> 0 | I41: =立项!C4 -> 0 | K41: =立项!C5 -> 0 | M41: =立项!C6 -> 0 | O41: =立项!C7 -> 0 | Q41: =立项!C8 -> 0 | S41: =立项!C9 -> 0 | U41: =立项!C10 -> 0 | W41: =立项!C11 -> 0 | Y41: =立项!C12 -> 0
G42: 研发天数 | H42: 研发社保 | I42: 研发天数 | J42: 研发社保 | K42: 研发天数 | L42: 研发社保 | M42: 研发天数 | N42: 研发社保 | O42: 研发天数 | P42: 研发社保 | Q42: 研发天数 | R42: 研发社保 | S42: 研发天数 | T42: 研发社保 | U42: 研发天数 | V42: 研发社保 | W42: 研发天数 | X42: 研发社保 | Y42: 研发天数 | Z42: 研发社保
A43: 1 | B43: ='人员人工-研发人员工资'!B43 -> 0 | D43: ='人员人工-研发人员工资'!D43 -> 0 | E43: =G43+I43+K43+M43+O43+Q43+S43+U43+W43+Y43 -> 0 | F43: =H43+J43+L43+N43+P43+R43+T43+V43+X43+Z43 -> 0 | G43: ='人员人工-研发人员工资'!G43 -> 0 | H43: =IF($D43=0,0,ROUND(G43/$D43*$C43,2)) -> 0 | I43: ='人员人工-研发人员工资'!I43 -> 0 | J43: =IF($D43=0,0,ROUND(I43/$D43*$C43,2)) -> 0 | K43: ='人员人工-研发人员工资'!K43 -> 0 | L43: =IF($D43=0,0,ROUND(K43/$D43*$C43,2)) -> 0 | M43: ='人员人工-研发人员工资'!M43 -> 0 | N43: =IF($D43=0,0,ROUND(M43/$D43*$C43,2)) -> 0 | O43: ='人员人工-研发人员工资'!O43 -> 0 | P43: =IF($D43=0,0,ROUND(O43/$D43*$C43,2)) -> 0 | Q43: ='人员人工-研发人员工资'!Q43 -> 0 | R43: =IF($D43=0,0,ROUND(Q43/$D43*$C43,2)) -> 0 | S43: ='人员人工-研发人员工资'!S43 -> 0 | T43: =IF($D43=0,0,ROUND(S43/$D43*$C43,2)) -> 0 | U43: ='人员人工-研发人员工资'!U43 -> 0 | V43: =IF($D43=0,0,ROUND(U43/$D43*$C43,2)) -> 0 | W43: ='人员人工-研发人员工资'!W43 -> 0 | X43: =IF($D43=0,0,ROUND(W43/$D43*$C43,2)) -> 0 | Y43: ='人员人工-研发人员工资'!Y43 -> 0 | Z43: =IF($D43=0,0,ROUND(Y43/$D43*$C43,2)) -> 0
A44: 2 | B44: ='人员人工-研发人员工资'!B44 -> 0 | D44: ='人员人工-研发人员工资'!D44 -> 0 | E44: =G44+I44+K44+M44+O44+Q44+S44+U44+W44+Y44 -> 0 | F44: =H44+J44+L44+N44+P44+R44+T44+V44+X44+Z44 -> 0 | G44: ='人员人工-研发人员工资'!G44 -> 0 | H44: =IF($D44=0,0,ROUND(G44/$D44*$C44,2)) -> 0 | I44: ='人员人工-研发人员工资'!I44 -> 0 | J44: =IF($D44=0,0,ROUND(I44/$D44*$C44,2)) -> 0 | K44: ='人员人工-研发人员工资'!K44 -> 0 | L44: =IF($D44=0,0,ROUND(K44/$D44*$C44,2)) -> 0 | M44: ='人员人工-研发人员工资'!M44 -> 0 | N44: =IF($D44=0,0,ROUND(M44/$D44*$C44,2)) -> 0 | O44: ='人员人工-研发人员工资'!O44 -> 0 | P44: =IF($D44=0,0,ROUND(O44/$D44*$C44,2)) -> 0 | Q44: ='人员人工-研发人员工资'!Q44 -> 0 | R44: =IF($D44=0,0,ROUND(Q44/$D44*$C44,2)) -> 0 | S44: ='人员人工-研发人员工资'!S44 -> 0 | T44: =IF($D44=0,0,ROUND(S44/$D44*$C44,2)) -> 0 | U44: ='人员人工-研发人员工资'!U44 -> 0 | V44: =IF($D44=0,0,ROUND(U44/$D44*$C44,2)) -> 0 | W44: ='人员人工-研发人员工资'!W44 -> 0 | X44: =IF($D44=0,0,ROUND(W44/$D44*$C44,2)) -> 0 | Y44: ='人员人工-研发人员工资'!Y44 -> 0 | Z44: =IF($D44=0,0,ROUND(Y44/$D44*$C44,2)) -> 0
A45: 3 | B45: ='人员人工-研发人员工资'!B45 -> 0 | D45: ='人员人工-研发人员工资'!D45 -> 0 | E45: =G45+I45+K45+M45+O45+Q45+S45+U45+W45+Y45 -> 0 | F45: =H45+J45+L45+N45+P45+R45+T45+V45+X45+Z45 -> 0 | G45: ='人员人工-研发人员工资'!G45 -> 0 | H45: =IF($D45=0,0,ROUND(G45/$D45*$C45,2)) -> 0 | I45: ='人员人工-研发人员工资'!I45 -> 0 | J45: =IF($D45=0,0,ROUND(I45/$D45*$C45,2)) -> 0 | K45: ='人员人工-研发人员工资'!K45 -> 0 | L45: =IF($D45=0,0,ROUND(K45/$D45*$C45,2)) -> 0 | M45: ='人员人工-研发人员工资'!M45 -> 0 | N45: =IF($D45=0,0,ROUND(M45/$D45*$C45,2)) -> 0 | O45: ='人员人工-研发人员工资'!O45 -> 0 | P45: =IF($D45=0,0,ROUND(O45/$D45*$C45,2)) -> 0 | Q45: ='人员人工-研发人员工资'!Q45 -> 0 | R45: =IF($D45=0,0,ROUND(Q45/$D45*$C45,2)) -> 0 | S45: ='人员人工-研发人员工资'!S45 -> 0 | T45: =IF($D45=0,0,ROUND(S45/$D45*$C45,2)) -> 0 | U45: ='人员人工-研发人员工资'!U45 -> 0 | V45: =IF($D45=0,0,ROUND(U45/$D45*$C45,2)) -> 0 | W45: ='人员人工-研发人员工资'!W45 -> 0 | X45: =IF($D45=0,0,ROUND(W45/$D45*$C45,2)) -> 0 | Y45: ='人员人工-研发人员工资'!Y45 -> 0 | Z45: =IF($D45=0,0,ROUND(Y45/$D45*$C45,2)) -> 0
A46: 4 | B46: ='人员人工-研发人员工资'!B46 -> 0 | D46: ='人员人工-研发人员工资'!D46 -> 0 | E46: =G46+I46+K46+M46+O46+Q46+S46+U46+W46+Y46 -> 0 | F46: =H46+J46+L46+N46+P46+R46+T46+V46+X46+Z46 -> 0 | G46: ='人员人工-研发人员工资'!G46 -> 0 | H46: =IF($D46=0,0,ROUND(G46/$D46*$C46,2)) -> 0 | I46: ='人员人工-研发人员工资'!I46 -> 0 | J46: =IF($D46=0,0,ROUND(I46/$D46*$C46,2)) -> 0 | K46: ='人员人工-研发人员工资'!K46 -> 0 | L46: =IF($D46=0,0,ROUND(K46/$D46*$C46,2)) -> 0 | M46: ='人员人工-研发人员工资'!M46 -> 0 | N46: =IF($D46=0,0,ROUND(M46/$D46*$C46,2)) -> 0 | O46: ='人员人工-研发人员工资'!O46 -> 0 | P46: =IF($D46=0,0,ROUND(O46/$D46*$C46,2)) -> 0 | Q46: ='人员人工-研发人员工资'!Q46 -> 0 | R46: =IF($D46=0,0,ROUND(Q46/$D46*$C46,2)) -> 0 | S46: ='人员人工-研发人员工资'!S46 -> 0 | T46: =IF($D46=0,0,ROUND(S46/$D46*$C46,2)) -> 0 | U46: ='人员人工-研发人员工资'!U46 -> 0 | V46: =IF($D46=0,0,ROUND(U46/$D46*$C46,2)) -> 0 | W46: ='人员人工-研发人员工资'!W46 -> 0 | X46: =IF($D46=0,0,ROUND(W46/$D46*$C46,2)) -> 0 | Y46: ='人员人工-研发人员工资'!Y46 -> 0 | Z46: =IF($D46=0,0,ROUND(Y46/$D46*$C46,2)) -> 0
A47: 5 | B47: ='人员人工-研发人员工资'!B47 -> 0 | D47: ='人员人工-研发人员工资'!D47 -> 0 | E47: =G47+I47+K47+M47+O47+Q47+S47+U47+W47+Y47 -> 0 | F47: =H47+J47+L47+N47+P47+R47+T47+V47+X47+Z47 -> 0 | G47: ='人员人工-研发人员工资'!G47 -> 0 | H47: =IF($D47=0,0,ROUND(G47/$D47*$C47,2)) -> 0 | I47: ='人员人工-研发人员工资'!I47 -> 0 | J47: =IF($D47=0,0,ROUND(I47/$D47*$C47,2)) -> 0 | K47: ='人员人工-研发人员工资'!K47 -> 0 | L47: =IF($D47=0,0,ROUND(K47/$D47*$C47,2)) -> 0 | M47: ='人员人工-研发人员工资'!M47 -> 0 | N47: =IF($D47=0,0,ROUND(M47/$D47*$C47,2)) -> 0 | O47: ='人员人工-研发人员工资'!O47 -> 0 | P47: =IF($D47=0,0,ROUND(O47/$D47*$C47,2)) -> 0 | Q47: ='人员人工-研发人员工资'!Q47 -> 0 | R47: =IF($D47=0,0,ROUND(Q47/$D47*$C47,2)) -> 0 | S47: ='人员人工-研发人员工资'!S47 -> 0 | T47: =IF($D47=0,0,ROUND(S47/$D47*$C47,2)) -> 0 | U47: ='人员人工-研发人员工资'!U47 -> 0 | V47: =IF($D47=0,0,ROUND(U47/$D47*$C47,2)) -> 0 | W47: ='人员人工-研发人员工资'!W47 -> 0 | X47: =IF($D47=0,0,ROUND(W47/$D47*$C47,2)) -> 0 | Y47: ='人员人工-研发人员工资'!Y47 -> 0 | Z47: =IF($D47=0,0,ROUND(Y47/$D47*$C47,2)) -> 0
A48: 6 | B48: ='人员人工-研发人员工资'!B48 -> 0 | D48: ='人员人工-研发人员工资'!D48 -> 0 | E48: =G48+I48+K48+M48+O48+Q48+S48+U48+W48+Y48 -> 0 | F48: =H48+J48+L48+N48+P48+R48+T48+V48+X48+Z48 -> 0 | G48: ='人员人工-研发人员工资'!G48 -> 0 | H48: =IF($D48=0,0,ROUND(G48/$D48*$C48,2)) -> 0 | I48: ='人员人工-研发人员工资'!I48 -> 0 | J48: =IF($D48=0,0,ROUND(I48/$D48*$C48,2)) -> 0 | K48: ='人员人工-研发人员工资'!K48 -> 0 | L48: =IF($D48=0,0,ROUND(K48/$D48*$C48,2)) -> 0 | M48: ='人员人工-研发人员工资'!M48 -> 0 | N48: =IF($D48=0,0,ROUND(M48/$D48*$C48,2)) -> 0 | O48: ='人员人工-研发人员工资'!O48 -> 0 | P48: =IF($D48=0,0,ROUND(O48/$D48*$C48,2)) -> 0 | Q48: ='人员人工-研发人员工资'!Q48 -> 0 | R48: =IF($D48=0,0,ROUND(Q48/$D48*$C48,2)) -> 0 | S48: ='人员人工-研发人员工资'!S48 -> 0 | T48: =IF($D48=0,0,ROUND(S48/$D48*$C48,2)) -> 0 | U48: ='人员人工-研发人员工资'!U48 -> 0 | V48: =IF($D48=0,0,ROUND(U48/$D48*$C48,2)) -> 0 | W48: ='人员人工-研发人员工资'!W48 -> 0 | X48: =IF($D48=0,0,ROUND(W48/$D48*$C48,2)) -> 0 | Y48: ='人员人工-研发人员工资'!Y48 -> 0 | Z48: =IF($D48=0,0,ROUND(Y48/$D48*$C48,2)) -> 0
A49: 7 | B49: ='人员人工-研发人员工资'!B49 -> 0 | D49: ='人员人工-研发人员工资'!D49 -> 0 | E49: =G49+I49+K49+M49+O49+Q49+S49+U49+W49+Y49 -> 0 | F49: =H49+J49+L49+N49+P49+R49+T49+V49+X49+Z49 -> 0 | G49: ='人员人工-研发人员工资'!G49 -> 0 | H49: =IF($D49=0,0,ROUND(G49/$D49*$C49,2)) -> 0 | I49: ='人员人工-研发人员工资'!I49 -> 0 | J49: =IF($D49=0,0,ROUND(I49/$D49*$C49,2)) -> 0 | K49: ='人员人工-研发人员工资'!K49 -> 0 | L49: =IF($D49=0,0,ROUND(K49/$D49*$C49,2)) -> 0 | M49: ='人员人工-研发人员工资'!M49 -> 0 | N49: =IF($D49=0,0,ROUND(M49/$D49*$C49,2)) -> 0 | O49: ='人员人工-研发人员工资'!O49 -> 0 | P49: =IF($D49=0,0,ROUND(O49/$D49*$C49,2)) -> 0 | Q49: ='人员人工-研发人员工资'!Q49 -> 0 | R49: =IF($D49=0,0,ROUND(Q49/$D49*$C49,2)) -> 0 | S49: ='人员人工-研发人员工资'!S49 -> 0 | T49: =IF($D49=0,0,ROUND(S49/$D49*$C49,2)) -> 0 | U49: ='人员人工-研发人员工资'!U49 -> 0 | V49: =IF($D49=0,0,ROUND(U49/$D49*$C49,2)) -> 0 | W49: ='人员人工-研发人员工资'!W49 -> 0 | X49: =IF($D49=0,0,ROUND(W49/$D49*$C49,2)) -> 0 | Y49: ='人员人工-研发人员工资'!Y49 -> 0 | Z49: =IF($D49=0,0,ROUND(Y49/$D49*$C49,2)) -> 0
A50: 8 | B50: ='人员人工-研发人员工资'!B50 -> 0 | D50: ='人员人工-研发人员工资'!D50 -> 0 | E50: =G50+I50+K50+M50+O50+Q50+S50+U50+W50+Y50 -> 0 | F50: =H50+J50+L50+N50+P50+R50+T50+V50+X50+Z50 -> 0 | G50: ='人员人工-研发人员工资'!G50 -> 0 | H50: =IF($D50=0,0,ROUND(G50/$D50*$C50,2)) -> 0 | I50: ='人员人工-研发人员工资'!I50 -> 0 | J50: =IF($D50=0,0,ROUND(I50/$D50*$C50,2)) -> 0 | K50: ='人员人工-研发人员工资'!K50 -> 0 | L50: =IF($D50=0,0,ROUND(K50/$D50*$C50,2)) -> 0 | M50: ='人员人工-研发人员工资'!M50 -> 0 | N50: =IF($D50=0,0,ROUND(M50/$D50*$C50,2)) -> 0 | O50: ='人员人工-研发人员工资'!O50 -> 0 | P50: =IF($D50=0,0,ROUND(O50/$D50*$C50,2)) -> 0 | Q50: ='人员人工-研发人员工资'!Q50 -> 0 | R50: =IF($D50=0,0,ROUND(Q50/$D50*$C50,2)) -> 0 | S50: ='人员人工-研发人员工资'!S50 -> 0 | T50: =IF($D50=0,0,ROUND(S50/$D50*$C50,2)) -> 0 | U50: ='人员人工-研发人员工资'!U50 -> 0 | V50: =IF($D50=0,0,ROUND(U50/$D50*$C50,2)) -> 0 | W50: ='人员人工-研发人员工资'!W50 -> 0 | X50: =IF($D50=0,0,ROUND(W50/$D50*$C50,2)) -> 0 | Y50: ='人员人工-研发人员工资'!Y50 -> 0 | Z50: =IF($D50=0,0,ROUND(Y50/$D50*$C50,2)) -> 0
A51: 9 | B51: ='人员人工-研发人员工资'!B51 -> 0 | D51: ='人员人工-研发人员工资'!D51 -> 0 | E51: =G51+I51+K51+M51+O51+Q51+S51+U51+W51+Y51 -> 0 | F51: =H51+J51+L51+N51+P51+R51+T51+V51+X51+Z51 -> 0 | G51: ='人员人工-研发人员工资'!G51 -> 0 | H51: =IF($D51=0,0,ROUND(G51/$D51*$C51,2)) -> 0 | I51: ='人员人工-研发人员工资'!I51 -> 0 | J51: =IF($D51=0,0,ROUND(I51/$D51*$C51,2)) -> 0 | K51: ='人员人工-研发人员工资'!K51 -> 0 | L51: =IF($D51=0,0,ROUND(K51/$D51*$C51,2)) -> 0 | M51: ='人员人工-研发人员工资'!M51 -> 0 | N51: =IF($D51=0,0,ROUND(M51/$D51*$C51,2)) -> 0 | O51: ='人员人工-研发人员工资'!O51 -> 0 | P51: =IF($D51=0,0,ROUND(O51/$D51*$C51,2)) -> 0 | Q51: ='人员人工-研发人员工资'!Q51 -> 0 | R51: =IF($D51=0,0,ROUND(Q51/$D51*$C51,2)) -> 0 | S51: ='人员人工-研发人员工资'!S51 -> 0 | T51: =IF($D51=0,0,ROUND(S51/$D51*$C51,2)) -> 0 | U51: ='人员人工-研发人员工资'!U51 -> 0 | V51: =IF($D51=0,0,ROUND(U51/$D51*$C51,2)) -> 0 | W51: ='人员人工-研发人员工资'!W51 -> 0 | X51: =IF($D51=0,0,ROUND(W51/$D51*$C51,2)) -> 0 | Y51: ='人员人工-研发人员工资'!Y51 -> 0 | Z51: =IF($D51=0,0,ROUND(Y51/$D51*$C51,2)) -> 0
A52: 10 | B52: ='人员人工-研发人员工资'!B52 -> 0 | D52: ='人员人工-研发人员工资'!D52 -> 0 | E52: =G52+I52+K52+M52+O52+Q52+S52+U52+W52+Y52 -> 0 | F52: =H52+J52+L52+N52+P52+R52+T52+V52+X52+Z52 -> 0 | G52: ='人员人工-研发人员工资'!G52 -> 0 | H52: =IF($D52=0,0,ROUND(G52/$D52*$C52,2)) -> 0 | I52: ='人员人工-研发人员工资'!I52 -> 0 | J52: =IF($D52=0,0,ROUND(I52/$D52*$C52,2)) -> 0 | K52: ='人员人工-研发人员工资'!K52 -> 0 | L52: =IF($D52=0,0,ROUND(K52/$D52*$C52,2)) -> 0 | M52: ='人员人工-研发人员工资'!M52 -> 0 | N52: =IF($D52=0,0,ROUND(M52/$D52*$C52,2)) -> 0 | O52: ='人员人工-研发人员工资'!O52 -> 0 | P52: =IF($D52=0,0,ROUND(O52/$D52*$C52,2)) -> 0 | Q52: ='人员人工-研发人员工资'!Q52 -> 0 | R52: =IF($D52=0,0,ROUND(Q52/$D52*$C52,2)) -> 0 | S52: ='人员人工-研发人员工资'!S52 -> 0 | T52: =IF($D52=0,0,ROUND(S52/$D52*$C52,2)) -> 0 | U52: ='人员人工-研发人员工资'!U52 -> 0 | V52: =IF($D52=0,0,ROUND(U52/$D52*$C52,2)) -> 0 | W52: ='人员人工-研发人员工资'!W52 -> 0 | X52: =IF($D52=0,0,ROUND(W52/$D52*$C52,2)) -> 0 | Y52: ='人员人工-研发人员工资'!Y52 -> 0 | Z52: =IF($D52=0,0,ROUND(Y52/$D52*$C52,2)) -> 0
A53: 11 | B53: ='人员人工-研发人员工资'!B53 -> 0 | D53: ='人员人工-研发人员工资'!D53 -> 0 | E53: =G53+I53+K53+M53+O53+Q53+S53+U53+W53+Y53 -> 0 | F53: =H53+J53+L53+N53+P53+R53+T53+V53+X53+Z53 -> 0 | G53: ='人员人工-研发人员工资'!G53 -> 0 | H53: =IF($D53=0,0,ROUND(G53/$D53*$C53,2)) -> 0 | I53: ='人员人工-研发人员工资'!I53 -> 0 | J53: =IF($D53=0,0,ROUND(I53/$D53*$C53,2)) -> 0 | K53: ='人员人工-研发人员工资'!K53 -> 0 | L53: =IF($D53=0,0,ROUND(K53/$D53*$C53,2)) -> 0 | M53: ='人员人工-研发人员工资'!M53 -> 0 | N53: =IF($D53=0,0,ROUND(M53/$D53*$C53,2)) -> 0 | O53: ='人员人工-研发人员工资'!O53 -> 0 | P53: =IF($D53=0,0,ROUND(O53/$D53*$C53,2)) -> 0 | Q53: ='人员人工-研发人员工资'!Q53 -> 0 | R53: =IF($D53=0,0,ROUND(Q53/$D53*$C53,2)) -> 0 | S53: ='人员人工-研发人员工资'!S53 -> 0 | T53: =IF($D53=0,0,ROUND(S53/$D53*$C53,2)) -> 0 | U53: ='人员人工-研发人员工资'!U53 -> 0 | V53: =IF($D53=0,0,ROUND(U53/$D53*$C53,2)) -> 0 | W53: ='人员人工-研发人员工资'!W53 -> 0 | X53: =IF($D53=0,0,ROUND(W53/$D53*$C53,2)) -> 0 | Y53: ='人员人工-研发人员工资'!Y53 -> 0 | Z53: =IF($D53=0,0,ROUND(Y53/$D53*$C53,2)) -> 0
A54: 12 | B54: ='人员人工-研发人员工资'!B54 -> 0 | D54: ='人员人工-研发人员工资'!D54 -> 0 | E54: =G54+I54+K54+M54+O54+Q54+S54+U54+W54+Y54 -> 0 | F54: =H54+J54+L54+N54+P54+R54+T54+V54+X54+Z54 -> 0 | G54: ='人员人工-研发人员工资'!G54 -> 0 | H54: =IF($D54=0,0,ROUND(G54/$D54*$C54,2)) -> 0 | I54: ='人员人工-研发人员工资'!I54 -> 0 | J54: =IF($D54=0,0,ROUND(I54/$D54*$C54,2)) -> 0 | K54: ='人员人工-研发人员工资'!K54 -> 0 | L54: =IF($D54=0,0,ROUND(K54/$D54*$C54,2)) -> 0 | M54: ='人员人工-研发人员工资'!M54 -> 0 | N54: =IF($D54=0,0,ROUND(M54/$D54*$C54,2)) -> 0 | O54: ='人员人工-研发人员工资'!O54 -> 0 | P54: =IF($D54=0,0,ROUND(O54/$D54*$C54,2)) -> 0 | Q54: ='人员人工-研发人员工资'!Q54 -> 0 | R54: =IF($D54=0,0,ROUND(Q54/$D54*$C54,2)) -> 0 | S54: ='人员人工-研发人员工资'!S54 -> 0 | T54: =IF($D54=0,0,ROUND(S54/$D54*$C54,2)) -> 0 | U54: ='人员人工-研发人员工资'!U54 -> 0 | V54: =IF($D54=0,0,ROUND(U54/$D54*$C54,2)) -> 0 | W54: ='人员人工-研发人员工资'!W54 -> 0 | X54: =IF($D54=0,0,ROUND(W54/$D54*$C54,2)) -> 0 | Y54: ='人员人工-研发人员工资'!Y54 -> 0 | Z54: =IF($D54=0,0,ROUND(Y54/$D54*$C54,2)) -> 0
... A72: 30 | B72: ='人员人工-研发人员工资'!B72 -> 0 | D72: ='人员人工-研发人员工资'!D72 -> 0 | E72: =G72+I72+K72+M72+O72+Q72+S72+U72+W72+Y72 -> 0 | F72: =H72+J72+L72+N72+P72+R72+T72+V72+X72+Z72 -> 0 | G72: ='人员人工-研发人员工资'!G72 -> 0 | H72: =IF($D72=0,0,ROUND(G72/$D72*$C72,2)) -> 0 | I72: ='人员人工-研发人员工资'!I72 -> 0 | J72: =IF($D72=0,0,ROUND(I72/$D72*$C72,2)) -> 0 | K72: ='人员人工-研发人员工资'!K72 -> 0 | L72: =IF($D72=0,0,ROUND(K72/$D72*$C72,2)) -> 0 | M72: ='人员人工-研发人员工资'!M72 -> 0 | N72: =IF($D72=0,0,ROUND(M72/$D72*$C72,2)) -> 0 | O72: ='人员人工-研发人员工资'!O72 -> 0 | P72: =IF($D72=0,0,ROUND(O72/$D72*$C72,2)) -> 0 | Q72: ='人员人工-研发人员工资'!Q72 -> 0 | R72: =IF($D72=0,0,ROUND(Q72/$D72*$C72,2)) -> 0 | S72: ='人员人工-研发人员工资'!S72 -> 0 | T72: =IF($D72=0,0,ROUND(S72/$D72*$C72,2)) -> 0 | U72: ='人员人工-研发人员工资'!U72 -> 0 | V72: =IF($D72=0,0,ROUND(U72/$D72*$C72,2)) -> 0 | W72: ='人员人工-研发人员工资'!W72 -> 0 | X72: =IF($D72=0,0,ROUND(W72/$D72*$C72,2)) -> 0 | Y72: ='人员人工-研发人员工资'!Y72 -> 0 | Z72: =IF($D72=0,0,ROUND(Y72/$D72*$C72,2)) -> 0
A73: 合计 | C73: =SUM(C43:C72) -> 0 | D73: =SUM(D43:D72) -> 0 | E73: =SUM(E43:E72) -> 0 | F73: =SUM(F43:F72) -> 0 | G73: =SUM(G43:G72) -> 0 | H73: =SUM(H43:H72) -> 0 | I73: =SUM(I43:I72) -> 0 | J73: =SUM(J43:J72) -> 0 | ... Z73: =SUM(Z43:Z72) -> 0
B76: 2025年3月份研发人员社保项目分摊表
A78: 序号 | B78: 姓名 | C78: 月社保 | D78: 出勤天数 | E78: 研发天数合计 | F78: 研发社保合计 | G78: =立项!$A$3 -> RD01 | I78: =立项!$A$4 -> RD02 | K78: =立项!$A$5 -> RD03 | M78: =立项!$A$6 -> RD04 | O78: =立项!$A$7 -> RD05 | Q78: =立项!$A$8 -> RD06 | S78: =立项!$A$9 -> RD07 | U78: =立项!$A$10 -> RD08 | W78: =立项!$A$11 -> RD09 | Y78: =立项!$A$12 -> RD10
G79: =立项!C3 -> 0 | I79: =立项!C4 -> 0 | K79: =立项!C5 -> 0 | M79: =立项!C6 -> 0 | O79: =立项!C7 -> 0 | Q79: =立项!C8 -> 0 | S79: =立项!C9 -> 0 | U79: =立项!C10 -> 0 | W79: =立项!C11 -> 0 | Y79: =立项!C12 -> 0
G80: 研发天数 | H80: 研发社保 | I80: 研发天数 | J80: 研发社保 | K80: 研发天数 | L80: 研发社保 | M80: 研发天数 | N80: 研发社保 | O80: 研发天数 | P80: 研发社保 | Q80: 研发天数 | R80: 研发社保 | S80: 研发天数 | T80: 研发社保 | U80: 研发天数 | V80: 研发社保 | W80: 研发天数 | X80: 研发社保 | Y80: 研发天数 | Z80: 研发社保
A81: 1 | B81: ='人员人工-研发人员工资'!B81 -> 0 | D81: ='人员人工-研发人员工资'!D81 -> 0 | E81: =G81+I81+K81+M81+O81+Q81+S81+U81+W81+Y81 -> 0 | F81: =H81+J81+L81+N81+P81+R81+T81+V81+X81+Z81 -> 0 | G81: ='人员人工-研发人员工资'!G81 -> 0 | H81: =IF($D81=0,0,ROUND(G81/$D81*$C81,2)) -> 0 | I81: ='人员人工-研发人员工资'!I81 -> 0 | J81: =IF($D81=0,0,ROUND(I81/$D81*$C81,2)) -> 0 | K81: ='人员人工-研发人员工资'!K81 -> 0 | L81: =IF($D81=0,0,ROUND(K81/$D81*$C81,2)) -> 0 | M81: ='人员人工-研发人员工资'!M81 -> 0 | N81: =IF($D81=0,0,ROUND(M81/$D81*$C81,2)) -> 0 | O81: ='人员人工-研发人员工资'!O81 -> 0 | P81: =IF($D81=0,0,ROUND(O81/$D81*$C81,2)) -> 0 | Q81: ='人员人工-研发人员工资'!Q81 -> 0 | R81: =IF($D81=0,0,ROUND(Q81/$D81*$C81,2)) -> 0 | S81: ='人员人工-研发人员工资'!S81 -> 0 | T81: =IF($D81=0,0,ROUND(S81/$D81*$C81,2)) -> 0 | U81: ='人员人工-研发人员工资'!U81 -> 0 | V81: =IF($D81=0,0,ROUND(U81/$D81*$C81,2)) -> 0 | W81: ='人员人工-研发人员工资'!W81 -> 0 | X81: =IF($D81=0,0,ROUND(W81/$D81*$C81,2)) -> 0 | Y81: ='人员人工-研发人员工资'!Y81 -> 0 | Z81: =IF($D81=0,0,ROUND(Y81/$D81*$C81,2)) -> 0
A82: 2 | B82: ='人员人工-研发人员工资'!B82 -> 0 | D82: ='人员人工-研发人员工资'!D82 -> 0 | E82: =G82+I82+K82+M82+O82+Q82+S82+U82+W82+Y82 -> 0 | F82: =H82+J82+L82+N82+P82+R82+T82+V82+X82+Z82 -> 0 | G82: ='人员人工-研发人员工资'!G82 -> 0 | H82: =IF($D82=0,0,ROUND(G82/$D82*$C82,2)) -> 0 | I82: ='人员人工-研发人员工资'!I82 -> 0 | J82: =IF($D82=0,0,ROUND(I82/$D82*$C82,2)) -> 0 | K82: ='人员人工-研发人员工资'!K82 -> 0 | L82: =IF($D82=0,0,ROUND(K82/$D82*$C82,2)) -> 0 | M82: ='人员人工-研发人员工资'!M82 -> 0 | N82: =IF($D82=0,0,ROUND(M82/$D82*$C82,2)) -> 0 | O82: ='人员人工-研发人员工资'!O82 -> 0 | P82: =IF($D82=0,0,ROUND(O82/$D82*$C82,2)) -> 0 | Q82: ='人员人工-研发人员工资'!Q82 -> 0 | R82: =IF($D82=0,0,ROUND(Q82/$D82*$C82,2)) -> 0 | S82: ='人员人工-研发人员工资'!S82 -> 0 | T82: =IF($D82=0,0,ROUND(S82/$D82*$C82,2)) -> 0 | U82: ='人员人工-研发人员工资'!U82 -> 0 | V82: =IF($D82=0,0,ROUND(U82/$D82*$C82,2)) -> 0 | W82: ='人员人工-研发人员工资'!W82 -> 0 | X82: =IF($D82=0,0,ROUND(W82/$D82*$C82,2)) -> 0 | Y82: ='人员人工-研发人员工资'!Y82 -> 0 | Z82: =IF($D82=0,0,ROUND(Y82/$D82*$C82,2)) -> 0
A83: 3 | B83: ='人员人工-研发人员工资'!B83 -> 0 | D83: ='人员人工-研发人员工资'!D83 -> 0 | E83: =G83+I83+K83+M83+O83+Q83+S83+U83+W83+Y83 -> 0 | F83: =H83+J83+L83+N83+P83+R83+T83+V83+X83+Z83 -> 0 | G83: ='人员人工-研发人员工资'!G83 -> 0 | H83: =IF($D83=0,0,ROUND(G83/$D83*$C83,2)) -> 0 | I83: ='人员人工-研发人员工资'!I83 -> 0 | J83: =IF($D83=0,0,ROUND(I83/$D83*$C83,2)) -> 0 | K83: ='人员人工-研发人员工资'!K83 -> 0 | L83: =IF($D83=0,0,ROUND(K83/$D83*$C83,2)) -> 0 | M83: ='人员人工-研发人员工资'!M83 -> 0 | N83: =IF($D83=0,0,ROUND(M83/$D83*$C83,2)) -> 0 | O83: ='人员人工-研发人员工资'!O83 -> 0 | P83: =IF($D83=0,0,ROUND(O83/$D83*$C83,2)) -> 0 | Q83: ='人员人工-研发人员工资'!Q83 -> 0 | R83: =IF($D83=0,0,ROUND(Q83/$D83*$C83,2)) -> 0 | S83: ='人员人工-研发人员工资'!S83 -> 0 | T83: =IF($D83=0,0,ROUND(S83/$D83*$C83,2)) -> 0 | U83: ='人员人工-研发人员工资'!U83 -> 0 | V83: =IF($D83=0,0,ROUND(U83/$D83*$C83,2)) -> 0 | W83: ='人员人工-研发人员工资'!W83 -> 0 | X83: =IF($D83=0,0,ROUND(W83/$D83*$C83,2)) -> 0 | Y83: ='人员人工-研发人员工资'!Y83 -> 0 | Z83: =IF($D83=0,0,ROUND(Y83/$D83*$C83,2)) -> 0
A84: 4 | B84: ='人员人工-研发人员工资'!B84 -> 0 | D84: ='人员人工-研发人员工资'!D84 -> 0 | E84: =G84+I84+K84+M84+O84+Q84+S84+U84+W84+Y84 -> 0 | F84: =H84+J84+L84+N84+P84+R84+T84+V84+X84+Z84 -> 0 | G84: ='人员人工-研发人员工资'!G84 -> 0 | H84: =IF($D84=0,0,ROUND(G84/$D84*$C84,2)) -> 0 | I84: ='人员人工-研发人员工资'!I84 -> 0 | J84: =IF($D84=0,0,ROUND(I84/$D84*$C84,2)) -> 0 | K84: ='人员人工-研发人员工资'!K84 -> 0 | L84: =IF($D84=0,0,ROUND(K84/$D84*$C84,2)) -> 0 | M84: ='人员人工-研发人员工资'!M84 -> 0 | N84: =IF($D84=0,0,ROUND(M84/$D84*$C84,2)) -> 0 | O84: ='人员人工-研发人员工资'!O84 -> 0 | P84: =IF($D84=0,0,ROUND(O84/$D84*$C84,2)) -> 0 | Q84: ='人员人工-研发人员工资'!Q84 -> 0 | R84: =IF($D84=0,0,ROUND(Q84/$D84*$C84,2)) -> 0 | S84: ='人员人工-研发人员工资'!S84 -> 0 | T84: =IF($D84=0,0,ROUND(S84/$D84*$C84,2)) -> 0 | U84: ='人员人工-研发人员工资'!U84 -> 0 | V84: =IF($D84=0,0,ROUND(U84/$D84*$C84,2)) -> 0 | W84: ='人员人工-研发人员工资'!W84 -> 0 | X84: =IF($D84=0,0,ROUND(W84/$D84*$C84,2)) -> 0 | Y84: ='人员人工-研发人员工资'!Y84 -> 0 | Z84: =IF($D84=0,0,ROUND(Y84/$D84*$C84,2)) -> 0
A85: 5 | B85: ='人员人工-研发人员工资'!B85 -> 0 | D85: ='人员人工-研发人员工资'!D85 -> 0 | E85: =G85+I85+K85+M85+O85+Q85+S85+U85+W85+Y85 -> 0 | F85: =H85+J85+L85+N85+P85+R85+T85+V85+X85+Z85 -> 0 | G85: ='人员人工-研发人员工资'!G85 -> 0 | H85: =IF($D85=0,0,ROUND(G85/$D85*$C85,2)) -> 0 | I85: ='人员人工-研发人员工资'!I85 -> 0 | J85: =IF($D85=0,0,ROUND(I85/$D85*$C85,2)) -> 0 | K85: ='人员人工-研发人员工资'!K85 -> 0 | L85: =IF($D85=0,0,ROUND(K85/$D85*$C85,2)) -> 0 | M85: ='人员人工-研发人员工资'!M85 -> 0 | N85: =IF($D85=0,0,ROUND(M85/$D85*$C85,2)) -> 0 | O85: ='人员人工-研发人员工资'!O85 -> 0 | P85: =IF($D85=0,0,ROUND(O85/$D85*$C85,2)) -> 0 | Q85: ='人员人工-研发人员工资'!Q85 -> 0 | R85: =IF($D85=0,0,ROUND(Q85/$D85*$C85,2)) -> 0 | S85: ='人员人工-研发人员工资'!S85 -> 0 | T85: =IF($D85=0,0,ROUND(S85/$D85*$C85,2)) -> 0 | U85: ='人员人工-研发人员工资'!U85 -> 0 | V85: =IF($D85=0,0,ROUND(U85/$D85*$C85,2)) -> 0 | W85: ='人员人工-研发人员工资'!W85 -> 0 | X85: =IF($D85=0,0,ROUND(W85/$D85*$C85,2)) -> 0 | Y85: ='人员人工-研发人员工资'!Y85 -> 0 | Z85: =IF($D85=0,0,ROUND(Y85/$D85*$C85,2)) -> 0
A86: 6 | B86: ='人员人工-研发人员工资'!B86 -> 0 | D86: ='人员人工-研发人员工资'!D86 -> 0 | E86: =G86+I86+K86+M86+O86+Q86+S86+U86+W86+Y86 -> 0 | F86: =H86+J86+L86+N86+P86+R86+T86+V86+X86+Z86 -> 0 | G86: ='人员人工-研发人员工资'!G86 -> 0 | H86: =IF($D86=0,0,ROUND(G86/$D86*$C86,2)) -> 0 | I86: ='人员人工-研发人员工资'!I86 -> 0 | J86: =IF($D86=0,0,ROUND(I86/$D86*$C86,2)) -> 0 | K86: ='人员人工-研发人员工资'!K86 -> 0 | L86: =IF($D86=0,0,ROUND(K86/$D86*$C86,2)) -> 0 | M86: ='人员人工-研发人员工资'!M86 -> 0 | N86: =IF($D86=0,0,ROUND(M86/$D86*$C86,2)) -> 0 | O86: ='人员人工-研发人员工资'!O86 -> 0 | P86: =IF($D86=0,0,ROUND(O86/$D86*$C86,2)) -> 0 | Q86: ='人员人工-研发人员工资'!Q86 -> 0 | R86: =IF($D86=0,0,ROUND(Q86/$D86*$C86,2)) -> 0 | S86: ='人员人工-研发人员工资'!S86 -> 0 | T86: =IF($D86=0,0,ROUND(S86/$D86*$C86,2)) -> 0 | U86: ='人员人工-研发人员工资'!U86 -> 0 | V86: =IF($D86=0,0,ROUND(U86/$D86*$C86,2)) -> 0 | W86: ='人员人工-研发人员工资'!W86 -> 0 | X86: =IF($D86=0,0,ROUND(W86/$D86*$C86,2)) -> 0 | Y86: ='人员人工-研发人员工资'!Y86 -> 0 | Z86: =IF($D86=0,0,ROUND(Y86/$D86*$C86,2)) -> 0
A87: 7 | B87: ='人员人工-研发人员工资'!B87 -> 0 | D87: ='人员人工-研发人员工资'!D87 -> 0 | E87: =G87+I87+K87+M87+O87+Q87+S87+U87+W87+Y87 -> 0 | F87: =H87+J87+L87+N87+P87+R87+T87+V87+X87+Z87 -> 0 | G87: ='人员人工-研发人员工资'!G87 -> 0 | H87: =IF($D87=0,0,ROUND(G87/$D87*$C87,2)) -> 0 | I87: ='人员人工-研发人员工资'!I87 -> 0 | J87: =IF($D87=0,0,ROUND(I87/$D87*$C87,2)) -> 0 | K87: ='人员人工-研发人员工资'!K87 -> 0 | L87: =IF($D87=0,0,ROUND(K87/$D87*$C87,2)) -> 0 | M87: ='人员人工-研发人员工资'!M87 -> 0 | N87: =IF($D87=0,0,ROUND(M87/$D87*$C87,2)) -> 0 | O87: ='人员人工-研发人员工资'!O87 -> 0 | P87: =IF($D87=0,0,ROUND(O87/$D87*$C87,2)) -> 0 | Q87: ='人员人工-研发人员工资'!Q87 -> 0 | R87: =IF($D87=0,0,ROUND(Q87/$D87*$C87,2)) -> 0 | S87: ='人员人工-研发人员工资'!S87 -> 0 | T87: =IF($D87=0,0,ROUND(S87/$D87*$C87,2)) -> 0 | U87: ='人员人工-研发人员工资'!U87 -> 0 | V87: =IF($D87=0,0,ROUND(U87/$D87*$C87,2)) -> 0 | W87: ='人员人工-研发人员工资'!W87 -> 0 | X87: =IF($D87=0,0,ROUND(W87/$D87*$C87,2)) -> 0 | Y87: ='人员人工-研发人员工资'!Y87 -> 0 | Z87: =IF($D87=0,0,ROUND(Y87/$D87*$C87,2)) -> 0
A88: 8 | B88: ='人员人工-研发人员工资'!B88 -> 0 | D88: ='人员人工-研发人员工资'!D88 -> 0 | E88: =G88+I88+K88+M88+O88+Q88+S88+U88+W88+Y88 -> 0 | F88: =H88+J88+L88+N88+P88+R88+T88+V88+X88+Z88 -> 0 | G88: ='人员人工-研发人员工资'!G88 -> 0 | H88: =IF($D88=0,0,ROUND(G88/$D88*$C88,2)) -> 0 | I88: ='人员人工-研发人员工资'!I88 -> 0 | J88: =IF($D88=0,0,ROUND(I88/$D88*$C88,2)) -> 0 | K88: ='人员人工-研发人员工资'!K88 -> 0 | L88: =IF($D88=0,0,ROUND(K88/$D88*$C88,2)) -> 0 | M88: ='人员人工-研发人员工资'!M88 -> 0 | N88: =IF($D88=0,0,ROUND(M88/$D88*$C88,2)) -> 0 | O88: ='人员人工-研发人员工资'!O88 -> 0 | P88: =IF($D88=0,0,ROUND(O88/$D88*$C88,2)) -> 0 | Q88: ='人员人工-研发人员工资'!Q88 -> 0 | R88: =IF($D88=0,0,ROUND(Q88/$D88*$C88,2)) -> 0 | S88: ='人员人工-研发人员工资'!S88 -> 0 | T88: =IF($D88=0,0,ROUND(S88/$D88*$C88,2)) -> 0 | U88: ='人员人工-研发人员工资'!U88 -> 0 | V88: =IF($D88=0,0,ROUND(U88/$D88*$C88,2)) -> 0 | W88: ='人员人工-研发人员工资'!W88 -> 0 | X88: =IF($D88=0,0,ROUND(W88/$D88*$C88,2)) -> 0 | Y88: ='人员人工-研发人员工资'!Y88 -> 0 | Z88: =IF($D88=0,0,ROUND(Y88/$D88*$C88,2)) -> 0
A89: 9 | B89: ='人员人工-研发人员工资'!B89 -> 0 | D89: ='人员人工-研发人员工资'!D89 -> 0 | E89: =G89+I89+K89+M89+O89+Q89+S89+U89+W89+Y89 -> 0 | F89: =H89+J89+L89+N89+P89+R89+T89+V89+X89+Z89 -> 0 | G89: ='人员人工-研发人员工资'!G89 -> 0 | H89: =IF($D89=0,0,ROUND(G89/$D89*$C89,2)) -> 0 | I89: ='人员人工-研发人员工资'!I89 -> 0 | J89: =IF($D89=0,0,ROUND(I89/$D89*$C89,2)) -> 0 | K89: ='人员人工-研发人员工资'!K89 -> 0 | L89: =IF($D89=0,0,ROUND(K89/$D89*$C89,2)) -> 0 | M89: ='人员人工-研发人员工资'!M89 -> 0 | N89: =IF($D89=0,0,ROUND(M89/$D89*$C89,2)) -> 0 | O89: ='人员人工-研发人员工资'!O89 -> 0 | P89: =IF($D89=0,0,ROUND(O89/$D89*$C89,2)) -> 0 | Q89: ='人员人工-研发人员工资'!Q89 -> 0 | R89: =IF($D89=0,0,ROUND(Q89/$D89*$C89,2)) -> 0 | S89: ='人员人工-研发人员工资'!S89 -> 0 | T89: =IF($D89=0,0,ROUND(S89/$D89*$C89,2)) -> 0 | U89: ='人员人工-研发人员工资'!U89 -> 0 | V89: =IF($D89=0,0,ROUND(U89/$D89*$C89,2)) -> 0 | W89: ='人员人工-研发人员工资'!W89 -> 0 | X89: =IF($D89=0,0,ROUND(W89/$D89*$C89,2)) -> 0 | Y89: ='人员人工-研发人员工资'!Y89 -> 0 | Z89: =IF($D89=0,0,ROUND(Y89/$D89*$C89,2)) -> 0
A90: 10 | B90: ='人员人工-研发人员工资'!B90 -> 0 | D90: ='人员人工-研发人员工资'!D90 -> 0 | E90: =G90+I90+K90+M90+O90+Q90+S90+U90+W90+Y90 -> 0 | F90: =H90+J90+L90+N90+P90+R90+T90+V90+X90+Z90 -> 0 | G90: ='人员人工-研发人员工资'!G90 -> 0 | H90: =IF($D90=0,0,ROUND(G90/$D90*$C90,2)) -> 0 | I90: ='人员人工-研发人员工资'!I90 -> 0 | J90: =IF($D90=0,0,ROUND(I90/$D90*$C90,2)) -> 0 | K90: ='人员人工-研发人员工资'!K90 -> 0 | L90: =IF($D90=0,0,ROUND(K90/$D90*$C90,2)) -> 0 | M90: ='人员人工-研发人员工资'!M90 -> 0 | N90: =IF($D90=0,0,ROUND(M90/$D90*$C90,2)) -> 0 | O90: ='人员人工-研发人员工资'!O90 -> 0 | P90: =IF($D90=0,0,ROUND(O90/$D90*$C90,2)) -> 0 | Q90: ='人员人工-研发人员工资'!Q90 -> 0 | R90: =IF($D90=0,0,ROUND(Q90/$D90*$C90,2)) -> 0 | S90: ='人员人工-研发人员工资'!S90 -> 0 | T90: =IF($D90=0,0,ROUND(S90/$D90*$C90,2)) -> 0 | U90: ='人员人工-研发人员工资'!U90 -> 0 | V90: =IF($D90=0,0,ROUND(U90/$D90*$C90,2)) -> 0 | W90: ='人员人工-研发人员工资'!W90 -> 0 | X90: =IF($D90=0,0,ROUND(W90/$D90*$C90,2)) -> 0 | Y90: ='人员人工-研发人员工资'!Y90 -> 0 | Z90: =IF($D90=0,0,ROUND(Y90/$D90*$C90,2)) -> 0
A91: 11 | B91: ='人员人工-研发人员工资'!B91 -> 0 | D91: ='人员人工-研发人员工资'!D91 -> 0 | E91: =G91+I91+K91+M91+O91+Q91+S91+U91+W91+Y91 -> 0 | F91: =H91+J91+L91+N91+P91+R91+T91+V91+X91+Z91 -> 0 | G91: ='人员人工-研发人员工资'!G91 -> 0 | H91: =IF($D91=0,0,ROUND(G91/$D91*$C91,2)) -> 0 | I91: ='人员人工-研发人员工资'!I91 -> 0 | J91: =IF($D91=0,0,ROUND(I91/$D91*$C91,2)) -> 0 | K91: ='人员人工-研发人员工资'!K91 -> 0 | L91: =IF($D91=0,0,ROUND(K91/$D91*$C91,2)) -> 0 | M91: ='人员人工-研发人员工资'!M91 -> 0 | N91: =IF($D91=0,0,ROUND(M91/$D91*$C91,2)) -> 0 | O91: ='人员人工-研发人员工资'!O91 -> 0 | P91: =IF($D91=0,0,ROUND(O91/$D91*$C91,2)) -> 0 | Q91: ='人员人工-研发人员工资'!Q91 -> 0 | R91: =IF($D91=0,0,ROUND(Q91/$D91*$C91,2)) -> 0 | S91: ='人员人工-研发人员工资'!S91 -> 0 | T91: =IF($D91=0,0,ROUND(S91/$D91*$C91,2)) -> 0 | U91: ='人员人工-研发人员工资'!U91 -> 0 | V91: =IF($D91=0,0,ROUND(U91/$D91*$C91,2)) -> 0 | W91: ='人员人工-研发人员工资'!W91 -> 0 | X91: =IF($D91=0,0,ROUND(W91/$D91*$C91,2)) -> 0 | Y91: ='人员人工-研发人员工资'!Y91 -> 0 | Z91: =IF($D91=0,0,ROUND(Y91/$D91*$C91,2)) -> 0
A92: 12 | B92: ='人员人工-研发人员工资'!B92 -> 0 | D92: ='人员人工-研发人员工资'!D92 -> 0 | E92: =G92+I92+K92+M92+O92+Q92+S92+U92+W92+Y92 -> 0 | F92: =H92+J92+L92+N92+P92+R92+T92+V92+X92+Z92 -> 0 | G92: ='人员人工-研发人员工资'!G92 -> 0 | H92: =IF($D92=0,0,ROUND(G92/$D92*$C92,2)) -> 0 | I92: ='人员人工-研发人员工资'!I92 -> 0 | J92: =IF($D92=0,0,ROUND(I92/$D92*$C92,2)) -> 0 | K92: ='人员人工-研发人员工资'!K92 -> 0 | L92: =IF($D92=0,0,ROUND(K92/$D92*$C92,2)) -> 0 | M92: ='人员人工-研发人员工资'!M92 -> 0 | N92: =IF($D92=0,0,ROUND(M92/$D92*$C92,2)) -> 0 | O92: ='人员人工-研发人员工资'!O92 -> 0 | P92: =IF($D92=0,0,ROUND(O92/$D92*$C92,2)) -> 0 | Q92: ='人员人工-研发人员工资'!Q92 -> 0 | R92: =IF($D92=0,0,ROUND(Q92/$D92*$C92,2)) -> 0 | S92: ='人员人工-研发人员工资'!S92 -> 0 | T92: =IF($D92=0,0,ROUND(S92/$D92*$C92,2)) -> 0 | U92: ='人员人工-研发人员工资'!U92 -> 0 | V92: =IF($D92=0,0,ROUND(U92/$D92*$C92,2)) -> 0 | W92: ='人员人工-研发人员工资'!W92 -> 0 | X92: =IF($D92=0,0,ROUND(W92/$D92*$C92,2)) -> 0 | Y92: ='人员人工-研发人员工资'!Y92 -> 0 | Z92: =IF($D92=0,0,ROUND(Y92/$D92*$C92,2)) -> 0
... A110: 30 | B110: ='人员人工-研发人员工资'!B110 -> 0 | D110: ='人员人工-研发人员工资'!D110 -> 0 | E110: =G110+I110+K110+M110+O110+Q110+S110+U110+W110+Y110 -> 0 | F110: =H110+J110+L110+N110+P110+R110+T110+V110+X110+Z110 -> 0 | G110: ='人员人工-研发人员工资'!G110 -> 0 | H110: =IF($D110=0,0,ROUND(G110/$D110*$C110,2)) -> 0 | I110: ='人员人工-研发人员工资'!I110 -> 0 | J110: =IF($D110=0,0,ROUND(I110/$D110*$C110,2)) -> 0 | K110: ='人员人工-研发人员工资'!K110 -> 0 | L110: =IF($D110=0,0,ROUND(K110/$D110*$C110,2)) -> 0 | M110: ='人员人工-研发人员工资'!M110 -> 0 | N110: =IF($D110=0,0,ROUND(M110/$D110*$C110,2)) -> 0 | O110: ='人员人工-研发人员工资'!O110 -> 0 | P110: =IF($D110=0,0,ROUND(O110/$D110*$C110,2)) -> 0 | Q110: ='人员人工-研发人员工资'!Q110 -> 0 | R110: =IF($D110=0,0,ROUND(Q110/$D110*$C110,2)) -> 0 | S110: ='人员人工-研发人员工资'!S110 -> 0 | T110: =IF($D110=0,0,ROUND(S110/$D110*$C110,2)) -> 0 | U110: ='人员人工-研发人员工资'!U110 -> 0 | V110: =IF($D110=0,0,ROUND(U110/$D110*$C110,2)) -> 0 | W110: ='人员人工-研发人员工资'!W110 -> 0 | X110: =IF($D110=0,0,ROUND(W110/$D110*$C110,2)) -> 0 | Y110: ='人员人工-研发人员工资'!Y110 -> 0 | Z110: =IF($D110=0,0,ROUND(Y110/$D110*$C110,2)) -> 0
A111: 合计 | C111: =SUM(C81:C110) -> 0 | D111: =SUM(D81:D110) -> 0 | E111: =SUM(E81:E110) -> 0 | F111: =SUM(F81:F110) -> 0 | G111: =SUM(G81:G110) -> 0 | H111: =SUM(H81:H110) -> 0 | I111: =SUM(I81:I110) -> 0 | J111: =SUM(J81:J110) -> 0 | ... Z111: =SUM(Z81:Z110) -> 0
B114: 2025年4月份研发人员社保项目分摊表
A116: 序号 | B116: 姓名 | C116: 月社保 | D116: 出勤天数 | E116: 研发天数合计 | F116: 研发社保合计 | G116: =立项!$A$3 -> RD01 | I116: =立项!$A$4 -> RD02 | K116: =立项!$A$5 -> RD03 | M116: =立项!$A$6 -> RD04 | O116: =立项!$A$7 -> RD05 | Q116: =立项!$A$8 -> RD06 | S116: =立项!$A$9 -> RD07 | U116: =立项!$A$10 -> RD08 | W116: =立项!$A$11 -> RD09 | Y116: =立项!$A$12 -> RD10
G117: =立项!C3 -> 0 | I117: =立项!C4 -> 0 | K117: =立项!C5 -> 0 | M117: =立项!C6 -> 0 | O117: =立项!C7 -> 0 | Q117: =立项!C8 -> 0 | S117: =立项!C9 -> 0 | U117: =立项!C10 -> 0 | W117: =立项!C11 -> 0 | Y117: =立项!C12 -> 0
G118: 研发天数 | H118: 研发社保 | I118: 研发天数 | J118: 研发社保 | K118: 研发天数 | L118: 研发社保 | M118: 研发天数 | N118: 研发社保 | O118: 研发天数 | P118: 研发社保 | Q118: 研发天数 | R118: 研发社保 | S118: 研发天数 | T118: 研发社保 | U118: 研发天数 | V118: 研发社保 | W118: 研发天数 | X118: 研发社保 | Y118: 研发天数 | Z118: 研发社保
A119: 1 | B119: ='人员人工-研发人员工资'!B119 -> 0 | D119: ='人员人工-研发人员工资'!D119 -> 0 | E119: =G119+I119+K119+M119+O119+Q119+S119+U119+W119+Y119 -> 0 | F119: =H119+J119+L119+N119+P119+R119+T119+V119+X119+Z119 -> 0 | G119: ='人员人工-研发人员工资'!G119 -> 0 | H119: =IF($D119=0,0,ROUND(G119/$D119*$C119,2)) -> 0 | I119: ='人员人工-研发人员工资'!I119 -> 0 | J119: =IF($D119=0,0,ROUND(I119/$D119*$C119,2)) -> 0 | K119: ='人员人工-研发人员工资'!K119 -> 0 | L119: =IF($D119=0,0,ROUND(K119/$D119*$C119,2)) -> 0 | M119: ='人员人工-研发人员工资'!M119 -> 0 | N119: =IF($D119=0,0,ROUND(M119/$D119*$C119,2)) -> 0 | O119: ='人员人工-研发人员工资'!O119 -> 0 | P119: =IF($D119=0,0,ROUND(O119/$D119*$C119,2)) -> 0 | Q119: ='人员人工-研发人员工资'!Q119 -> 0 | R119: =IF($D119=0,0,ROUND(Q119/$D119*$C119,2)) -> 0 | S119: ='人员人工-研发人员工资'!S119 -> 0 | T119: =IF($D119=0,0,ROUND(S119/$D119*$C119,2)) -> 0 | U119: ='人员人工-研发人员工资'!U119 -> 0 | V119: =IF($D119=0,0,ROUND(U119/$D119*$C119,2)) -> 0 | W119: ='人员人工-研发人员工资'!W119 -> 0 | X119: =IF($D119=0,0,ROUND(W119/$D119*$C119,2)) -> 0 | Y119: ='人员人工-研发人员工资'!Y119 -> 0 | Z119: =IF($D119=0,0,ROUND(Y119/$D119*$C119,2)) -> 0
A120: 2 | B120: ='人员人工-研发人员工资'!B120 -> 0 | D120: ='人员人工-研发人员工资'!D120 -> 0 | E120: =G120+I120+K120+M120+O120+Q120+S120+U120+W120+Y120 -> 0 | F120: =H120+J120+L120+N120+P120+R120+T120+V120+X120+Z120 -> 0 | G120: ='人员人工-研发人员工资'!G120 -> 0 | H120: =IF($D120=0,0,ROUND(G120/$D120*$C120,2)) -> 0 | I120: ='人员人工-研发人员工资'!I120 -> 0 | J120: =IF($D120=0,0,ROUND(I120/$D120*$C120,2)) -> 0 | K120: ='人员人工-研发人员工资'!K120 -> 0 | L120: =IF($D120=0,0,ROUND(K120/$D120*$C120,2)) -> 0 | M120: ='人员人工-研发人员工资'!M120 -> 0 | N120: =IF($D120=0,0,ROUND(M120/$D120*$C120,2)) -> 0 | O120: ='人员人工-研发人员工资'!O120 -> 0 | P120: =IF($D120=0,0,ROUND(O120/$D120*$C120,2)) -> 0 | Q120: ='人员人工-研发人员工资'!Q120 -> 0 | R120: =IF($D120=0,0,ROUND(Q120/$D120*$C120,2)) -> 0 | S120: ='人员人工-研发人员工资'!S120 -> 0 | T120: =IF($D120=0,0,ROUND(S120/$D120*$C120,2)) -> 0 | U120: ='人员人工-研发人员工资'!U120 -> 0 | V120: =IF($D120=0,0,ROUND(U120/$D120*$C120,2)) -> 0 | W120: ='人员人工-研发人员工资'!W120 -> 0 | X120: =IF($D120=0,0,ROUND(W120/$D120*$C120,2)) -> 0 | Y120: ='人员人工-研发人员工资'!Y120 -> 0 | Z120: =IF($D120=0,0,ROUND(Y120/$D120*$C120,2)) -> 0
A121: 3 | B121: ='人员人工-研发人员工资'!B121 -> 0 | D121: ='人员人工-研发人员工资'!D121 -> 0 | E121: =G121+I121+K121+M121+O121+Q121+S121+U121+W121+Y121 -> 0 | F121: =H121+J121+L121+N121+P121+R121+T121+V121+X121+Z121 -> 0 | G121: ='人员人工-研发人员工资'!G121 -> 0 | H121: =IF($D121=0,0,ROUND(G121/$D121*$C121,2)) -> 0 | I121: ='人员人工-研发人员工资'!I121 -> 0 | J121: =IF($D121=0,0,ROUND(I121/$D121*$C121,2)) -> 0 | K121: ='人员人工-研发人员工资'!K121 -> 0 | L121: =IF($D121=0,0,ROUND(K121/$D121*$C121,2)) -> 0 | M121: ='人员人工-研发人员工资'!M121 -> 0 | N121: =IF($D121=0,0,ROUND(M121/$D121*$C121,2)) -> 0 | O121: ='人员人工-研发人员工资'!O121 -> 0 | P121: =IF($D121=0,0,ROUND(O121/$D121*$C121,2)) -> 0 | Q121: ='人员人工-研发人员工资'!Q121 -> 0 | R121: =IF($D121=0,0,ROUND(Q121/$D121*$C121,2)) -> 0 | S121: ='人员人工-研发人员工资'!S121 -> 0 | T121: =IF($D121=0,0,ROUND(S121/$D121*$C121,2)) -> 0 | U121: ='人员人工-研发人员工资'!U121 -> 0 | V121: =IF($D121=0,0,ROUND(U121/$D121*$C121,2)) -> 0 | W121: ='人员人工-研发人员工资'!W121 -> 0 | X121: =IF($D121=0,0,ROUND(W121/$D121*$C121,2)) -> 0 | Y121: ='人员人工-研发人员工资'!Y121 -> 0 | Z121: =IF($D121=0,0,ROUND(Y121/$D121*$C121,2)) -> 0
A122: 4 | B122: ='人员人工-研发人员工资'!B122 -> 0 | D122: ='人员人工-研发人员工资'!D122 -> 0 | E122: =G122+I122+K122+M122+O122+Q122+S122+U122+W122+Y122 -> 0 | F122: =H122+J122+L122+N122+P122+R122+T122+V122+X122+Z122 -> 0 | G122: ='人员人工-研发人员工资'!G122 -> 0 | H122: =IF($D122=0,0,ROUND(G122/$D122*$C122,2)) -> 0 | I122: ='人员人工-研发人员工资'!I122 -> 0 | J122: =IF($D122=0,0,ROUND(I122/$D122*$C122,2)) -> 0 | K122: ='人员人工-研发人员工资'!K122 -> 0 | L122: =IF($D122=0,0,ROUND(K122/$D122*$C122,2)) -> 0 | M122: ='人员人工-研发人员工资'!M122 -> 0 | N122: =IF($D122=0,0,ROUND(M122/$D122*$C122,2)) -> 0 | O122: ='人员人工-研发人员工资'!O122 -> 0 | P122: =IF($D122=0,0,ROUND(O122/$D122*$C122,2)) -> 0 | Q122: ='人员人工-研发人员工资'!Q122 -> 0 | R122: =IF($D122=0,0,ROUND(Q122/$D122*$C122,2)) -> 0 | S122: ='人员人工-研发人员工资'!S122 -> 0 | T122: =IF($D122=0,0,ROUND(S122/$D122*$C122,2)) -> 0 | U122: ='人员人工-研发人员工资'!U122 -> 0 | V122: =IF($D122=0,0,ROUND(U122/$D122*$C122,2)) -> 0 | W122: ='人员人工-研发人员工资'!W122 -> 0 | X122: =IF($D122=0,0,ROUND(W122/$D122*$C122,2)) -> 0 | Y122: ='人员人工-研发人员工资'!Y122 -> 0 | Z122: =IF($D122=0,0,ROUND(Y122/$D122*$C122,2)) -> 0
A123: 5 | B123: ='人员人工-研发人员工资'!B123 -> 0 | D123: ='人员人工-研发人员工资'!D123 -> 0 | E123: =G123+I123+K123+M123+O123+Q123+S123+U123+W123+Y123 -> 0 | F123: =H123+J123+L123+N123+P123+R123+T123+V123+X123+Z123 -> 0 | G123: ='人员人工-研发人员工资'!G123 -> 0 | H123: =IF($D123=0,0,ROUND(G123/$D123*$C123,2)) -> 0 | I123: ='人员人工-研发人员工资'!I123 -> 0 | J123: =IF($D123=0,0,ROUND(I123/$D123*$C123,2)) -> 0 | K123: ='人员人工-研发人员工资'!K123 -> 0 | L123: =IF($D123=0,0,ROUND(K123/$D123*$C123,2)) -> 0 | M123: ='人员人工-研发人员工资'!M123 -> 0 | N123: =IF($D123=0,0,ROUND(M123/$D123*$C123,2)) -> 0 | O123: ='人员人工-研发人员工资'!O123 -> 0 | P123: =IF($D123=0,0,ROUND(O123/$D123*$C123,2)) -> 0 | Q123: ='人员人工-研发人员工资'!Q123 -> 0 | R123: =IF($D123=0,0,ROUND(Q123/$D123*$C123,2)) -> 0 | S123: ='人员人工-研发人员工资'!S123 -> 0 | T123: =IF($D123=0,0,ROUND(S123/$D123*$C123,2)) -> 0 | U123: ='人员人工-研发人员工资'!U123 -> 0 | V123: =IF($D123=0,0,ROUND(U123/$D123*$C123,2)) -> 0 | W123: ='人员人工-研发人员工资'!W123 -> 0 | X123: =IF($D123=0,0,ROUND(W123/$D123*$C123,2)) -> 0 | Y123: ='人员人工-研发人员工资'!Y123 -> 0 | Z123: =IF($D123=0,0,ROUND(Y123/$D123*$C123,2)) -> 0
A124: 6 | B124: ='人员人工-研发人员工资'!B125 -> 0 | D124: ='人员人工-研发人员工资'!D124 -> 0 | E124: =G124+I124+K124+M124+O124+Q124+S124+U124+W124+Y124 -> 0 | F124: =H124+J124+L124+N124+P124+R124+T124+V124+X124+Z124 -> 0 | G124: ='人员人工-研发人员工资'!G125 -> 0 | H124: =IF($D124=0,0,ROUND(G124/$D124*$C124,2)) -> 0 | I124: ='人员人工-研发人员工资'!I125 -> 0 | J124: =IF($D124=0,0,ROUND(I124/$D124*$C124,2)) -> 0 | K124: ='人员人工-研发人员工资'!K125 -> 0 | L124: =IF($D124=0,0,ROUND(K124/$D124*$C124,2)) -> 0 | M124: ='人员人工-研发人员工资'!M125 -> 0 | N124: =IF($D124=0,0,ROUND(M124/$D124*$C124,2)) -> 0 | O124: ='人员人工-研发人员工资'!O125 -> 0 | P124: =IF($D124=0,0,ROUND(O124/$D124*$C124,2)) -> 0 | Q124: ='人员人工-研发人员工资'!Q125 -> 0 | R124: =IF($D124=0,0,ROUND(Q124/$D124*$C124,2)) -> 0 | S124: ='人员人工-研发人员工资'!S125 -> 0 | T124: =IF($D124=0,0,ROUND(S124/$D124*$C124,2)) -> 0 | U124: ='人员人工-研发人员工资'!U125 -> 0 | V124: =IF($D124=0,0,ROUND(U124/$D124*$C124,2)) -> 0 | W124: ='人员人工-研发人员工资'!W125 -> 0 | X124: =IF($D124=0,0,ROUND(W124/$D124*$C124,2)) -> 0 | Y124: ='人员人工-研发人员工资'!Y125 -> 0 | Z124: =IF($D124=0,0,ROUND(Y124/$D124*$C124,2)) -> 0
A125: 7 | B125: ='人员人工-研发人员工资'!B125 -> 0 | D125: ='人员人工-研发人员工资'!D125 -> 0 | E125: =G125+I125+K125+M125+O125+Q125+S125+U125+W125+Y125 -> 0 | F125: =H125+J125+L125+N125+P125+R125+T125+V125+X125+Z125 -> 0 | G125: ='人员人工-研发人员工资'!G125 -> 0 | H125: =IF($D125=0,0,ROUND(G125/$D125*$C125,2)) -> 0 | I125: ='人员人工-研发人员工资'!I125 -> 0 | J125: =IF($D125=0,0,ROUND(I125/$D125*$C125,2)) -> 0 | K125: ='人员人工-研发人员工资'!K125 -> 0 | L125: =IF($D125=0,0,ROUND(K125/$D125*$C125,2)) -> 0 | M125: ='人员人工-研发人员工资'!M125 -> 0 | N125: =IF($D125=0,0,ROUND(M125/$D125*$C125,2)) -> 0 | O125: ='人员人工-研发人员工资'!O125 -> 0 | P125: =IF($D125=0,0,ROUND(O125/$D125*$C125,2)) -> 0 | Q125: ='人员人工-研发人员工资'!Q125 -> 0 | R125: =IF($D125=0,0,ROUND(Q125/$D125*$C125,2)) -> 0 | S125: ='人员人工-研发人员工资'!S125 -> 0 | T125: =IF($D125=0,0,ROUND(S125/$D125*$C125,2)) -> 0 | U125: ='人员人工-研发人员工资'!U125 -> 0 | V125: =IF($D125=0,0,ROUND(U125/$D125*$C125,2)) -> 0 | W125: ='人员人工-研发人员工资'!W125 -> 0 | X125: =IF($D125=0,0,ROUND(W125/$D125*$C125,2)) -> 0 | Y125: ='人员人工-研发人员工资'!Y125 -> 0 | Z125: =IF($D125=0,0,ROUND(Y125/$D125*$C125,2)) -> 0
A126: 8 | B126: ='人员人工-研发人员工资'!B126 -> 0 | D126: ='人员人工-研发人员工资'!D126 -> 0 | E126: =G126+I126+K126+M126+O126+Q126+S126+U126+W126+Y126 -> 0 | F126: =H126+J126+L126+N126+P126+R126+T126+V126+X126+Z126 -> 0 | G126: ='人员人工-研发人员工资'!G126 -> 0 | H126: =IF($D126=0,0,ROUND(G126/$D126*$C126,2)) -> 0 | I126: ='人员人工-研发人员工资'!I126 -> 0 | J126: =IF($D126=0,0,ROUND(I126/$D126*$C126,2)) -> 0 | K126: ='人员人工-研发人员工资'!K126 -> 0 | L126: =IF($D126=0,0,ROUND(K126/$D126*$C126,2)) -> 0 | M126: ='人员人工-研发人员工资'!M126 -> 0 | N126: =IF($D126=0,0,ROUND(M126/$D126*$C126,2)) -> 0 | O126: ='人员人工-研发人员工资'!O126 -> 0 | P126: =IF($D126=0,0,ROUND(O126/$D126*$C126,2)) -> 0 | Q126: ='人员人工-研发人员工资'!Q126 -> 0 | R126: =IF($D126=0,0,ROUND(Q126/$D126*$C126,2)) -> 0 | S126: ='人员人工-研发人员工资'!S126 -> 0 | T126: =IF($D126=0,0,ROUND(S126/$D126*$C126,2)) -> 0 | U126: ='人员人工-研发人员工资'!U126 -> 0 | V126: =IF($D126=0,0,ROUND(U126/$D126*$C126,2)) -> 0 | W126: ='人员人工-研发人员工资'!W126 -> 0 | X126: =IF($D126=0,0,ROUND(W126/$D126*$C126,2)) -> 0 | Y126: ='人员人工-研发人员工资'!Y126 -> 0 | Z126: =IF($D126=0,0,ROUND(Y126/$D126*$C126,2)) -> 0
A127: 9 | B127: ='人员人工-研发人员工资'!B127 -> 0 | D127: ='人员人工-研发人员工资'!D127 -> 0 | E127: =G127+I127+K127+M127+O127+Q127+S127+U127+W127+Y127 -> 0 | F127: =H127+J127+L127+N127+P127+R127+T127+V127+X127+Z127 -> 0 | G127: ='人员人工-研发人员工资'!G127 -> 0 | H127: =IF($D127=0,0,ROUND(G127/$D127*$C127,2)) -> 0 | I127: ='人员人工-研发人员工资'!I127 -> 0 | J127: =IF($D127=0,0,ROUND(I127/$D127*$C127,2)) -> 0 | K127: ='人员人工-研发人员工资'!K127 -> 0 | L127: =IF($D127=0,0,ROUND(K127/$D127*$C127,2)) -> 0 | M127: ='人员人工-研发人员工资'!M127 -> 0 | N127: =IF($D127=0,0,ROUND(M127/$D127*$C127,2)) -> 0 | O127: ='人员人工-研发人员工资'!O127 -> 0 | P127: =IF($D127=0,0,ROUND(O127/$D127*$C127,2)) -> 0 | Q127: ='人员人工-研发人员工资'!Q127 -> 0 | R127: =IF($D127=0,0,ROUND(Q127/$D127*$C127,2)) -> 0 | S127: ='人员人工-研发人员工资'!S127 -> 0 | T127: =IF($D127=0,0,ROUND(S127/$D127*$C127,2)) -> 0 | U127: ='人员人工-研发人员工资'!U127 -> 0 | V127: =IF($D127=0,0,ROUND(U127/$D127*$C127,2)) -> 0 | W127: ='人员人工-研发人员工资'!W127 -> 0 | X127: =IF($D127=0,0,ROUND(W127/$D127*$C127,2)) -> 0 | Y127: ='人员人工-研发人员工资'!Y127 -> 0 | Z127: =IF($D127=0,0,ROUND(Y127/$D127*$C127,2)) -> 0
A128: 10 | B128: ='人员人工-研发人员工资'!B128 -> 0 | D128: ='人员人工-研发人员工资'!D128 -> 0 | E128: =G128+I128+K128+M128+O128+Q128+S128+U128+W128+Y128 -> 0 | F128: =H128+J128+L128+N128+P128+R128+T128+V128+X128+Z128 -> 0 | G128: ='人员人工-研发人员工资'!G128 -> 0 | H128: =IF($D128=0,0,ROUND(G128/$D128*$C128,2)) -> 0 | I128: ='人员人工-研发人员工资'!I128 -> 0 | J128: =IF($D128=0,0,ROUND(I128/$D128*$C128,2)) -> 0 | K128: ='人员人工-研发人员工资'!K128 -> 0 | L128: =IF($D128=0,0,ROUND(K128/$D128*$C128,2)) -> 0 | M128: ='人员人工-研发人员工资'!M128 -> 0 | N128: =IF($D128=0,0,ROUND(M128/$D128*$C128,2)) -> 0 | O128: ='人员人工-研发人员工资'!O128 -> 0 | P128: =IF($D128=0,0,ROUND(O128/$D128*$C128,2)) -> 0 | Q128: ='人员人工-研发人员工资'!Q128 -> 0 | R128: =IF($D128=0,0,ROUND(Q128/$D128*$C128,2)) -> 0 | S128: ='人员人工-研发人员工资'!S128 -> 0 | T128: =IF($D128=0,0,ROUND(S128/$D128*$C128,2)) -> 0 | U128: ='人员人工-研发人员工资'!U128 -> 0 | V128: =IF($D128=0,0,ROUND(U128/$D128*$C128,2)) -> 0 | W128: ='人员人工-研发人员工资'!W128 -> 0 | X128: =IF($D128=0,0,ROUND(W128/$D128*$C128,2)) -> 0 | Y128: ='人员人工-研发人员工资'!Y128 -> 0 | Z128: =IF($D128=0,0,ROUND(Y128/$D128*$C128,2)) -> 0
A129: 11 | B129: ='人员人工-研发人员工资'!B129 -> 0 | D129: ='人员人工-研发人员工资'!D129 -> 0 | E129: =G129+I129+K129+M129+O129+Q129+S129+U129+W129+Y129 -> 0 | F129: =H129+J129+L129+N129+P129+R129+T129+V129+X129+Z129 -> 0 | G129: ='人员人工-研发人员工资'!G129 -> 0 | H129: =IF($D129=0,0,ROUND(G129/$D129*$C129,2)) -> 0 | I129: ='人员人工-研发人员工资'!I129 -> 0 | J129: =IF($D129=0,0,ROUND(I129/$D129*$C129,2)) -> 0 | K129: ='人员人工-研发人员工资'!K129 -> 0 | L129: =IF($D129=0,0,ROUND(K129/$D129*$C129,2)) -> 0 | M129: ='人员人工-研发人员工资'!M129 -> 0 | N129: =IF($D129=0,0,ROUND(M129/$D129*$C129,2)) -> 0 | O129: ='人员人工-研发人员工资'!O129 -> 0 | P129: =IF($D129=0,0,ROUND(O129/$D129*$C129,2)) -> 0 | Q129: ='人员人工-研发人员工资'!Q129 -> 0 | R129: =IF($D129=0,0,ROUND(Q129/$D129*$C129,2)) -> 0 | S129: ='人员人工-研发人员工资'!S129 -> 0 | T129: =IF($D129=0,0,ROUND(S129/$D129*$C129,2)) -> 0 | U129: ='人员人工-研发人员工资'!U129 -> 0 | V129: =IF($D129=0,0,ROUND(U129/$D129*$C129,2)) -> 0 | W129: ='人员人工-研发人员工资'!W129 -> 0 | X129: =IF($D129=0,0,ROUND(W129/$D129*$C129,2)) -> 0 | Y129: ='人员人工-研发人员工资'!Y129 -> 0 | Z129: =IF($D129=0,0,ROUND(Y129/$D129*$C129,2)) -> 0
A130: 12 | B130: ='人员人工-研发人员工资'!B130 -> 0 | D130: ='人员人工-研发人员工资'!D130 -> 0 | E130: =G130+I130+K130+M130+O130+Q130+S130+U130+W130+Y130 -> 0 | F130: =H130+J130+L130+N130+P130+R130+T130+V130+X130+Z130 -> 0 | G130: ='人员人工-研发人员工资'!G130 -> 0 | H130: =IF($D130=0,0,ROUND(G130/$D130*$C130,2)) -> 0 | I130: ='人员人工-研发人员工资'!I130 -> 0 | J130: =IF($D130=0,0,ROUND(I130/$D130*$C130,2)) -> 0 | K130: ='人员人工-研发人员工资'!K130 -> 0 | L130: =IF($D130=0,0,ROUND(K130/$D130*$C130,2)) -> 0 | M130: ='人员人工-研发人员工资'!M130 -> 0 | N130: =IF($D130=0,0,ROUND(M130/$D130*$C130,2)) -> 0 | O130: ='人员人工-研发人员工资'!O130 -> 0 | P130: =IF($D130=0,0,ROUND(O130/$D130*$C130,2)) -> 0 | Q130: ='人员人工-研发人员工资'!Q130 -> 0 | R130: =IF($D130=0,0,ROUND(Q130/$D130*$C130,2)) -> 0 | S130: ='人员人工-研发人员工资'!S130 -> 0 | T130: =IF($D130=0,0,ROUND(S130/$D130*$C130,2)) -> 0 | U130: ='人员人工-研发人员工资'!U130 -> 0 | V130: =IF($D130=0,0,ROUND(U130/$D130*$C130,2)) -> 0 | W130: ='人员人工-研发人员工资'!W130 -> 0 | X130: =IF($D130=0,0,ROUND(W130/$D130*$C130,2)) -> 0 | Y130: ='人员人工-研发人员工资'!Y130 -> 0 | Z130: =IF($D130=0,0,ROUND(Y130/$D130*$C130,2)) -> 0
A131: 13 | B131: ='人员人工-研发人员工资'!B131 -> 0 | D131: ='人员人工-研发人员工资'!D131 -> 0 | E131: =G131+I131+K131+M131+O131+Q131+S131+U131+W131+Y131 -> 0 | F131: =H131+J131+L131+N131+P131+R131+T131+V131+X131+Z131 -> 0 | G131: ='人员人工-研发人员工资'!G131 -> 0 | H131: =IF($D131=0,0,ROUND(G131/$D131*$C131,2)) -> 0 | I131: ='人员人工-研发人员工资'!I131 -> 0 | J131: =IF($D131=0,0,ROUND(I131/$D131*$C131,2)) -> 0 | K131: ='人员人工-研发人员工资'!K131 -> 0 | L131: =IF($D131=0,0,ROUND(K131/$D131*$C131,2)) -> 0 | M131: ='人员人工-研发人员工资'!M131 -> 0 | N131: =IF($D131=0,0,ROUND(M131/$D131*$C131,2)) -> 0 | O131: ='人员人工-研发人员工资'!O131 -> 0 | P131: =IF($D131=0,0,ROUND(O131/$D131*$C131,2)) -> 0 | Q131: ='人员人工-研发人员工资'!Q131 -> 0 | R131: =IF($D131=0,0,ROUND(Q131/$D131*$C131,2)) -> 0 | S131: ='人员人工-研发人员工资'!S131 -> 0 | T131: =IF($D131=0,0,ROUND(S131/$D131*$C131,2)) -> 0 | U131: ='人员人工-研发人员工资'!U131 -> 0 | V131: =IF($D131=0,0,ROUND(U131/$D131*$C131,2)) -> 0 | W131: ='人员人工-研发人员工资'!W131 -> 0 | X131: =IF($D131=0,0,ROUND(W131/$D131*$C131,2)) -> 0 | Y131: ='人员人工-研发人员工资'!Y131 -> 0 | Z131: =IF($D131=0,0,ROUND(Y131/$D131*$C131,2)) -> 0
A132: 14 | B132: ='人员人工-研发人员工资'!B132 -> 0 | D132: ='人员人工-研发人员工资'!D132 -> 0 | E132: =G132+I132+K132+M132+O132+Q132+S132+U132+W132+Y132 -> 0 | F132: =H132+J132+L132+N132+P132+R132+T132+V132+X132+Z132 -> 0 | G132: ='人员人工-研发人员工资'!G132 -> 0 | H132: =IF($D132=0,0,ROUND(G132/$D132*$C132,2)) -> 0 | I132: ='人员人工-研发人员工资'!I132 -> 0 | J132: =IF($D132=0,0,ROUND(I132/$D132*$C132,2)) -> 0 | K132: ='人员人工-研发人员工资'!K132 -> 0 | L132: =IF($D132=0,0,ROUND(K132/$D132*$C132,2)) -> 0 | M132: ='人员人工-研发人员工资'!M132 -> 0 | N132: =IF($D132=0,0,ROUND(M132/$D132*$C132,2)) -> 0 | O132: ='人员人工-研发人员工资'!O132 -> 0 | P132: =IF($D132=0,0,ROUND(O132/$D132*$C132,2)) -> 0 | Q132: ='人员人工-研发人员工资'!Q132 -> 0 | R132: =IF($D132=0,0,ROUND(Q132/$D132*$C132,2)) -> 0 | S132: ='人员人工-研发人员工资'!S132 -> 0 | T132: =IF($D132=0,0,ROUND(S132/$D132*$C132,2)) -> 0 | U132: ='人员人工-研发人员工资'!U132 -> 0 | V132: =IF($D132=0,0,ROUND(U132/$D132*$C132,2)) -> 0 | W132: ='人员人工-研发人员工资'!W132 -> 0 | X132: =IF($D132=0,0,ROUND(W132/$D132*$C132,2)) -> 0 | Y132: ='人员人工-研发人员工资'!Y132 -> 0 | Z132: =IF($D132=0,0,ROUND(Y132/$D132*$C132,2)) -> 0
A133: 15 | B133: ='人员人工-研发人员工资'!B133 -> 0 | D133: ='人员人工-研发人员工资'!D133 -> 0 | E133: =G133+I133+K133+M133+O133+Q133+S133+U133+W133+Y133 -> 0 | F133: =H133+J133+L133+N133+P133+R133+T133+V133+X133+Z133 -> 0 | G133: ='人员人工-研发人员工资'!G133 -> 0 | H133: =IF($D133=0,0,ROUND(G133/$D133*$C133,2)) -> 0 | I133: ='人员人工-研发人员工资'!I133 -> 0 | J133: =IF($D133=0,0,ROUND(I133/$D133*$C133,2)) -> 0 | K133: ='人员人工-研发人员工资'!K133 -> 0 | L133: =IF($D133=0,0,ROUND(K133/$D133*$C133,2)) -> 0 | M133: ='人员人工-研发人员工资'!M133 -> 0 | N133: =IF($D133=0,0,ROUND(M133/$D133*$C133,2)) -> 0 | O133: ='人员人工-研发人员工资'!O133 -> 0 | P133: =IF($D133=0,0,ROUND(O133/$D133*$C133,2)) -> 0 | Q133: ='人员人工-研发人员工资'!Q133 -> 0 | R133: =IF($D133=0,0,ROUND(Q133/$D133*$C133,2)) -> 0 | S133: ='人员人工-研发人员工资'!S133 -> 0 | T133: =IF($D133=0,0,ROUND(S133/$D133*$C133,2)) -> 0 | U133: ='人员人工-研发人员工资'!U133 -> 0 | V133: =IF($D133=0,0,ROUND(U133/$D133*$C133,2)) -> 0 | W133: ='人员人工-研发人员工资'!W133 -> 0 | X133: =IF($D133=0,0,ROUND(W133/$D133*$C133,2)) -> 0 | Y133: ='人员人工-研发人员工资'!Y133 -> 0 | Z133: =IF($D133=0,0,ROUND(Y133/$D133*$C133,2)) -> 0
A134: 16 | B134: ='人员人工-研发人员工资'!B134 -> 0 | D134: ='人员人工-研发人员工资'!D134 -> 0 | E134: =G134+I134+K134+M134+O134+Q134+S134+U134+W134+Y134 -> 0 | F134: =H134+J134+L134+N134+P134+R134+T134+V134+X134+Z134 -> 0 | G134: ='人员人工-研发人员工资'!G134 -> 0 | H134: =IF($D134=0,0,ROUND(G134/$D134*$C134,2)) -> 0 | I134: ='人员人工-研发人员工资'!I134 -> 0 | J134: =IF($D134=0,0,ROUND(I134/$D134*$C134,2)) -> 0 | K134: ='人员人工-研发人员工资'!K134 -> 0 | L134: =IF($D134=0,0,ROUND(K134/$D134*$C134,2)) -> 0 | M134: ='人员人工-研发人员工资'!M134 -> 0 | N134: =IF($D134=0,0,ROUND(M134/$D134*$C134,2)) -> 0 | O134: ='人员人工-研发人员工资'!O134 -> 0 | P134: =IF($D134=0,0,ROUND(O134/$D134*$C134,2)) -> 0 | Q134: ='人员人工-研发人员工资'!Q134 -> 0 | R134: =IF($D134=0,0,ROUND(Q134/$D134*$C134,2)) -> 0 | S134: ='人员人工-研发人员工资'!S134 -> 0 | T134: =IF($D134=0,0,ROUND(S134/$D134*$C134,2)) -> 0 | U134: ='人员人工-研发人员工资'!U134 -> 0 | V134: =IF($D134=0,0,ROUND(U134/$D134*$C134,2)) -> 0 | W134: ='人员人工-研发人员工资'!W134 -> 0 | X134: =IF($D134=0,0,ROUND(W134/$D134*$C134,2)) -> 0 | Y134: ='人员人工-研发人员工资'!Y134 -> 0 | Z134: =IF($D134=0,0,ROUND(Y134/$D134*$C134,2)) -> 0
A135: 17 | B135: ='人员人工-研发人员工资'!B135 -> 0 | D135: ='人员人工-研发人员工资'!D135 -> 0 | E135: =G135+I135+K135+M135+O135+Q135+S135+U135+W135+Y135 -> 0 | F135: =H135+J135+L135+N135+P135+R135+T135+V135+X135+Z135 -> 0 | G135: ='人员人工-研发人员工资'!G135 -> 0 | H135: =IF($D135=0,0,ROUND(G135/$D135*$C135,2)) -> 0 | I135: ='人员人工-研发人员工资'!I135 -> 0 | J135: =IF($D135=0,0,ROUND(I135/$D135*$C135,2)) -> 0 | K135: ='人员人工-研发人员工资'!K135 -> 0 | L135: =IF($D135=0,0,ROUND(K135/$D135*$C135,2)) -> 0 | M135: ='人员人工-研发人员工资'!M135 -> 0 | N135: =IF($D135=0,0,ROUND(M135/$D135*$C135,2)) -> 0 | O135: ='人员人工-研发人员工资'!O135 -> 0 | P135: =IF($D135=0,0,ROUND(O135/$D135*$C135,2)) -> 0 | Q135: ='人员人工-研发人员工资'!Q135 -> 0 | R135: =IF($D135=0,0,ROUND(Q135/$D135*$C135,2)) -> 0 | S135: ='人员人工-研发人员工资'!S135 -> 0 | T135: =IF($D135=0,0,ROUND(S135/$D135*$C135,2)) -> 0 | U135: ='人员人工-研发人员工资'!U135 -> 0 | V135: =IF($D135=0,0,ROUND(U135/$D135*$C135,2)) -> 0 | W135: ='人员人工-研发人员工资'!W135 -> 0 | X135: =IF($D135=0,0,ROUND(W135/$D135*$C135,2)) -> 0 | Y135: ='人员人工-研发人员工资'!Y135 -> 0 | Z135: =IF($D135=0,0,ROUND(Y135/$D135*$C135,2)) -> 0
A136: 18 | B136: ='人员人工-研发人员工资'!B136 -> 0 | D136: ='人员人工-研发人员工资'!D136 -> 0 | E136: =G136+I136+K136+M136+O136+Q136+S136+U136+W136+Y136 -> 0 | F136: =H136+J136+L136+N136+P136+R136+T136+V136+X136+Z136 -> 0 | G136: ='人员人工-研发人员工资'!G136 -> 0 | H136: =IF($D136=0,0,ROUND(G136/$D136*$C136,2)) -> 0 | I136: ='人员人工-研发人员工资'!I136 -> 0 | J136: =IF($D136=0,0,ROUND(I136/$D136*$C136,2)) -> 0 | K136: ='人员人工-研发人员工资'!K136 -> 0 | L136: =IF($D136=0,0,ROUND(K136/$D136*$C136,2)) -> 0 | M136: ='人员人工-研发人员工资'!M136 -> 0 | N136: =IF($D136=0,0,ROUND(M136/$D136*$C136,2)) -> 0 | O136: ='人员人工-研发人员工资'!O136 -> 0 | P136: =IF($D136=0,0,ROUND(O136/$D136*$C136,2)) -> 0 | Q136: ='人员人工-研发人员工资'!Q136 -> 0 | R136: =IF($D136=0,0,ROUND(Q136/$D136*$C136,2)) -> 0 | S136: ='人员人工-研发人员工资'!S136 -> 0 | T136: =IF($D136=0,0,ROUND(S136/$D136*$C136,2)) -> 0 | U136: ='人员人工-研发人员工资'!U136 -> 0 | V136: =IF($D136=0,0,ROUND(U136/$D136*$C136,2)) -> 0 | W136: ='人员人工-研发人员工资'!W136 -> 0 | X136: =IF($D136=0,0,ROUND(W136/$D136*$C136,2)) -> 0 | Y136: ='人员人工-研发人员工资'!Y136 -> 0 | Z136: =IF($D136=0,0,ROUND(Y136/$D136*$C136,2)) -> 0
... A148: 30 | B148: ='人员人工-研发人员工资'!B148 -> 0 | D148: ='人员人工-研发人员工资'!D148 -> 0 | E148: =G148+I148+K148+M148+O148+Q148+S148+U148+W148+Y148 -> 0 | F148: =H148+J148+L148+N148+P148+R148+T148+V148+X148+Z148 -> 0 | G148: ='人员人工-研发人员工资'!G148 -> 0 | H148: =IF($D148=0,0,ROUND(G148/$D148*$C148,2)) -> 0 | I148: ='人员人工-研发人员工资'!I148 -> 0 | J148: =IF($D148=0,0,ROUND(I148/$D148*$C148,2)) -> 0 | K148: ='人员人工-研发人员工资'!K148 -> 0 | L148: =IF($D148=0,0,ROUND(K148/$D148*$C148,2)) -> 0 | M148: ='人员人工-研发人员工资'!M148 -> 0 | N148: =IF($D148=0,0,ROUND(M148/$D148*$C148,2)) -> 0 | O148: ='人员人工-研发人员工资'!O148 -> 0 | P148: =IF($D148=0,0,ROUND(O148/$D148*$C148,2)) -> 0 | Q148: ='人员人工-研发人员工资'!Q148 -> 0 | R148: =IF($D148=0,0,ROUND(Q148/$D148*$C148,2)) -> 0 | S148: ='人员人工-研发人员工资'!S148 -> 0 | T148: =IF($D148=0,0,ROUND(S148/$D148*$C148,2)) -> 0 | U148: ='人员人工-研发人员工资'!U148 -> 0 | V148: =IF($D148=0,0,ROUND(U148/$D148*$C148,2)) -> 0 | W148: ='人员人工-研发人员工资'!W148 -> 0 | X148: =IF($D148=0,0,ROUND(W148/$D148*$C148,2)) -> 0 | Y148: ='人员人工-研发人员工资'!Y148 -> 0 | Z148: =IF($D148=0,0,ROUND(Y148/$D148*$C148,2)) -> 0
A149: 合计 | C149: =SUM(C119:C148) -> 0 | D149: =SUM(D119:D148) -> 0 | E149: =SUM(E119:E148) -> 0 | F149: =SUM(F119:F148) -> 0 | G149: =SUM(G119:G148) -> 0 | H149: =SUM(H119:H148) -> 0 | I149: =SUM(I119:I148) -> 0 | J149: =SUM(J119:J148) -> 0 | ... Z149: =SUM(Z119:Z148) -> 0
B152: 2025年5月份研发人员社保项目分摊表
A154: 序号 | B154: 姓名 | C154: 月社保 | D154: 出勤天数 | E154: 研发天数合计 | F154: 研发社保合计 | G154: =立项!$A$3 -> RD01 | I154: =立项!$A$4 -> RD02 | K154: =立项!$A$5 -> RD03 | M154: =立项!$A$6 -> RD04 | O154: =立项!$A$7 -> RD05 | Q154: =立项!$A$8 -> RD06 | S154: =立项!$A$9 -> RD07 | U154: =立项!$A$10 -> RD08 | W154: =立项!$A$11 -> RD09 | Y154: =立项!$A$12 -> RD10
G155: =立项!C3 -> 0 | I155: =立项!C4 -> 0 | K155: =立项!C5 -> 0 | M155: =立项!C6 -> 0 | O155: =立项!C7 -> 0 | Q155: =立项!C8 -> 0 | S155: =立项!C9 -> 0 | U155: =立项!C10 -> 0 | W155: =立项!C11 -> 0 | Y155: =立项!C12 -> 0
G156: 研发天数 | H156: 研发社保 | I156: 研发天数 | J156: 研发社保 | K156: 研发天数 | L156: 研发社保 | M156: 研发天数 | N156: 研发社保 | O156: 研发天数 | P156: 研发社保 | Q156: 研发天数 | R156: 研发社保 | S156: 研发天数 | T156: 研发社保 | U156: 研发天数 | V156: 研发社保 | W156: 研发天数 | X156: 研发社保 | Y156: 研发天数 | Z156: 研发社保
A157: 1 | B157: ='人员人工-研发人员工资'!B157 -> 0 | D157: ='人员人工-研发人员工资'!D157 -> 0 | E157: =G157+I157+K157+M157+O157+Q157+S157+U157+W157+Y157 -> 0 | F157: =H157+J157+L157+N157+P157+R157+T157+V157+X157+Z157 -> 0 | G157: ='人员人工-研发人员工资'!G157 -> 0 | H157: =IF($D157=0,0,ROUND(G157/$D157*$C157,2)) -> 0 | I157: ='人员人工-研发人员工资'!I157 -> 0 | J157: =IF($D157=0,0,ROUND(I157/$D157*$C157,2)) -> 0 | K157: ='人员人工-研发人员工资'!K157 -> 0 | L157: =IF($D157=0,0,ROUND(K157/$D157*$C157,2)) -> 0 | M157: ='人员人工-研发人员工资'!M157 -> 0 | N157: =IF($D157=0,0,ROUND(M157/$D157*$C157,2)) -> 0 | O157: ='人员人工-研发人员工资'!O157 -> 0 | P157: =IF($D157=0,0,ROUND(O157/$D157*$C157,2)) -> 0 | Q157: ='人员人工-研发人员工资'!Q157 -> 0 | R157: =IF($D157=0,0,ROUND(Q157/$D157*$C157,2)) -> 0 | S157: ='人员人工-研发人员工资'!S157 -> 0 | T157: =IF($D157=0,0,ROUND(S157/$D157*$C157,2)) -> 0 | U157: ='人员人工-研发人员工资'!U157 -> 0 | V157: =IF($D157=0,0,ROUND(U157/$D157*$C157,2)) -> 0 | W157: ='人员人工-研发人员工资'!W157 -> 0 | X157: =IF($D157=0,0,ROUND(W157/$D157*$C157,2)) -> 0 | Y157: ='人员人工-研发人员工资'!Y157 -> 0 | Z157: =IF($D157=0,0,ROUND(Y157/$D157*$C157,2)) -> 0
A158: 2 | B158: ='人员人工-研发人员工资'!B158 -> 0 | D158: ='人员人工-研发人员工资'!D158 -> 0 | E158: =G158+I158+K158+M158+O158+Q158+S158+U158+W158+Y158 -> 0 | F158: =H158+J158+L158+N158+P158+R158+T158+V158+X158+Z158 -> 0 | G158: ='人员人工-研发人员工资'!G158 -> 0 | H158: =IF($D158=0,0,ROUND(G158/$D158*$C158,2)) -> 0 | I158: ='人员人工-研发人员工资'!I158 -> 0 | J158: =IF($D158=0,0,ROUND(I158/$D158*$C158,2)) -> 0 | K158: ='人员人工-研发人员工资'!K158 -> 0 | L158: =IF($D158=0,0,ROUND(K158/$D158*$C158,2)) -> 0 | M158: ='人员人工-研发人员工资'!M158 -> 0 | N158: =IF($D158=0,0,ROUND(M158/$D158*$C158,2)) -> 0 | O158: ='人员人工-研发人员工资'!O158 -> 0 | P158: =IF($D158=0,0,ROUND(O158/$D158*$C158,2)) -> 0 | Q158: ='人员人工-研发人员工资'!Q158 -> 0 | R158: =IF($D158=0,0,ROUND(Q158/$D158*$C158,2)) -> 0 | S158: ='人员人工-研发人员工资'!S158 -> 0 | T158: =IF($D158=0,0,ROUND(S158/$D158*$C158,2)) -> 0 | U158: ='人员人工-研发人员工资'!U158 -> 0 | V158: =IF($D158=0,0,ROUND(U158/$D158*$C158,2)) -> 0 | W158: ='人员人工-研发人员工资'!W158 -> 0 | X158: =IF($D158=0,0,ROUND(W158/$D158*$C158,2)) -> 0 | Y158: ='人员人工-研发人员工资'!Y158 -> 0 | Z158: =IF($D158=0,0,ROUND(Y158/$D158*$C158,2)) -> 0
A159: 3 | B159: ='人员人工-研发人员工资'!B159 -> 0 | D159: ='人员人工-研发人员工资'!D159 -> 0 | E159: =G159+I159+K159+M159+O159+Q159+S159+U159+W159+Y159 -> 0 | F159: =H159+J159+L159+N159+P159+R159+T159+V159+X159+Z159 -> 0 | G159: ='人员人工-研发人员工资'!G159 -> 0 | H159: =IF($D159=0,0,ROUND(G159/$D159*$C159,2)) -> 0 | I159: ='人员人工-研发人员工资'!I159 -> 0 | J159: =IF($D159=0,0,ROUND(I159/$D159*$C159,2)) -> 0 | K159: ='人员人工-研发人员工资'!K159 -> 0 | L159: =IF($D159=0,0,ROUND(K159/$D159*$C159,2)) -> 0 | M159: ='人员人工-研发人员工资'!M159 -> 0 | N159: =IF($D159=0,0,ROUND(M159/$D159*$C159,2)) -> 0 | O159: ='人员人工-研发人员工资'!O159 -> 0 | P159: =IF($D159=0,0,ROUND(O159/$D159*$C159,2)) -> 0 | Q159: ='人员人工-研发人员工资'!Q159 -> 0 | R159: =IF($D159=0,0,ROUND(Q159/$D159*$C159,2)) -> 0 | S159: ='人员人工-研发人员工资'!S159 -> 0 | T159: =IF($D159=0,0,ROUND(S159/$D159*$C159,2)) -> 0 | U159: ='人员人工-研发人员工资'!U159 -> 0 | V159: =IF($D159=0,0,ROUND(U159/$D159*$C159,2)) -> 0 | W159: ='人员人工-研发人员工资'!W159 -> 0 | X159: =IF($D159=0,0,ROUND(W159/$D159*$C159,2)) -> 0 | Y159: ='人员人工-研发人员工资'!Y159 -> 0 | Z159: =IF($D159=0,0,ROUND(Y159/$D159*$C159,2)) -> 0
A160: 4 | B160: ='人员人工-研发人员工资'!B160 -> 0 | D160: ='人员人工-研发人员工资'!D160 -> 0 | E160: =G160+I160+K160+M160+O160+Q160+S160+U160+W160+Y160 -> 0 | F160: =H160+J160+L160+N160+P160+R160+T160+V160+X160+Z160 -> 0 | G160: ='人员人工-研发人员工资'!G160 -> 0 | H160: =IF($D160=0,0,ROUND(G160/$D160*$C160,2)) -> 0 | I160: ='人员人工-研发人员工资'!I160 -> 0 | J160: =IF($D160=0,0,ROUND(I160/$D160*$C160,2)) -> 0 | K160: ='人员人工-研发人员工资'!K160 -> 0 | L160: =IF($D160=0,0,ROUND(K160/$D160*$C160,2)) -> 0 | M160: ='人员人工-研发人员工资'!M160 -> 0 | N160: =IF($D160=0,0,ROUND(M160/$D160*$C160,2)) -> 0 | O160: ='人员人工-研发人员工资'!O160 -> 0 | P160: =IF($D160=0,0,ROUND(O160/$D160*$C160,2)) -> 0 | Q160: ='人员人工-研发人员工资'!Q160 -> 0 | R160: =IF($D160=0,0,ROUND(Q160/$D160*$C160,2)) -> 0 | S160: ='人员人工-研发人员工资'!S160 -> 0 | T160: =IF($D160=0,0,ROUND(S160/$D160*$C160,2)) -> 0 | U160: ='人员人工-研发人员工资'!U160 -> 0 | V160: =IF($D160=0,0,ROUND(U160/$D160*$C160,2)) -> 0 | W160: ='人员人工-研发人员工资'!W160 -> 0 | X160: =IF($D160=0,0,ROUND(W160/$D160*$C160,2)) -> 0 | Y160: ='人员人工-研发人员工资'!Y160 -> 0 | Z160: =IF($D160=0,0,ROUND(Y160/$D160*$C160,2)) -> 0
A161: 5 | B161: ='人员人工-研发人员工资'!B161 -> 0 | D161: ='人员人工-研发人员工资'!D161 -> 0 | E161: =G161+I161+K161+M161+O161+Q161+S161+U161+W161+Y161 -> 0 | F161: =H161+J161+L161+N161+P161+R161+T161+V161+X161+Z161 -> 0 | G161: ='人员人工-研发人员工资'!G161 -> 0 | H161: =IF($D161=0,0,ROUND(G161/$D161*$C161,2)) -> 0 | I161: ='人员人工-研发人员工资'!I161 -> 0 | J161: =IF($D161=0,0,ROUND(I161/$D161*$C161,2)) -> 0 | K161: ='人员人工-研发人员工资'!K161 -> 0 | L161: =IF($D161=0,0,ROUND(K161/$D161*$C161,2)) -> 0 | M161: ='人员人工-研发人员工资'!M161 -> 0 | N161: =IF($D161=0,0,ROUND(M161/$D161*$C161,2)) -> 0 | O161: ='人员人工-研发人员工资'!O161 -> 0 | P161: =IF($D161=0,0,ROUND(O161/$D161*$C161,2)) -> 0 | Q161: ='人员人工-研发人员工资'!Q161 -> 0 | R161: =IF($D161=0,0,ROUND(Q161/$D161*$C161,2)) -> 0 | S161: ='人员人工-研发人员工资'!S161 -> 0 | T161: =IF($D161=0,0,ROUND(S161/$D161*$C161,2)) -> 0 | U161: ='人员人工-研发人员工资'!U161 -> 0 | V161: =IF($D161=0,0,ROUND(U161/$D161*$C161,2)) -> 0 | W161: ='人员人工-研发人员工资'!W161 -> 0 | X161: =IF($D161=0,0,ROUND(W161/$D161*$C161,2)) -> 0 | Y161: ='人员人工-研发人员工资'!Y161 -> 0 | Z161: =IF($D161=0,0,ROUND(Y161/$D161*$C161,2)) -> 0
A162: 6 | B162: ='人员人工-研发人员工资'!B162 -> 0 | D162: ='人员人工-研发人员工资'!D162 -> 0 | E162: =G162+I162+K162+M162+O162+Q162+S162+U162+W162+Y162 -> 0 | F162: =H162+J162+L162+N162+P162+R162+T162+V162+X162+Z162 -> 0 | G162: ='人员人工-研发人员工资'!G162 -> 0 | H162: =IF($D162=0,0,ROUND(G162/$D162*$C162,2)) -> 0 | I162: ='人员人工-研发人员工资'!I162 -> 0 | J162: =IF($D162=0,0,ROUND(I162/$D162*$C162,2)) -> 0 | K162: ='人员人工-研发人员工资'!K162 -> 0 | L162: =IF($D162=0,0,ROUND(K162/$D162*$C162,2)) -> 0 | M162: ='人员人工-研发人员工资'!M162 -> 0 | N162: =IF($D162=0,0,ROUND(M162/$D162*$C162,2)) -> 0 | O162: ='人员人工-研发人员工资'!O162 -> 0 | P162: =IF($D162=0,0,ROUND(O162/$D162*$C162,2)) -> 0 | Q162: ='人员人工-研发人员工资'!Q162 -> 0 | R162: =IF($D162=0,0,ROUND(Q162/$D162*$C162,2)) -> 0 | S162: ='人员人工-研发人员工资'!S162 -> 0 | T162: =IF($D162=0,0,ROUND(S162/$D162*$C162,2)) -> 0 | U162: ='人员人工-研发人员工资'!U162 -> 0 | V162: =IF($D162=0,0,ROUND(U162/$D162*$C162,2)) -> 0 | W162: ='人员人工-研发人员工资'!W162 -> 0 | X162: =IF($D162=0,0,ROUND(W162/$D162*$C162,2)) -> 0 | Y162: ='人员人工-研发人员工资'!Y162 -> 0 | Z162: =IF($D162=0,0,ROUND(Y162/$D162*$C162,2)) -> 0
...

Sheet 人员人工-研发人员公积金
B1: 2025年1月份研发人员公积金项目分摊表
